include/alucodes.sv
//-----------------------------------------------------
// File Name : alucodes.sv
// Function : pMIPS ALU function code definitions
// Author: tjk
// Last rev. 23 Oct 12
//-----------------------------------------------------
//
`ifndef ALUCODES_V
`define ALUCODES_V

`define RA 3'b000
`define RB 3'b001
`define RADD 3'b010
`define RSUB 3'b011
`define RAND 3'b100
`define ROR 3'b101
`define RXOR 3'b110
`define RNOR 3'b111

`endif

rtl/picoMIPS/ALU.sv
//-----------------------------------------------------
// File Name   : alu.sv
// Function    : ALU module for picoMIPS
//-----------------------------------------------------

`include "alucodes.sv"  
module ALU #(
    parameter int BUS_WIDTH = 8,
    parameter int FUNC_WIDTH = 3,
    parameter int FLAG_WIDTH = 3
) (
    input logic [BUS_WIDTH-1:0] a, b, // ALU operands
    input logic [FUNC_WIDTH-1:0] func, // ALU function code
    output logic [FLAG_WIDTH-1:0] flags, // ALU flags V,N,Z
    output logic [BUS_WIDTH-1:0] result // ALU result
);       

// create an BUS_WIDTH-bit adder 
// and then build the ALU around the adder
logic[BUS_WIDTH-1:0] ar, b1; 
always_comb
begin
    if(func == `RSUB)
        b1 = ~b + 1'b1; // 2's complement subtrahend
    else 
        b1 = b;

    ar = a + b1; // BUS_WIDTH-bit adder
end 
   
// create the ALU, use signal ar in arithmetic operations
always_comb
begin
    flags = '0;
    result = a; // default
    case(func)
        `RA    : result = a;
        `RB    : result = b;
        `RADD  : begin
            result = ar; // arithmetic addition
            flags[2] = a[7] & b[7] & ~result[7] | ~a[7] & ~b[7] & result[7]; // V
        end
        `RSUB  : begin
            result = ar; // arithmetic subtraction
            flags[2] = ~a[7] & b[7] & result[7] | a[7] & ~b[7] & ~result[7]; // V       
        end   
        `RAND  : result = a & b;
        `ROR   : result = a | b;
        `RXOR  : result = a ^ b;
        `RNOR  : result = ~ (a | b);
        default : result = a;

    endcase
    // calculate flags Z and N
    flags[1] = result[BUS_WIDTH-1];         // N
    flags[0] = result == {BUS_WIDTH{1'b0}}; // Z
end 

endmodule

rtl/picoMIPS/Register_File.sv
//-----------------------------------------------------
// File Name : regs.sv
// Function : picoMIPS 32 x n registers, %0 == 0
//-----------------------------------------------------

// BUS_WIDTH - data bus width 
// ADDR_WIDTH - data bus width 
module Register_File #(
	parameter int BUS_WIDTH = 8,
	parameter int ADDR_WIDTH = 5
) (
	input logic clk, we, // clk and write control
 	input logic [BUS_WIDTH-1:0] wr_data,
 	input logic [ADDR_WIDTH-1:0] rd_addr, rs_addr,
 	output logic [BUS_WIDTH-1:0] rd_data, rs_data
);

// 5 bit address -> 1 << 5 = 2^5 = 32 registers
parameter N = (1 << ADDR_WIDTH);

// Declare 32 n-bit registers 
logic [BUS_WIDTH-1:0] gpr [N-1:0];

// specify initial conditions
integer i;
initial 
begin
	for (i = 0; i < N; i = i + 1)
		gpr[i] = '0;
end

// write process, dest reg is rd_addr_2
always_ff @ (posedge clk)
begin
	if (we)
		gpr[rd_addr] <= wr_data;
end

// read process, output 0 if %0 is selected
always_comb
begin
	if (rd_addr == '0)
		rd_data = {BUS_WIDTH{1'b0}};
	else  
		rd_data = gpr[rd_addr];
end

always_comb
begin
	if (rs_addr == '0)
		rs_data = {BUS_WIDTH{1'b0}};
	else  
		rs_data = gpr[rs_addr];
end	


endmodule // module regs

include/opcodes.sv
//-----------------------------------------------------
// File Name : opcodes.sv
// Function : pMIPS instr opcode definitions
// Author: jf
//-----------------------------------------------------
//
`define NOP 6'b000000
`define ADD 6'b001010
`define SUB 6'b010011
`define ADDI 6'b011010
`define SUBI 6'b100011
`define BEQ 6'b101011
`define BNE 6'b110011
`define BGE 6'b111011

rtl/picoMIPS/Instruction_Decoder.sv
//---------------------------------------------------------
// File Name   : decoder.sv
// Function    : picoMIPS instruction decoder 
// Author: tjk
// ver 2:  // NOP, ADD, ADDI, and branches
// Last revised: 26 Oct 2012
//---------------------------------------------------------

`include "alucodes.sv"
`include "opcodes.sv"
//---------------------------------------------------------
module Instruction_Decoder #(
    parameter int OPCODE_WIDTH = 6,
    parameter int FUNC_WIDTH = 3,
    parameter int FLAG_WIDTH = 3
) ( 
    input logic [OPCODE_WIDTH-1:0] opcode,         // top 6 bits of instruction
    input logic [FLAG_WIDTH-1:0] flags,            // ALU flags
    output logic PC_incr, PC_abs_branch, PC_rel_branch, // PC control
    output logic [FUNC_WIDTH-1:0] ALU_func,         // ALU control
    output logic imm,                              // imm mux control
    output logic we                                // register file control
);
   
logic rel_branch; // temp variable to control conditional branching
always_comb 
begin
    // set default output signal values for NOP instruction
    PC_incr       = '1;
    PC_abs_branch = '0;
    PC_rel_branch = '0;
    ALU_func      = opcode[FUNC_WIDTH-1:0]; 
    imm           = '0;
    we            = '0; 
    rel_branch    = '0; 
    case(opcode)
        `NOP: ;
        // numeric
        `ADD,`SUB : begin 
            we  = '1; 
        end
        `ADDI,`SUBI: begin 
            we  = '1; 
            imm = '1; 
        end
        // relative branches
        `BEQ: rel_branch = flags[0];  // branch if Z==1
        `BNE: rel_branch = ~flags[0]; // branch if Z==0
        `BGE: rel_branch = ~flags[1]; // branch if N==0
    endcase 

    if(rel_branch)
    begin
        PC_incr = '0;
        PC_rel_branch = '1; 
    end

end 

endmodule

rtl/picoMIPS/Program_Memory.sv
//-----------------------------------------------------
// File Name : program_memory.sv
// Function : Program memory Psize x Isize - reads from file prog.hex
//-----------------------------------------------------

// psize - address width, Isize - instruction width
module Program_Memory #(
    parameter int ADDR_WIDTH = 6,
    parameter int INSTR_WIDTH = 24
) (
    input logic [ADDR_WIDTH-1:0] addr,
    output logic [INSTR_WIDTH-1:0] instr //  - instruction code I
); 

// program memory declaration, note: 1<<n is same as 2^n
logic [INSTR_WIDTH-1:0] progMem[(1<<ADDR_WIDTH)-1:0];

// get memory contents from file
initial
    $readmemh("../../programs/prog.hex", progMem);
  
// program memory read 
always_comb
    instr = progMem[addr]; 
  
endmodule

rtl/picoMIPS/Program_Counter.sv
//-----------------------------------------------------
// File Name : pc.sv
// Function : picoMIPS Program Counter
// functions: increment, absolute and relative branches
//-----------------------------------------------------

module Program_Counter #(
    parameter int ADDR_WIDTH = 6
) (
    input logic clk, reset, PC_incr, PC_abs_branch, PC_rel_branch,
    input logic [ADDR_WIDTH-1:0] branch_addr,
    output logic [ADDR_WIDTH-1:0] PC_out
);

logic[ADDR_WIDTH-1:0] r_branch; // temp variable for addition operand
always_comb
begin
    if (PC_incr)
        r_branch = { {(ADDR_WIDTH-1){1'b0}}, 1'b1};
    else 
        r_branch = branch_addr;
end

always_ff @ ( posedge clk or posedge reset) // async reset
begin
    if (reset)
        PC_out <= '0;
    else 
    begin 
        if (PC_incr | PC_rel_branch) // increment or relative branch
            PC_out <= PC_out + r_branch; 
        else if (PC_abs_branch) // absolute branch
            PC_out <= branch_addr;
    end
end
	 
endmodule // module pc

rtl/picoMIPS/CPU.sv
//------------------------------------
// File Name   : cpu.sv
// Function    : picoMIPS CPU top level encapsulating module
//------------------------------------

`include "alucodes.sv"
module CPU #(
    parameter int INSTR_WIDTH  = 24, // Width of an instruction
    parameter int OPCODE_WIDTH = 6,  // Width of each opcode in the instuction
    parameter int ADDR_WIDTH   = 5,  // Size of each memory address in the register file (# addresses = 2^ADDR_WIDTH)
    parameter int BUS_WIDTH    = 8,  // Data-path bus width (ALU operands size)
    parameter int FUNC_WIDTH   = 3,  // Width of the ALU function code
    parameter int FLAG_WIDTH   = 3   // Numer of ALU flags (V, N, Z)
) (
    input logic clk,  
    input logic reset,                    // master reset
    output logic [BUS_WIDTH-1:0] out_port // need an output port, tentatively this will be the ALU output
);       

//the "macro" to dump signals
`ifdef COCOTB_SIM
initial begin
    $dumpfile ("CPU.vcd");
    $dumpvars (0, CPU);
    #1;
end
`endif

// ALU
logic [FUNC_WIDTH-1:0] ALU_func; // ALU function
logic [FLAG_WIDTH-1:0] flags; // ALU flags, routed to decoder
logic imm; // immediate operand signal
logic [BUS_WIDTH-1:0] ALU_b; // output from imm MUX

// registers
logic [BUS_WIDTH-1:0] rd_data, rs_data, wr_data; 
logic we; 

// Program Counter 
logic PC_incr, PC_abs_branch, PC_rel_branch; 
logic [ADDR_WIDTH-1:0] prog_addr;

// Program Memory
logic [INSTR_WIDTH-1:0] instr;

Program_Counter #(
   .ADDR_WIDTH(ADDR_WIDTH)
) program_counter_0 (
   .clk(clk),
   .reset(reset),
   .PC_incr(PC_incr),
   .PC_abs_branch(PC_abs_branch),
   .PC_rel_branch(PC_rel_branch),
   .branch_addr(instr[ADDR_WIDTH-1:0]),
   .PC_out(prog_addr) 
);

Program_Memory #(
   .ADDR_WIDTH(ADDR_WIDTH),
   .INSTR_WIDTH(INSTR_WIDTH)
) program_memory_0 (
   .addr(prog_addr),
   .instr(instr)
);

parameter OPCODE_BEGIN = INSTR_WIDTH-1;
parameter OPCODE_END = OPCODE_BEGIN-(OPCODE_WIDTH-1);
Instruction_Decoder #(
   .OPCODE_WIDTH(OPCODE_WIDTH),
   .FUNC_WIDTH(FUNC_WIDTH),
   .FLAG_WIDTH(FLAG_WIDTH)
) instruction_decoder_0 (
   .opcode(instr[OPCODE_BEGIN:OPCODE_END]),
   .PC_incr(PC_incr),
   .PC_abs_branch(PC_abs_branch), 
   .PC_rel_branch(PC_rel_branch),
   .flags(flags), // ALU flags
   .ALU_func(ALU_func),
   .imm(imm),
   .we(we)
);

parameter RD_ADDR_BEGIN = OPCODE_END-1;
parameter RD_ADDR_END = RD_ADDR_BEGIN-(ADDR_WIDTH-1);
parameter RS_ADDR_BEGIN = RD_ADDR_END-1;
parameter RS_ADDR_END = RS_ADDR_BEGIN-(ADDR_WIDTH-1);
Register_File #(
   .BUS_WIDTH(BUS_WIDTH),
   .ADDR_WIDTH(ADDR_WIDTH)
) register_file_0 (
   .clk(clk),
   .we(we),
   .wr_data(wr_data),
   .rd_addr(instr[RD_ADDR_BEGIN:RD_ADDR_END]),  // reg %d number
   .rs_addr(instr[RS_ADDR_BEGIN:RS_ADDR_END]),  // reg %s number
   .rd_data(rd_data),
   .rs_data(rs_data)
);

// create MUX for immediate operand
assign ALU_b = (imm ? instr[BUS_WIDTH-1:0] : rs_data);

ALU #(
   .BUS_WIDTH(BUS_WIDTH),
   .FUNC_WIDTH(FUNC_WIDTH),
   .FLAG_WIDTH(FLAG_WIDTH)
) alu_0 (
   .a(rd_data),
   .b(ALU_b),
   .func(ALU_func),
   .flags(flags),
   .result(wr_data) // ALU result -> destination reg
); 

// connect ALU result to outport
assign out_port = wr_data;

endmodule

simulation/CPU_traces/CPU.vcd
$date
	Mon Mar  6 02:11:54 2023
$end
$version
	Icarus Verilog
$end
$timescale
	1ps
$end
$scope module CPU $end
$var wire 1 ! clk $end
$var wire 8 " out_port [7:0] $end
$var wire 1 # reset $end
$var wire 8 $ wr_data [7:0] $end
$var wire 1 % we $end
$var wire 8 & rs_data [7:0] $end
$var wire 8 ' rd_data [7:0] $end
$var wire 5 ( prog_addr [4:0] $end
$var wire 24 ) instr [23:0] $end
$var wire 1 * imm $end
$var wire 3 + flags [2:0] $end
$var wire 1 , PC_rel_branch $end
$var wire 1 - PC_incr $end
$var wire 1 . PC_abs_branch $end
$var wire 3 / ALU_func [2:0] $end
$var wire 8 0 ALU_b [7:0] $end
$scope module alu_0 $end
$var wire 8 1 b [7:0] $end
$var wire 3 2 func [2:0] $end
$var wire 8 3 a [7:0] $end
$var reg 8 4 ar [7:0] $end
$var reg 8 5 b1 [7:0] $end
$var reg 3 6 flags [2:0] $end
$var reg 8 7 result [7:0] $end
$upscope $end
$scope module instruction_decoder_0 $end
$var wire 3 8 flags [2:0] $end
$var wire 6 9 opcode [5:0] $end
$var reg 3 : ALU_func [2:0] $end
$var reg 1 . PC_abs_branch $end
$var reg 1 - PC_incr $end
$var reg 1 , PC_rel_branch $end
$var reg 1 * imm $end
$var reg 1 ; rel_branch $end
$var reg 1 % we $end
$upscope $end
$scope module program_counter_0 $end
$var wire 1 . PC_abs_branch $end
$var wire 1 - PC_incr $end
$var wire 1 , PC_rel_branch $end
$var wire 5 < branch_addr [4:0] $end
$var wire 1 ! clk $end
$var wire 1 # reset $end
$var reg 5 = PC_out [4:0] $end
$var reg 5 > r_branch [4:0] $end
$upscope $end
$scope module program_memory_0 $end
$var wire 5 ? addr [4:0] $end
$var reg 24 @ instr [23:0] $end
$upscope $end
$scope module register_file_0 $end
$var wire 1 ! clk $end
$var wire 5 A rd_addr [4:0] $end
$var wire 5 B rs_addr [4:0] $end
$var wire 1 % we $end
$var wire 8 C wr_data [7:0] $end
$var reg 8 D rd_data [7:0] $end
$var reg 8 E rs_data [7:0] $end
$var integer 32 F i [31:0] $end
$upscope $end
$upscope $end
$enddefinitions $end
#0
$dumpvars
b100000 F
b0 E
b0 D
b0 C
b0 B
b0 A
b0 @
b0 ?
b1 >
b0 =
b0 <
0;
b0 :
b0 9
b1 8
b0 7
b1 6
b0 5
b0 4
b0 3
b0 2
b0 1
b0 0
b0 /
0.
1-
0,
b1 +
0*
b0 )
b0 (
b0 '
b0 &
0%
b0 $
1#
b0 "
1!
$end
#5000
0!
#10000
1!
#15000
0!
#20000
0#
1!
#25000
0!
#30000
b11 "
b11 $
b11 7
b11 C
b11 4
b11 5
b11 0
b11 1
b0 +
b0 6
b0 8
1*
1%
b10 /
b10 2
b10 :
b1 A
b11010 9
b11 <
b11010000010000000000011 )
b11010000010000000000011 @
b1 (
b1 =
b1 ?
1!
#35000
0!
#40000
1%
1*
b1 +
b1 6
b1 8
b0 5
b0 0
b0 1
b10 A
b0 <
b0 "
b0 $
b0 7
b0 C
b0 4
b11010000100000000000000 )
b11010000100000000000000 @
b0 '
b0 3
b0 D
b10 (
b10 =
b10 ?
1!
#45000
0!
#50000
1%
1*
b1 "
b1 $
b1 7
b1 C
b0 +
b0 6
b0 8
b1 4
b1 5
b1 0
b1 1
b10 B
b1 <
b11010000100001000000001 )
b11010000100001000000001 @
b11 (
b11 =
b11 ?
1!
#55000
0!
#60000
b1 +
b1 6
b1 8
b11111101 5
b11 0
b11 1
1%
1*
b11 /
b11 2
b11 :
b1 B
b1 A
b100011 9
b11 <
b0 "
b0 $
b0 7
b0 C
b0 4
b100011000010000100000011 )
b100011000010000100000011 @
b11 &
b11 E
b11 '
b11 3
b11 D
b100 (
b100 =
b100 ?
1!
#65000
0!
#70000
b0 5
b0 0
b0 1
b1 >
0,
1-
0;
0%
0*
b0 B
b110011 9
b11110 <
b0 "
b0 $
b0 7
b0 C
b1 +
b1 6
b1 8
b0 4
b110011000010000011111110 )
b110011000010000011111110 @
b0 &
b0 E
b0 '
b0 3
b0 D
b101 (
b101 =
b101 ?
1!
#75000
0!
#80000
b1 5
b1 0
b1 1
b10 "
b10 $
b10 7
b10 C
b0 +
b0 6
b0 8
b10 4
b1 &
b1 E
b1 '
b1 3
b1 D
1%
b10 /
b10 2
b10 :
b10 B
b10 A
b1010 9
b0 <
b1010000100001000000000 )
b1010000100001000000000 @
b110 (
b110 =
b110 ?
1!
#85000
0!
#90000
b10 5
b10 0
b10 1
b100 "
b100 $
b100 7
b100 C
b100 4
b10 &
b10 E
b10 '
b10 3
b10 D
b111 (
b111 =
b111 ?
1!
#95000
0!
#100000
b1 +
b1 6
b1 8
0%
b0 /
b0 2
b0 :
b0 5
b0 B
b0 A
b0 9
b0 0
b0 1
b0 "
b0 $
b0 7
b0 C
b0 4
b0 )
b0 @
b0 &
b0 E
b0 '
b0 3
b0 D
b1000 (
b1000 =
b1000 ?
1!
#105000
0!
#110000
b1001 (
b1001 =
b1001 ?
1!
#115000
0!
#120000
bx 5
bx 0
bx 1
bx "
bx $
bx 7
bx C
b0xx +
b0xx 6
b0xx 8
bx 4
bx &
bx E
bx '
bx 3
bx D
bx /
bx 2
bx :
bx B
bx A
bx 9
bx <
bx )
bx @
b1010 (
b1010 =
b1010 ?
1!
#125000
0!
#130000
b1011 (
b1011 =
b1011 ?
1!
