rtl/v6/mux_21.sv
module mux_21 #(
    parameter BIT_WIDTH = 8
) (   
    input  logic s, 
    input  logic [BIT_WIDTH-1:0] a, b,
    output logic [BIT_WIDTH-1:0] out
);
    `ifdef COCOTB_SIM
    initial begin
        $dumpfile ("mux_21.vcd");
        $dumpvars (0, mux_21);
        #1;
    end
    `endif 
    assign out = s ? a : b;
endmodule

rtl/v7/sfixed_adder.sv
import datatypes::max;

module sfixed_adder #(
    parameter A_LEFT    = 3, 
    parameter A_RIGHT   = 4, 
    parameter B_LEFT    = 3, 
    parameter B_RIGHT   = 4,
    parameter OUT_LEFT  = 4, 
    parameter OUT_RIGHT = 4
) (   
    input  logic signed [(A_LEFT+A_RIGHT+1)-1:0]     a,
    input  logic signed [(B_LEFT+B_RIGHT+1)-1:0]     b,
    output logic signed [(OUT_LEFT+OUT_RIGHT+1)-1:0] out
);

`ifdef COCOTB_SIM
initial begin
    $dumpfile ("sfixed_adder.vcd");
    $dumpvars (0, sfixed_adder);
    #1;
end
`endif

localparam OUTPUT_SIZE = (max(A_LEFT,B_LEFT)+1)+max(A_RIGHT,B_RIGHT)+1; 

logic signed [OUTPUT_SIZE-1:0] add_out;

always_comb
    add_out = a + b;

assign out = add_out[max(A_RIGHT,B_RIGHT)+OUT_LEFT:max(A_RIGHT,B_RIGHT)-OUT_RIGHT];

endmodule

rtl/v7/sfixed_mult.sv
module sfixed_mult #(
    parameter A_LEFT    = 3, 
    parameter A_RIGHT   = 4,
    parameter B_LEFT    = 3, 
    parameter B_RIGHT   = 4,
    parameter OUT_LEFT  = 7, 
    parameter OUT_RIGHT = 8
) (
    input  logic signed [(A_LEFT+A_RIGHT+1)-1:0]     a,
    input  logic signed [(B_LEFT+B_RIGHT+1)-1:0]     b,
    output logic signed [(OUT_LEFT+OUT_RIGHT+1)-1:0] out
);
`ifdef COCOTB_SIM
initial begin
    $dumpfile ("sfixed_mult.vcd");
    $dumpvars (0, sfixed_mult);
    #1;
end
`endif

localparam OUTPUT_SIZE = (A_LEFT+B_LEFT+1)+(A_RIGHT+B_RIGHT)+1; 
                                                                
logic signed [OUTPUT_SIZE-1:0] mult_out;

always_comb
    mult_out = a * b;

assign out = mult_out[(A_RIGHT+B_RIGHT)+OUT_LEFT:(A_RIGHT+B_RIGHT)-OUT_RIGHT];

endmodule

rtl/v7/ALU.sv
module ALU #(
    parameter BUS_WIDTH  = 8
) (
    input  logic [BUS_WIDTH-1:0] imm,
    input  logic [BUS_WIDTH-1:0] data_a,    
    input  logic [BUS_WIDTH-1:0] data_b,    
    input  logic                 f_imm,
    input  logic                 f_add,
    output logic [BUS_WIDTH-1:0] result 
);       

// setting up of add/subtract inputs
logic [BUS_WIDTH-1:0] op_e, e_add, coeff;
logic [BUS_WIDTH-1:0] op_a_reg, op_b_reg, op_c_reg, op_d_reg, op_e_reg;
logic [BUS_WIDTH-1:0] b_mux_out;

mux_21 #(
    BUS_WIDTH
) b_mux (   
    .s  (f_imm    ), 
    .a  (imm      ), 
    .b  (data_b   ),
    .out(b_mux_out)
);

// the computational part
logic [BUS_WIDTH-1:0] mult_out, add_out;

sfixed_mult #(
    7, 
    0,
    0, 
    7,
    7,
    0 
) m0 (
    .a  (data_a   ), // int
    .b  (b_mux_out), // tf
    .out(mult_out )
);

sfixed_adder #(
    7, 
    0, 
    7, 
    0,
    7, 
    0
) a0 ( 
    .a  (data_a   ), // int
    .b  (b_mux_out), // int
    .out(add_out  )
);

mux_21 #(
    BUS_WIDTH
) output_mux (   
    .s  (f_add   ), 
    .a  (add_out ), 
    .b  (mult_out),
    .out(result  )
);

endmodule

include/opcodes.sv
//-----------------------------------------------------
// File Name : opcodes.sv
// Function : pMIPS instr opcode definitions
// Author: jf
//-----------------------------------------------------
//
`define NOP  6'b000000
`define ADD  6'b000001
`define SUB  6'b000010
`define ADDI 6'b000011
`define SUBI 6'b000100
`define BEQ  6'b000101
`define BNE  6'b000110
`define BGE  6'b000111
`define BLO  6'b001000

rtl/v7/instruction_decoder.sv
`include "opcodes.sv"

module instruction_decoder #(
    parameter OPCODE_WIDTH = 3
) (
    input  logic [OPCODE_WIDTH-1:0] opcode,                  
    output logic                    f_add,            
    output logic                    f_imm,       
    output logic                    f_wait,      
    output logic                    f_load,      
    output logic                    f_wr_res
);

always_comb 
begin
    case(opcode)    
        `ADD: begin
            f_add      = '1;
            f_imm      = '0;
            f_wait     = '0;
            f_load     = '0;
            f_wr_res   = '1;
        end
        `ADDI: begin
            f_add      = '1;
            f_imm      = '1;
            f_wait     = '0;
            f_load     = '0;
            f_wr_res   = '1;
        end
        `MUL: begin
            f_add      = '0;
            f_imm      = '0;
            f_wait     = '0;
            f_load     = '0;
            f_wr_res   = '1;
        end
        `MULI: begin
            f_add      = '0;
            f_imm      = '1;
            f_wait     = '0;
            f_load     = '0;
            f_wr_res   = '1;
        end
        `WAIT: begin
            f_add      = '0;
            f_imm      = '0;
            f_wait     = '1;
            f_load     = '0;
            f_wr_res   = '0;
        end
        `LDSW: begin
            f_add      = '0;
            f_imm      = '0;
            f_wait     = '0;
            f_load     = '1;
            f_wr_res   = '1;
        end
        default : begin
            f_add      = '0;
            f_imm      = '0;
            f_wait     = '0;
            f_load     = '0;
            f_wr_res   = '0;
        end
    endcase 
end 

endmodule

rtl/v3/register_file.sv
module register_file #(
    parameter BUS_WIDTH  = 8,
    parameter ADDR_WIDTH = 3
) (
	input  logic                  clk, 
	input  logic                  we,
 	input  logic [ADDR_WIDTH-1:0] wr_addr,
	input  logic [BUS_WIDTH-1:0]  wr_data,
 	input  logic [ADDR_WIDTH-1:0] rd_addr_a, rd_addr_b,
 	output logic [BUS_WIDTH-1:0]  rd_data_a, rd_data_b
);

localparam N = (1 << ADDR_WIDTH);

logic [BUS_WIDTH-1:0] gpr [N-1:0];

initial begin
	for (int i = 0; i < N; i = i + 1)
		gpr[i] = '0;
end

// syncrhonous RAM write
always_ff @ (posedge clk)
begin
	if (we) begin 
		gpr[wr_addr] <= wr_data;
	end
	rd_data_b <= gpr[rd_addr_b];
	rd_data_a <= gpr[rd_addr_a];
end	
	

endmodule

rtl/v7/program_memory.sv
module program_memory #(
    parameter ADDR_WIDTH  = 4,
    parameter INSTR_WIDTH = 12
) (
    input  logic [ADDR_WIDTH-1:0]  addr,
    output logic [INSTR_WIDTH-1:0] instr
); 

(* ramstyle = "mlab" *) logic [INSTR_WIDTH-1:0] prog_mem [(1<<ADDR_WIDTH)-1:0];

initial
    $readmemh("/home/jonahfoley/ELEC6234/a_fine_CPU/programs/prog_4.hex", prog_mem);
   
always_comb
    instr = prog_mem[addr]; 
  
endmodule

rtl/v3/program_counter.sv
module program_counter #(
    parameter ADDR_WIDTH = 3
) (
    input  logic                  clk, n_reset,
    input  logic                  en,
    output logic [ADDR_WIDTH-1:0] count
);
 
always_ff @(posedge clk, negedge n_reset) 
begin   
    if (~n_reset) 
        count <= '0;
    else begin
        if (count == (2<<ADDR_WIDTH)-1) 
            count <= '0;
        else begin
            if (en)
                count <= count + { {ADDR_WIDTH-1{1'b0}}, 1'b1 };
        end
    end
end


endmodule

rtl/v7/CPU.sv
module CPU #(
    parameter INSTR_WIDTH      = 16,
    parameter OPCODE_WIDTH     = 3,
    parameter INSTR_ADDR_WIDTH = 4, 
    parameter REG_ADDR_WIDTH   = 2, 
    parameter BUS_WIDTH        = 8
) (
    input  logic                 clk,  
    input  logic                 n_reset,
    input  logic [BUS_WIDTH-1:0] in_port,
    input  logic                 ready_in,
    output logic [BUS_WIDTH-1:0] out_port
);       

//the macro to dump signals   
`ifdef COCOTB_SIM
initial begin
    $dumpfile ("CPU.vcd");
    $dumpvars (0, CPU);
    #1;
end
`endif

// input switch handshaking
logic ready_in_p, pattern_match;
always_ff @(posedge clk)
    ready_in_p <= ready_in;

logic [BUS_WIDTH-1:0] sw;
always_ff @(posedge clk)
    sw <= in_port;

assign pattern_match = (~ready_in_p & ready_in);

// -- instr counter
logic [INSTR_ADDR_WIDTH-1:0] PC_count;
logic PC_en, PC_comparator;

mux_21 #(
    1
) PC_en_mux (
    .s  (instr[1]     ), // differentiate between instr[1] == 1 (pattern) / 0 (rdy)
    .a  (pattern_match), // 1 -> pattern
    .b  (ready_in     ), // 0 -> ready in 
    .out(PC_comparator)
);

assign PC_en = ~(f_wait & (PC_comparator ^ instr[0]));

program_counter #(
   INSTR_ADDR_WIDTH
) pc (
   .clk    (clk     ),
   .n_reset(n_reset ),
   .en     (PC_en   ),
   .count  (PC_count)
);

// -- program ROM
logic [INSTR_WIDTH-1:0] instr;

program_memory #(
    INSTR_ADDR_WIDTH,
    INSTR_WIDTH
) pm (
    .addr (PC_count),
    .instr(instr   )
);

// -- reg file
logic  we, wr_sw;
logic [REG_ADDR_WIDTH-1:0] wr_addr;
logic [BUS_WIDTH-1:0] rd_data_a, rd_data_b;
logic [BUS_WIDTH-1:0] wr_data;

always_ff @(posedge clk) 
begin
    wr_sw   <= f_load;
    we      <= f_wr_res;
    wr_addr <= instr[11:10];
end

mux_21 #(
    BUS_WIDTH
) wr_data_mux (
    .s  (wr_sw     ),
    .a  (sw        ),
    .b  (ALU_result),
    .out(wr_data   )
);

register_file #(
    BUS_WIDTH,
    4
) rf (
	.clk      (clk       ),  
    .we       (we        ),
 	.wr_addr  (wr_addr   ),
	.wr_data  (wr_data   ),
 	.rd_addr_a(instr[9:8]), 
    .rd_addr_b(instr[7:6]),
 	.rd_data_a(rd_data_a ), 
    .rd_data_b(rd_data_b )
);

// -- decoder
logic f_add, f_imm, f_load, f_wait, f_wr_res;
logic [4:0] reg_en; 

instruction_decoder #(
    OPCODE_WIDTH
) id (
    .opcode    (instr[14:12]),                  
    .f_add     (f_add       ), 
    .f_imm     (f_imm       ),
    .f_wait    (f_wait      ),            
    .f_load    (f_load      ),            
    .f_wr_res  (f_wr_res    )
);

// -- ALU
logic [BUS_WIDTH-1:0] ALU_result;
logic [BUS_WIDTH-1:0] ALU_immd;
logic                 ALU_add, ALU_imm;

always_ff @(posedge clk) begin
    ALU_immd   <= instr[7:0];
    ALU_imm    <= f_imm;
    ALU_add    <= f_add;
end

ALU #(
    BUS_WIDTH
) alu0 (
    .imm   (ALU_immd  ),
    .data_a(rd_data_a ),    
    .data_b(rd_data_b ),    
    .f_imm (ALU_imm   ),
    .f_add (ALU_add   ),
    .result(ALU_result) 
);  

assign out_port = ALU_result;

endmodule

simulation/v7/CPU/mux_21.vcd
$date
	Sun Apr 23 22:17:01 2023
$end
$version
	Icarus Verilog
$end
$timescale
	1ps
$end
$scope module CPU $end
$scope module PC_en_mux $end
$var wire 1 ! a $end
$var wire 1 " b $end
$var wire 1 # s $end
$var wire 1 $ out $end
$upscope $end
$upscope $end
$scope module CPU $end
$scope module wr_data_mux $end
$var wire 8 % a [7:0] $end
$var wire 8 & b [7:0] $end
$var wire 1 ' s $end
$var wire 8 ( out [7:0] $end
$upscope $end
$upscope $end
$scope module CPU $end
$scope module alu0 $end
$scope module b_mux $end
$var wire 8 ) a [7:0] $end
$var wire 1 * s $end
$var wire 8 + out [7:0] $end
$var wire 8 , b [7:0] $end
$upscope $end
$upscope $end
$upscope $end
$scope module CPU $end
$scope module alu0 $end
$scope module m0 $end
$var wire 8 - b [7:0] $end
$var wire 8 . out [7:0] $end
$var wire 8 / a [7:0] $end
$var reg 16 0 mult_out [15:0] $end
$upscope $end
$upscope $end
$upscope $end
$scope module CPU $end
$scope module alu0 $end
$scope module a0 $end
$var wire 8 1 out [7:0] $end
$var wire 8 2 b [7:0] $end
$var wire 8 3 a [7:0] $end
$var reg 9 4 add_out [8:0] $end
$upscope $end
$upscope $end
$upscope $end
$scope module CPU $end
$scope module alu0 $end
$scope module output_mux $end
$var wire 8 5 a [7:0] $end
$var wire 8 6 b [7:0] $end
$var wire 1 7 s $end
$var wire 8 8 out [7:0] $end
$upscope $end
$upscope $end
$upscope $end
$scope module CPU $end
$var wire 1 9 PC_en $end
$var wire 1 : clk $end
$var wire 8 ; in_port [7:0] $end
$var wire 1 < n_reset $end
$var wire 8 = out_port [7:0] $end
$var wire 1 ! pattern_match $end
$var wire 1 " ready_in $end
$var wire 8 > wr_data [7:0] $end
$var wire 8 ? rd_data_b [7:0] $end
$var wire 8 @ rd_data_a [7:0] $end
$var wire 16 A instr [15:0] $end
$var wire 1 B f_wr_res $end
$var wire 1 C f_wait $end
$var wire 1 D f_load $end
$var wire 1 E f_imm $end
$var wire 1 F f_add $end
$var wire 4 G PC_count [3:0] $end
$var wire 1 $ PC_comparator $end
$var wire 8 H ALU_result [7:0] $end
$var reg 1 7 ALU_add $end
$var reg 1 * ALU_imm $end
$var reg 8 I ALU_immd [7:0] $end
$var reg 1 J ready_in_p $end
$var reg 8 K sw [7:0] $end
$var reg 1 L we $end
$var reg 2 M wr_addr [1:0] $end
$var reg 1 ' wr_sw $end
$scope module PC_en_mux $end
$upscope $end
$scope module alu0 $end
$var wire 1 7 f_add $end
$var wire 1 * f_imm $end
$var wire 8 N imm [7:0] $end
$var wire 8 O result [7:0] $end
$var wire 8 P mult_out [7:0] $end
$var wire 8 Q data_b [7:0] $end
$var wire 8 R data_a [7:0] $end
$var wire 8 S b_mux_out [7:0] $end
$var wire 8 T add_out [7:0] $end
$scope module a0 $end
$upscope $end
$scope module b_mux $end
$upscope $end
$scope module m0 $end
$upscope $end
$scope module output_mux $end
$upscope $end
$upscope $end
$scope module id $end
$var wire 3 U opcode [2:0] $end
$var reg 1 F f_add $end
$var reg 1 E f_imm $end
$var reg 1 D f_load $end
$var reg 1 C f_wait $end
$var reg 1 B f_wr_res $end
$upscope $end
$scope module pc $end
$var wire 1 : clk $end
$var wire 1 9 en $end
$var wire 1 < n_reset $end
$var reg 4 V count [3:0] $end
$upscope $end
$scope module pm $end
$var wire 4 W addr [3:0] $end
$var reg 16 X instr [15:0] $end
$upscope $end
$scope module rf $end
$var wire 1 : clk $end
$var wire 2 Y rd_addr_a [1:0] $end
$var wire 2 Z rd_addr_b [1:0] $end
$var wire 1 L we $end
$var wire 2 [ wr_addr [1:0] $end
$var wire 8 \ wr_data [7:0] $end
$var wire 8 ] rd_data_b [7:0] $end
$var wire 8 ^ rd_data_a [7:0] $end
$scope module sr0 $end
$var wire 1 : clk $end
$var wire 2 _ rd_addr_a [1:0] $end
$var wire 2 ` rd_addr_b [1:0] $end
$var wire 1 L we $end
$var wire 2 a wr_addr [1:0] $end
$var wire 8 b wr_data [7:0] $end
$var reg 8 c rd_data_a [7:0] $end
$var reg 8 d rd_data_b [7:0] $end
$scope begin $ivl_for_loop0 $end
$var integer 32 e i [31:0] $end
$upscope $end
$upscope $end
$upscope $end
$scope module wr_data_mux $end
$upscope $end
$upscope $end
$enddefinitions $end
#0
$dumpvars
b100 e
bx d
bx c
bx b
bx a
b0 `
b0 _
bx ^
bx ]
bx \
bx [
b0 Z
b0 Y
b101000000000011 X
b0 W
b0 V
b101 U
bx T
bx S
bx R
bx Q
bx P
bx O
bx N
bx M
0L
b0 K
0J
bx I
bx H
b0 G
0F
0E
0D
1C
0B
b101000000000011 A
bx @
bx ?
bx >
bx =
0<
b0 ;
1:
09
bx 8
07
bx 6
bx 5
bx 4
bx 3
bx 2
bx 1
bx 0
bx /
bx .
bx -
bx ,
bx +
0*
bx )
bx (
0'
bx &
b0 %
0$
1#
0"
0!
$end
#5000
0:
#10000
b0 (
b0 >
b0 \
b0 b
b0 =
b0 &
b0 8
b0 H
b0 O
b0 .
b0 6
b0 P
b0 1
b0 5
b0 T
b0 0
b0 4
b0 +
b0 -
b0 2
b0 S
b11 )
b11 I
b11 N
b0 M
b0 [
b0 a
b0 /
b0 3
b0 @
b0 R
b0 ^
b0 c
b0 ,
b0 ?
b0 Q
b0 ]
b0 d
1:
#15000
0:
#20000
1<
1:
#25000
0:
#30000
1:
#35000
0:
#40000
1:
#45000
0:
#50000
1:
#55000
0:
#60000
1:
#65000
0:
#70000
1:
#75000
0:
#80000
1:
#85000
0:
#90000
1:
#95000
0:
#100000
1:
#105000
0:
#110000
1:
#115000
0:
#120000
19
1$
1!
1"
b10100110 ;
1:
#125000
0:
#130000
0$
0"
1B
1D
0C
b110 U
0#
0!
b110000000000000 A
b110000000000000 X
b1 G
b1 V
b1 W
b10100110 %
b10100110 K
1J
1:
#135000
0:
#140000
09
0B
0D
1C
b101 U
1#
b101000000000011 A
b101000000000011 X
b10100110 (
b10100110 >
b10100110 \
b10100110 b
b10 G
b10 V
b10 W
0J
1L
1'
b0 )
b0 I
b0 N
1:
#145000
0:
#150000
b111111 =
b111111 &
b111111 8
b111111 H
b111111 O
b111111 .
b111111 6
b111111 P
b1001100 1
b1001100 5
b1001100 T
b111111 (
b111111 >
b111111 \
b111111 b
b1111110100100 0
b101001100 4
b10100110 +
b10100110 -
b10100110 2
b10100110 S
b11 )
b11 I
b11 N
0L
0'
b10100110 /
b10100110 3
b10100110 @
b10100110 R
b10100110 ^
b10100110 c
b10100110 ,
b10100110 ?
b10100110 Q
b10100110 ]
b10100110 d
1:
#155000
0:
#160000
1:
#165000
0:
#170000
1:
#175000
0:
#180000
1:
#185000
0:
#190000
19
1$
1!
1"
b11110 ;
1:
#195000
0:
#200000
0$
0"
1B
1D
0C
b110 U
0#
0!
b110010000000000 A
b110010000000000 X
b11 G
b11 V
b11 W
1J
b11110 %
b11110 K
1:
#205000
0:
#210000
0D
1E
b100 U
b1 Z
b1 `
b100100001100000 A
b100100001100000 X
b11110 (
b11110 >
b11110 \
b11110 b
b100 G
b100 V
b100 W
b0 )
b0 I
b0 N
b1 M
b1 [
b1 a
1L
1'
0J
1:
#215000
0:
#220000
b10111100 =
b10111100 &
b10111100 8
b10111100 H
b10111100 O
b10111100 .
b10111100 6
b10111100 P
b110 1
b110 5
b110 T
b1 Y
b1 _
b1101111001000000 0
b110 4
b100110101000000 A
b100110101000000 X
b10111100 (
b10111100 >
b10111100 \
b10111100 b
b1100000 +
b1100000 -
b1100000 2
b1100000 S
b101 G
b101 V
b101 W
b11110 ,
b11110 ?
b11110 Q
b11110 ]
b11110 d
b10 M
b10 [
b10 a
0'
1*
b1100000 )
b1100000 I
b1100000 N
1:
#225000
0:
#230000
b1111 (
b1111 >
b1111 \
b1111 b
b1111 =
b1111 &
b1111 8
b1111 H
b1111 O
0E
1F
b0 U
b10 Z
b10 `
b11 Y
b11 _
b1111 .
b1111 6
b1111 P
b1011110 1
b1011110 5
b1011110 T
b1000000 +
b1000000 -
b1000000 2
b1000000 S
b101110000000 A
b101110000000 X
b11110000000 0
b1011110 4
b110 G
b110 V
b110 W
b1000000 )
b1000000 I
b1000000 N
b11 M
b11 [
b11 a
b11110 /
b11110 3
b11110 @
b11110 R
b11110 ^
b11110 c
1:
#235000
0:
#240000
1E
b1 U
b0 Z
b0 `
b10 Y
b10 _
b11111000 .
b11111000 6
b11111000 P
b11001011 1
b11001011 5
b11001011 T
b11001011 (
b11001011 >
b11001011 \
b11001011 b
b1101000010100 A
b1101000010100 X
b1111110000000100 0
b111001011 4
b11001011 =
b11001011 &
b11001011 8
b11001011 H
b11001011 O
b10111100 +
b10111100 -
b10111100 2
b10111100 S
b111 G
b111 V
b111 W
b1111 /
b1111 3
b1111 @
b1111 R
b1111 ^
b1111 c
b10111100 ,
b10111100 ?
b10111100 Q
b10111100 ]
b10111100 d
b10 M
b10 [
b10 a
17
0*
b10000000 )
b10000000 I
b10000000 N
1:
#245000
0:
#250000
b11011111 (
b11011111 >
b11011111 \
b11011111 b
0F
b11011111 =
b11011111 &
b11011111 8
b11011111 H
b11011111 O
b100 U
b11 Z
b11 `
b0 Y
b0 _
b11110111 .
b11110111 6
b11110111 P
b11011111 1
b11011111 5
b11011111 T
b100000011000000 A
b100000011000000 X
b1111101111011100 0
b111011111 4
b10100 +
b10100 -
b10100 2
b10100 S
b1000 G
b1000 V
b1000 W
1*
b10100 )
b10100 I
b10100 N
b11001011 /
b11001011 3
b11001011 @
b11001011 R
b11001011 ^
b11001011 c
b10100110 ,
b10100110 ?
b10100110 Q
b10100110 ]
b10100110 d
1:
#255000
0:
#260000
b1 Z
b1 `
b1 Y
b1 _
b101101 .
b101101 6
b101101 P
b1100110 1
b1100110 5
b1100110 T
b101101 (
b101101 >
b101101 \
b101101 b
b100010101100000 A
b100010101100000 X
b1011010000000 0
b101100110 4
b101101 =
b101101 &
b101101 8
b101101 H
b101101 O
b11000000 +
b11000000 -
b11000000 2
b11000000 S
b1001 G
b1001 V
b1001 W
b10100110 /
b10100110 3
b10100110 @
b10100110 R
b10100110 ^
b10100110 c
b1111 ,
b1111 ?
b1111 Q
b1111 ]
b1111 d
b0 M
b0 [
b0 a
07
b11000000 )
b11000000 I
b11000000 N
1:
#265000
0:
#270000
b10110 (
b10110 >
b10110 \
b10110 b
b10110 =
b10110 &
b10110 8
b10110 H
b10110 O
0E
1F
b0 U
b0 Z
b0 `
b10110 .
b10110 6
b10110 P
b1111110 1
b1111110 5
b1111110 T
b1100000 +
b1100000 -
b1100000 2
b1100000 S
b100000000 A
b100000000 X
b101101000000 0
b1111110 4
b1010 G
b1010 V
b1010 W
b1100000 )
b1100000 I
b1100000 N
b1 M
b1 [
b1 a
b11110 /
b11110 3
b11110 @
b11110 R
b11110 ^
b11110 c
b11110 ,
b11110 ?
b11110 Q
b11110 ]
b11110 d
1:
#275000
0:
#280000
1E
b1 U
b11 Z
b11 `
b0 Y
b0 _
b111 .
b111 6
b111 P
b1000011 1
b1000011 5
b1000011 T
b1000011 (
b1000011 >
b1000011 \
b1000011 b
b1000011101100 A
b1000011101100 X
b1111011110 0
b1000011 4
b1000011 =
b1000011 &
b1000011 8
b1000011 H
b1000011 O
b101101 +
b101101 -
b101101 2
b101101 S
b1011 G
b1011 V
b1011 W
b10110 /
b10110 3
b10110 @
b10110 R
b10110 ^
b10110 c
b101101 ,
b101101 ?
b101101 Q
b101101 ]
b101101 d
b0 M
b0 [
b0 a
17
0*
b0 )
b0 I
b0 N
1:
#285000
0:
#290000
b101111 (
b101111 >
b101111 \
b101111 b
b101111 =
b101111 &
b101111 8
b101111 H
b101111 O
b0 Z
b0 `
b10 Y
b10 _
b11110101 .
b11110101 6
b11110101 P
b101111 1
b101111 5
b101111 T
b1101000000000 A
b1101000000000 X
b1111101011000100 0
b101111 4
b11101100 +
b11101100 -
b11101100 2
b11101100 S
b1100 G
b1100 V
b1100 W
1*
b11101100 )
b11101100 I
b11101100 N
b1000011 /
b1000011 3
b1000011 @
b1000011 R
b1000011 ^
b1000011 c
b1111 ,
b1111 ?
b1111 Q
b1111 ]
b1111 d
1:
#295000
0:
#300000
09
b11011111 (
b11011111 >
b11011111 \
b11011111 b
0B
1C
0E
0F
b11011111 =
b11011111 &
b11011111 8
b11011111 H
b11011111 O
b101 U
b0 Y
b0 _
b0 .
b0 6
b0 P
b11011111 1
b11011111 5
b11011111 T
b101000000000001 A
b101000000000001 X
b0 0
b111011111 4
b0 +
b0 -
b0 2
b0 S
b1101 G
b1101 V
b1101 W
b11011111 /
b11011111 3
b11011111 @
b11011111 R
b11011111 ^
b11011111 c
b101111 ,
b101111 ?
b101111 Q
b101111 ]
b101111 d
b10 M
b10 [
b10 a
b0 )
b0 I
b0 N
1:
#305000
0:
#310000
19
1!
1$
1"
b10001 .
b10001 6
b10001 P
b10001 (
b10001 >
b10001 \
b10001 b
b100010100001 0
b1011110 1
b1011110 5
b1011110 T
b10001 =
b10001 &
b10001 8
b10001 H
b10001 O
b101111 +
b101111 -
b101111 2
b101111 S
b1011110 4
07
0*
b1 )
b1 I
b1 N
b0 M
b0 [
b0 a
0L
b101111 /
b101111 3
b101111 @
b101111 R
b101111 ^
b101111 c
1:
#315000
0:
#320000
1B
0C
1E
1F
b1 U
0!
b1000000000000 A
b1000000000000 X
b1110 G
b1110 V
b1110 W
1J
1:
#325000
0:
#330000
09
0B
1C
0E
0F
b0 .
b0 6
b0 P
b101111 1
b101111 5
b101111 T
b101 U
b101111 (
b101111 >
b101111 \
b101111 b
b0 0
b101111 4
b101000000000000 A
b101000000000000 X
b101111 =
b101111 &
b101111 8
b101111 H
b101111 O
b0 +
b0 -
b0 2
b0 S
b1111 G
b1111 V
b1111 W
17
1*
b0 )
b0 I
b0 N
1L
1:
#335000
0:
#340000
19
0$
0"
b10001 .
b10001 6
b10001 P
b1011110 1
b1011110 5
b1011110 T
b10001 (
b10001 >
b10001 \
b10001 b
b100010100001 0
b1011110 4
b10001 =
b10001 &
b10001 8
b10001 H
b10001 O
b101111 +
b101111 -
b101111 2
b101111 S
0L
07
0*
1:
#345000
0:
#350000
09
1#
b101000000000011 A
b101000000000011 X
b0 G
b0 V
b0 W
0J
1:
#355000
0:
#360000
b11 )
b11 I
b11 N
1:
#365000
0:
#370000
1:
#375000
0:
#380000
1:
#385000
0:
#390000
19
1$
1!
1"
b10001 ;
1:
#395000
0:
#400000
0$
0"
1B
1D
0C
b110 U
0#
0!
b110000000000000 A
b110000000000000 X
b1 G
b1 V
b1 W
1J
b10001 %
b10001 K
1:
#405000
0:
#410000
09
0B
0D
1C
b101 U
1#
b101000000000011 A
b101000000000011 X
b10 G
b10 V
b10 W
b0 )
b0 I
b0 N
1L
1'
0J
1:
#415000
0:
#420000
b10 (
b10 >
b10 \
b10 b
b10 =
b10 &
b10 8
b10 H
b10 O
b10 .
b10 6
b10 P
b100010 1
b100010 5
b100010 T
b100100001 0
b100010 4
b10001 +
b10001 -
b10001 2
b10001 S
b10001 /
b10001 3
b10001 @
b10001 R
b10001 ^
b10001 c
b10001 ,
b10001 ?
b10001 Q
b10001 ]
b10001 d
0L
0'
b11 )
b11 I
b11 N
1:
#425000
0:
#430000
19
1$
1!
1"
b11011110 ;
1:
#435000
0:
#440000
0$
0"
1B
1D
0C
b110 U
0#
0!
b110010000000000 A
b110010000000000 X
b11 G
b11 V
b11 W
1J
b11011110 %
b11011110 K
1:
#445000
0:
#450000
0D
1E
b100 U
b1 Z
b1 `
b100100001100000 A
b100100001100000 X
b11011110 (
b11011110 >
b11011110 \
b11011110 b
b100 G
b100 V
b100 W
b0 )
b0 I
b0 N
b1 M
b1 [
b1 a
1L
1'
0J
1:
#455000
0:
#460000
b1100 =
b1100 &
b1100 8
b1100 H
b1100 O
b1100 .
b1100 6
b1100 P
b1110001 1
b1110001 5
b1110001 T
b1 Y
b1 _
b11001100000 0
b1110001 4
b100110101000000 A
b100110101000000 X
b1100 (
b1100 >
b1100 \
b1100 b
b1100000 +
b1100000 -
b1100000 2
b1100000 S
b101 G
b101 V
b101 W
b11011110 ,
b11011110 ?
b11011110 Q
b11011110 ]
b11011110 d
b10 M
b10 [
b10 a
0'
1*
b1100000 )
b1100000 I
b1100000 N
1:
#465000
0:
#470000
b11101111 (
b11101111 >
b11101111 \
b11101111 b
b11101111 =
b11101111 &
b11101111 8
b11101111 H
b11101111 O
0E
1F
b0 U
b10 Z
b10 `
b11 Y
b11 _
b11101111 .
b11101111 6
b11101111 P
b11110 1
b11110 5
b11110 T
b1000000 +
b1000000 -
b1000000 2
b1000000 S
b101110000000 A
b101110000000 X
b1111011110000000 0
b11110 4
b110 G
b110 V
b110 W
b1000000 )
b1000000 I
b1000000 N
b11 M
b11 [
b11 a
b11011110 /
b11011110 3
b11011110 @
b11011110 R
b11011110 ^
b11011110 c
1:
#475000
0:
#480000
1E
b1 U
b0 Z
b0 `
b10 Y
b10 _
b11111110 .
b11111110 6
b11111110 P
b11111011 1
b11111011 5
b11111011 T
b11111011 (
b11111011 >
b11111011 \
b11111011 b
b1101000010100 A
b1101000010100 X
b1111111100110100 0
b111111011 4
b11111011 =
b11111011 &
b11111011 8
b11111011 H
b11111011 O
b1100 +
b1100 -
b1100 2
b1100 S
b111 G
b111 V
b111 W
b11101111 /
b11101111 3
b11101111 @
b11101111 R
b11101111 ^
b11101111 c
b1100 ,
b1100 ?
b1100 Q
b1100 ]
b1100 d
b10 M
b10 [
b10 a
17
0*
b10000000 )
b10000000 I
b10000000 N
1:
#485000
0:
#490000
b1111 (
b1111 >
b1111 \
b1111 b
0F
b1111 =
b1111 &
b1111 8
b1111 H
b1111 O
b100 U
b11 Z
b11 `
b0 Y
b0 _
b11111111 .
b11111111 6
b11111111 P
b1111 1
b1111 5
b1111 T
b100000011000000 A
b100000011000000 X
b1111111110011100 0
b1111 4
b10100 +
b10100 -
b10100 2
b10100 S
b1000 G
b1000 V
b1000 W
1*
b10100 )
b10100 I
b10100 N
b11111011 /
b11111011 3
b11111011 @
b11111011 R
b11111011 ^
b11111011 c
b10001 ,
b10001 ?
b10001 Q
b10001 ]
b10001 d
1:
#495000
0:
#500000
b1 Z
b1 `
b1 Y
b1 _
b11110111 .
b11110111 6
b11110111 P
b11010001 1
b11010001 5
b11010001 T
b11110111 (
b11110111 >
b11110111 \
b11110111 b
b100010101100000 A
b100010101100000 X
b1111101111000000 0
b111010001 4
b11110111 =
b11110111 &
b11110111 8
b11110111 H
b11110111 O
b11000000 +
b11000000 -
b11000000 2
b11000000 S
b1001 G
b1001 V
b1001 W
b10001 /
b10001 3
b10001 @
b10001 R
b10001 ^
b10001 c
b11101111 ,
b11101111 ?
b11101111 Q
b11101111 ]
b11101111 d
b0 M
b0 [
b0 a
07
b11000000 )
b11000000 I
b11000000 N
1:
#505000
0:
