rtl/v7/sfixed_adder.sv
import datatypes::max;

module sfixed_adder #(
    parameter A_LEFT    = 3, 
    parameter A_RIGHT   = 4, 
    parameter B_LEFT    = 3, 
    parameter B_RIGHT   = 4,
    parameter OUT_LEFT  = 4, 
    parameter OUT_RIGHT = 4
) (   
    input  logic signed [(A_LEFT+A_RIGHT+1)-1:0]     a,
    input  logic signed [(B_LEFT+B_RIGHT+1)-1:0]     b,
    output logic signed [(OUT_LEFT+OUT_RIGHT+1)-1:0] out
);

`ifdef COCOTB_SIM
initial begin
    $dumpfile ("sfixed_adder.vcd");
    $dumpvars (0, sfixed_adder);
    #1;
end
`endif

localparam OUTPUT_SIZE = (max(A_LEFT,B_LEFT)+1)+max(A_RIGHT,B_RIGHT)+1; 

logic signed [OUTPUT_SIZE-1:0] add_out;

always_comb
    add_out = a + b;

assign out = add_out[max(A_RIGHT,B_RIGHT)+OUT_LEFT:max(A_RIGHT,B_RIGHT)-OUT_RIGHT];

endmodule

rtl/v7/sfixed_mult.sv
module sfixed_mult #(
    parameter A_LEFT    = 3, 
    parameter A_RIGHT   = 4,
    parameter B_LEFT    = 3, 
    parameter B_RIGHT   = 4,
    parameter OUT_LEFT  = 7, 
    parameter OUT_RIGHT = 8
) (
    input  logic signed [(A_LEFT+A_RIGHT+1)-1:0]     a,
    input  logic signed [(B_LEFT+B_RIGHT+1)-1:0]     b,
    output logic signed [(OUT_LEFT+OUT_RIGHT+1)-1:0] out
);
`ifdef COCOTB_SIM
initial begin
    $dumpfile ("sfixed_mult.vcd");
    $dumpvars (0, sfixed_mult);
    #1;
end
`endif

localparam OUTPUT_SIZE = (A_LEFT+B_LEFT+1)+(A_RIGHT+B_RIGHT)+1; 
                                                                
logic signed [OUTPUT_SIZE-1:0] mult_out;

always_comb
    mult_out = a * b;

assign out = mult_out[(A_RIGHT+B_RIGHT)+OUT_LEFT:(A_RIGHT+B_RIGHT)-OUT_RIGHT];

endmodule

rtl/v6/mux_21.sv
module mux_21 #(
    parameter BIT_WIDTH = 8
) (   
    input  logic s, 
    input  logic [BIT_WIDTH-1:0] a, b,
    output logic [BIT_WIDTH-1:0] out
);
    `ifdef COCOTB_SIM
    initial begin
        $dumpfile ("mux_21.vcd");
        $dumpvars (0, mux_21);
        #1;
    end
    `endif 
    assign out = s ? a : b;
endmodule

rtl/v5/ALU.sv
module ALU #(
    parameter BUS_WIDTH  = 8
) (
    input  logic                 clk, 
    input  logic [BUS_WIDTH-1:0] sw,
    input  logic [BUS_WIDTH-1:0] imm,
    input  logic [BUS_WIDTH-1:0] data_a,    
    input  logic [BUS_WIDTH-1:0] data_b,    
    input  logic [4:0]           reg_en,
    input  logic                 f_add,
    input  logic                 f_load,
    output logic [BUS_WIDTH-1:0] result 
);       

// setting up of add/subtract inputs
logic [BUS_WIDTH-1:0] op_e, e_add, coeff;
logic [BUS_WIDTH-1:0] op_a_reg, op_b_reg, op_c_reg, op_d_reg, op_e_reg;


mux_21 #(
    BUS_WIDTH
) e_add_mux (   
    .s  (f_load), 
    .a  (sw    ), 
    .b  (data_a),
    .out(e_add )
);

mux_21 #(
    BUS_WIDTH
) op_e_mux (   
    .s  (f_add), 
    .a  (e_add), 
    .b  (imm  ),
    .out(op_e )
);

mux_21 #(
    BUS_WIDTH
) coeff_mux (   
    .s  (f_add              ), 
    .a  ({BUS_WIDTH-1{1'b0}}), 
    .b  (imm                ),
    .out(coeff              )
);


// input registers
always_ff @( posedge clk ) begin 
    if (reg_en[0]) 
        op_a_reg <= data_a;
end

always_ff @( posedge clk ) begin 
    if (reg_en[1]) 
        op_b_reg <= coeff;
end

always_ff @( posedge clk ) begin 
    if (reg_en[2]) begin
        op_c_reg <= data_b;
    end
end

always_ff @( posedge clk ) begin 
    if (reg_en[3])
        op_d_reg <= coeff;
end

always_ff @( posedge clk ) begin
    if (reg_en[4])
        op_e_reg <= op_e;
end


// the computational part
logic[BUS_WIDTH-1:0] mult_a, mult_b, add_a, add_b;

sfixed_mult #(
    7, 
    0,
    0, 
    7,
    7,
    0 
) m0 (
    .a  (op_a_reg), // int
    .b  (op_b_reg), // tf
    .out(mult_a  )
);

sfixed_mult #(
    7, 
    0,
    0, 
    7,
    7, 
    0
) m1 (
    .a  (op_c_reg), // int
    .b  (op_d_reg), // tf
    .out(mult_b  )
);

(* keep *) sfixed_adder #(  
    7, 
    0, 
    7, 
    0,
    7, 
    0 
) a0 (   
    .a  (mult_a), // int
    .b  (mult_b), // int
    .out(add_a )
);

(* keep *) sfixed_adder #(
    7, 
    0, 
    7, 
    0,
    7, 
    0
) a1 (   /* synthesis keep */
    .a  (add_a   ), // int
    .b  (op_e_reg), // int
    .out(result  )
);

endmodule

include/opcodes.sv
//-----------------------------------------------------
// File Name : opcodes.sv
// Function : pMIPS instr opcode definitions
// Author: jf
//-----------------------------------------------------
//
`define NOP  6'b000000
`define ADD  6'b000001
`define SUB  6'b000010
`define ADDI 6'b000011
`define SUBI 6'b000100
`define BEQ  6'b000101
`define BNE  6'b000110
`define BGE  6'b000111
`define BLO  6'b001000

rtl/v6/instruction_decoder.sv
`include "opcodes.sv"

module instruction_decoder #(
    parameter OPCODE_WIDTH = 3
) (
    input  logic [OPCODE_WIDTH-1:0] opcode,                  
    output logic                    f_add,            
    output logic                    f_wait,       
    output logic                    f_load,      
    output logic                    wr_res,         
    output logic [4:0]              ALU_reg_en
);

always_comb 
begin
    case(opcode)    
        `MOV : begin
            f_load     = '0;
            f_add      = '1; 
            f_wait     = '0;
            wr_res     = '1; 
            ALU_reg_en = 5'b11111; // C, A
        end
        `MAC : begin 
            f_load     = '0;
            f_add      = '0;
            f_wait     = '0;
            wr_res     = '1; 
            ALU_reg_en = 5'b00101; // C, A
        end
        `WAIT: begin
            f_load     = '0;
            f_add      = '0;
            f_wait     = '1;
            wr_res     = '0;
            ALU_reg_en = 5'b00000;
        end
        `SETB: begin
            f_load     = '0;
            f_add      = '0;
            f_wait     = '0;
            wr_res     = '0;
            ALU_reg_en = 5'b00010; 
        end
        `SETD: begin
            f_load     = '0;
            f_add      = '0;
            f_wait     = '0;
            wr_res     = '0;
            ALU_reg_en = 5'b01000;
        end
        `SETE: begin
            f_load     = '0;
            f_add      = '0;
            f_wait     = '0;
            wr_res     = '0;
            ALU_reg_en = 5'b10000;
        end
        `LDSW: begin
            f_load     = '1;
            f_add      = '1;
            f_wait     = '0;
            wr_res     = '1;
            ALU_reg_en = 5'b11111;
        end
        default : begin
            f_load     = '0;
            f_add      = '0;
            f_wait     = '0;
            wr_res     = '0;
            ALU_reg_en = '0;
        end
    endcase 
end 

endmodule

rtl/v3/register_file.sv
module register_file #(
    parameter BUS_WIDTH  = 8,
    parameter ADDR_WIDTH = 3
) (
	input  logic                  clk, 
	input  logic                  we,
 	input  logic [ADDR_WIDTH-1:0] wr_addr,
	input  logic [BUS_WIDTH-1:0]  wr_data,
 	input  logic [ADDR_WIDTH-1:0] rd_addr_a, rd_addr_b,
 	output logic [BUS_WIDTH-1:0]  rd_data_a, rd_data_b
);

localparam N = (1 << ADDR_WIDTH);

logic [BUS_WIDTH-1:0] gpr [N-1:0];

initial begin
	for (int i = 0; i < N; i = i + 1)
		gpr[i] = '0;
end

// syncrhonous RAM write
always_ff @ (posedge clk)
begin
	if (we) begin 
		gpr[wr_addr] <= wr_data;
	end
	rd_data_b <= gpr[rd_addr_b];
	rd_data_a <= gpr[rd_addr_a];
end	
	

endmodule

rtl/v6/program_memory.sv
module program_memory #(
    parameter ADDR_WIDTH  = 4,
    parameter INSTR_WIDTH = 12
) (
    input  logic [ADDR_WIDTH-1:0]  addr,
    output logic [INSTR_WIDTH-1:0] instr
); 

(* ramstyle = "mlab" *) logic [INSTR_WIDTH-1:0] prog_mem [(1<<ADDR_WIDTH)-1:0];

initial
begin
`ifdef COCOTB_SIM
    $readmemh("/home/jonahfoley/ELEC6234/a_fine_CPU/programs/prog_3.hex", prog_mem);
`else
    $readmemh("../../programs/prog_3.hex", prog_mem);
`endif
end
   
always_comb
    instr = prog_mem[addr]; 
  
endmodule

rtl/v3/program_counter.sv
module program_counter #(
    parameter ADDR_WIDTH = 3
) (
    input  logic                  clk, n_reset,
    input  logic                  en,
    output logic [ADDR_WIDTH-1:0] count
);
 
always_ff @(posedge clk, negedge n_reset) 
begin   
    if (~n_reset) 
        count <= '0;
    else begin
        if (count == (2<<ADDR_WIDTH)-1) 
            count <= '0;
        else begin
            if (en)
                count <= count + { {ADDR_WIDTH-1{1'b0}}, 1'b1 };
        end
    end
end


endmodule

rtl/v6/CPU.sv
module CPU #(
    parameter INSTR_WIDTH      = 12,
    parameter OPCODE_WIDTH     = 3,
    parameter INSTR_ADDR_WIDTH = 4, 
    parameter REG_ADDR_WIDTH   = 2, 
    parameter BUS_WIDTH        = 8
) (
    input  logic                 clk,  
    input  logic                 n_reset,
    input  logic [BUS_WIDTH-1:0] in_port,
    input  logic                 ready_in,
    output logic [BUS_WIDTH-1:0] out_port
);       

//the macro to dump signals   
`ifdef COCOTB_SIM
initial begin
    $dumpfile ("CPU.vcd");
    $dumpvars (0, CPU);
    #1;
end
`endif

// input switch handshaking
logic ready_in_p, pattern_match;
always_ff @(posedge clk)
    ready_in_p <= ready_in;

logic [1:0][BUS_WIDTH-1:0] sw;
always_ff @(posedge clk)
    sw <= {sw[0], in_port};

assign pattern_match = (~ready_in_p & ready_in);

// -- instr counter
logic [INSTR_ADDR_WIDTH-1:0] PC_count;
logic PC_en, PC_comparator;

mux_21 #(
    1
) PC_en_mux (
    .s  (instr[3]     ), // differentiate between instr[5:3] == 001 (pattern) / 000 (rdy)
    .a  (pattern_match), // 001 -> pattern
    .b  (ready_in     ), // 000 -> ready in 
    .out(PC_comparator)
);

assign PC_en = ~(PC_wait & (PC_comparator ^ instr[0]));

program_counter #(
   INSTR_ADDR_WIDTH
) pc (
   .clk    (clk     ),
   .n_reset(n_reset ),
   .en     (PC_en   ),
   .count  (PC_count)
);

// -- program ROM
logic [INSTR_WIDTH-1:0] instr;

program_memory #(
    INSTR_ADDR_WIDTH,
    INSTR_WIDTH
) pm (
    .addr (PC_count),
    .instr(instr   )
);

// -- reg file
logic wr_res;
logic [1:0] we;
logic [1:0][REG_ADDR_WIDTH-1:0] wr_addr;
logic [BUS_WIDTH-1:0] rd_data_a, rd_data_b;

always_ff @(posedge clk) 
begin
    we      <= {we[0], wr_res};
    wr_addr <= {wr_addr[0], instr[7:6]};
end

register_file #(
    BUS_WIDTH,
    3
) rf (
	.clk      (clk       ),  
    .we       (we[1]     ),
 	.wr_addr  (wr_addr[1]),
	.wr_data  (ALU_result),
 	.rd_addr_a(instr[4:3]), 
    .rd_addr_b(instr[1:0]),
 	.rd_data_a(rd_data_a ), 
    .rd_data_b(rd_data_b )
);

// -- decoder
logic f_add, f_load, PC_wait;
logic [4:0] reg_en; 

instruction_decoder #(
    OPCODE_WIDTH
) id (
    .opcode    (instr[11:9]),                  
    .f_add     (f_add      ), 
    .f_wait    (PC_wait    ),            
    .f_load    (f_load     ),            
    .wr_res    (wr_res     ),         
    .ALU_reg_en(reg_en     )
);

// -- ALU
logic [BUS_WIDTH-1:0] ALU_result;
logic [BUS_WIDTH-1:0] ALU_imm;
logic [4:0]           ALU_reg_en; 
logic                 ALU_add, ALU_load;

always_ff @(posedge clk) begin
    ALU_imm    <= instr[7:0];
    ALU_load   <= f_load;
    ALU_add    <= f_add;
    ALU_reg_en <= reg_en;
end

ALU #(
    BUS_WIDTH
) alu (
    .clk   (clk       ),
    .sw    (sw[1]     ),
    .imm   (ALU_imm   ),
    .data_a(rd_data_a ),
    .data_b(rd_data_b ),   
    .reg_en(ALU_reg_en),
    .f_add (ALU_add   ),
    .f_load(ALU_load  ),
    .result(ALU_result)
);    

assign out_port = ALU_result;

endmodule

simulation/v5/CPU/mux_21.vcd
$date
	Sun Apr 23 02:15:13 2023
$end
$version
	Icarus Verilog
$end
$timescale
	1ps
$end
$scope module CPU $end
$scope module PC_en_mux $end
$var wire 1 ! a $end
$var wire 1 " b $end
$var wire 1 # s $end
$var wire 1 $ out $end
$upscope $end
$upscope $end
$scope module CPU $end
$scope module alu $end
$scope module e_add_mux $end
$var wire 8 % a [7:0] $end
$var wire 1 & s $end
$var wire 8 ' out [7:0] $end
$var wire 8 ( b [7:0] $end
$upscope $end
$upscope $end
$upscope $end
$scope module CPU $end
$scope module alu $end
$scope module op_e_mux $end
$var wire 8 ) a [7:0] $end
$var wire 8 * b [7:0] $end
$var wire 1 + s $end
$var wire 8 , out [7:0] $end
$upscope $end
$upscope $end
$upscope $end
$scope module CPU $end
$scope module alu $end
$scope module coeff_mux $end
$var wire 8 - a [7:0] $end
$var wire 8 . b [7:0] $end
$var wire 1 + s $end
$var wire 8 / out [7:0] $end
$upscope $end
$upscope $end
$upscope $end
$scope module CPU $end
$scope module alu $end
$scope module m0 $end
$var wire 8 0 a [7:0] $end
$var wire 8 1 b [7:0] $end
$var wire 8 2 out [7:0] $end
$var reg 16 3 mult_out [15:0] $end
$upscope $end
$upscope $end
$upscope $end
$scope module CPU $end
$scope module alu $end
$scope module m1 $end
$var wire 8 4 a [7:0] $end
$var wire 8 5 b [7:0] $end
$var wire 8 6 out [7:0] $end
$var reg 16 7 mult_out [15:0] $end
$upscope $end
$upscope $end
$upscope $end
$scope module CPU $end
$scope module alu $end
$scope module a0 $end
$var wire 8 8 out [7:0] $end
$var wire 8 9 b [7:0] $end
$var wire 8 : a [7:0] $end
$var reg 9 ; add_out [8:0] $end
$upscope $end
$upscope $end
$upscope $end
$scope module CPU $end
$scope module alu $end
$scope module a1 $end
$var wire 8 < a [7:0] $end
$var wire 8 = b [7:0] $end
$var wire 8 > out [7:0] $end
$var reg 9 ? add_out [8:0] $end
$upscope $end
$upscope $end
$upscope $end
$scope module CPU $end
$var wire 1 @ PC_en $end
$var wire 1 A clk $end
$var wire 8 B in_port [7:0] $end
$var wire 1 C n_reset $end
$var wire 8 D out_port [7:0] $end
$var wire 1 ! pattern_match $end
$var wire 1 " ready_in $end
$var wire 1 E wr_res $end
$var wire 5 F reg_en [4:0] $end
$var wire 8 G rd_data_b [7:0] $end
$var wire 8 H rd_data_a [7:0] $end
$var wire 12 I instr [11:0] $end
$var wire 1 J f_load $end
$var wire 1 K f_add $end
$var wire 1 L PC_wait $end
$var wire 4 M PC_count [3:0] $end
$var wire 1 $ PC_comparator $end
$var wire 8 N ALU_result [7:0] $end
$var reg 1 + ALU_add $end
$var reg 8 O ALU_imm [7:0] $end
$var reg 1 & ALU_load $end
$var reg 5 P ALU_reg_en [4:0] $end
$var reg 1 Q ready_in_p $end
$var reg 16 R sw [15:0] $end
$var reg 2 S we [1:0] $end
$var reg 4 T wr_addr [3:0] $end
$scope module PC_en_mux $end
$upscope $end
$scope module alu $end
$var wire 1 A clk $end
$var wire 1 + f_add $end
$var wire 1 & f_load $end
$var wire 8 U imm [7:0] $end
$var wire 5 V reg_en [4:0] $end
$var wire 8 W sw [7:0] $end
$var wire 8 X result [7:0] $end
$var wire 8 Y op_e [7:0] $end
$var wire 8 Z mult_b [7:0] $end
$var wire 8 [ mult_a [7:0] $end
$var wire 8 \ e_add [7:0] $end
$var wire 8 ] data_b [7:0] $end
$var wire 8 ^ data_a [7:0] $end
$var wire 8 _ coeff [7:0] $end
$var wire 8 ` add_a [7:0] $end
$var reg 8 a op_a_reg [7:0] $end
$var reg 8 b op_b_reg [7:0] $end
$var reg 8 c op_c_reg [7:0] $end
$var reg 8 d op_d_reg [7:0] $end
$var reg 8 e op_e_reg [7:0] $end
$scope module a0 $end
$upscope $end
$scope module a1 $end
$upscope $end
$scope module coeff_mux $end
$upscope $end
$scope module e_add_mux $end
$upscope $end
$scope module m0 $end
$upscope $end
$scope module m1 $end
$upscope $end
$scope module op_e_mux $end
$upscope $end
$upscope $end
$scope module id $end
$var wire 3 f opcode [2:0] $end
$var reg 5 g ALU_reg_en [4:0] $end
$var reg 1 K f_add $end
$var reg 1 J f_load $end
$var reg 1 L f_wait $end
$var reg 1 E wr_res $end
$upscope $end
$scope module pc $end
$var wire 1 A clk $end
$var wire 1 @ en $end
$var wire 1 C n_reset $end
$var reg 4 h count [3:0] $end
$upscope $end
$scope module pm $end
$var wire 4 i addr [3:0] $end
$var reg 12 j instr [11:0] $end
$upscope $end
$scope module rf $end
$var wire 1 A clk $end
$var wire 2 k rd_addr_a [1:0] $end
$var wire 2 l rd_addr_b [1:0] $end
$var wire 1 m we $end
$var wire 2 n wr_addr [1:0] $end
$var wire 8 o wr_data [7:0] $end
$var wire 8 p rd_data_b [7:0] $end
$var wire 8 q rd_data_a [7:0] $end
$scope module sr0 $end
$var wire 1 A clk $end
$var wire 2 r rd_addr_a [1:0] $end
$var wire 2 s rd_addr_b [1:0] $end
$var wire 1 m we $end
$var wire 2 t wr_addr [1:0] $end
$var wire 8 u wr_data [7:0] $end
$var reg 8 v rd_data_a [7:0] $end
$var reg 8 w rd_data_b [7:0] $end
$scope begin $ivl_for_loop0 $end
$var integer 32 x i [31:0] $end
$upscope $end
$upscope $end
$upscope $end
$upscope $end
$enddefinitions $end
#0
$dumpvars
b11 x
bx w
bx v
bx u
bx t
b1 s
b1 r
bx q
bx p
bx o
bx n
xm
b1 l
b1 k
b111000001001 j
b0 i
b0 h
b0 g
b111 f
bx e
bx d
bx c
bx b
bx a
bx `
bx _
bx ^
bx ]
bx \
bx [
bx Z
bx Y
bx X
bx W
b0 V
bx U
bx T
bx0 S
bx00000000 R
0Q
b0 P
bx O
bx N
b0 M
1L
0K
0J
b111000001001 I
bx H
bx G
b0 F
0E
bx D
0C
b0 B
1A
0@
bx ?
bx >
bx =
bx <
bx ;
bx :
bx 9
bx 8
bx 7
bx 6
bx 5
bx 4
bx 3
bx 2
bx 1
bx 0
bx /
bx .
b0 -
bx ,
0+
bx *
bx )
bx (
bx '
0&
bx %
0$
1#
0"
0!
$end
#5000
0A
#10000
b1001 /
b1001 _
b1001 ,
b1001 Y
0m
b0 %
b0 W
b0 '
b0 )
b0 \
b1001 *
b1001 .
b1001 O
b1001 U
bx00 T
b0 S
b0 R
b0 (
b0 H
b0 ^
b0 q
b0 v
b0 G
b0 ]
b0 p
b0 w
1A
#15000
0A
#20000
1C
b0 n
b0 t
b0 T
1A
#25000
0A
#30000
1A
#35000
0A
#40000
1A
#45000
0A
#50000
1A
#55000
0A
#60000
1A
#65000
0A
#70000
1A
#75000
0A
#80000
1A
#85000
0A
#90000
1A
#95000
0A
#100000
1A
#105000
0A
#110000
1A
#115000
0A
#120000
1@
1$
1!
1"
b1011101 B
1A
#125000
0A
#130000
0$
0"
b11111 F
b11111 g
1E
0L
1K
1J
0!
b110 f
b0 l
b0 s
b0 k
b0 r
0#
b110000000000 I
b110000000000 j
b1011101 R
1Q
b1 M
b1 h
b1 i
1A
#135000
0A
#140000
0@
b0 F
b0 g
0E
1L
0K
0J
b1011101 '
b1011101 )
b1011101 \
b111 f
b1 l
b1 s
b1 k
b1 r
1#
b1011101 %
b1011101 W
b0 /
b0 _
b1011101 ,
b1011101 Y
b111000001001 I
b111000001001 j
0Q
b101110101011101 R
b1 S
b11111 P
b11111 V
1+
1&
b0 *
b0 .
b0 O
b0 U
b10 M
b10 h
b10 i
1A
#145000
0A
#150000
b1011101 D
b1011101 >
b1011101 N
b1011101 X
b1011101 o
b1011101 u
b1011101 ?
b0 8
b0 <
b0 `
b0 ;
b0 6
b0 9
b0 Z
b0 2
b0 :
b0 [
b1001 /
b1001 _
b1001 ,
b1001 Y
b0 '
b0 )
b0 \
1m
b0 7
b0 3
b0 P
b0 V
0+
0&
b1001 *
b1001 .
b1001 O
b1001 U
b10 S
b1011101 =
b1011101 e
b0 5
b0 d
b0 4
b0 c
b0 1
b0 b
b0 0
b0 a
1A
#155000
0A
#160000
0m
b0 S
1A
#165000
0A
#170000
1A
#175000
0A
#180000
1A
#185000
0A
#190000
1@
1$
1!
1"
b1101101 B
1A
#195000
0A
#200000
0$
0"
b11111 F
b11111 g
1E
0L
1K
1J
0!
b110 f
b0 l
b0 s
b0 k
b0 r
0#
b110001000000 I
b110001000000 j
1Q
b101110101101101 R
b11 M
b11 h
b11 i
1A
#205000
0A
#210000
b10 F
b10 g
0E
0K
0J
b11 f
b0 /
b0 _
b1101101 ,
b1101101 Y
b1101101 %
b1101101 W
b1101101 '
b1101101 )
b1101101 \
b11001100000 I
b11001100000 j
b11111 P
b11111 V
1+
1&
b1000000 *
b1000000 .
b1000000 O
b1000000 U
b1 T
b1 S
b110110101101101 R
0Q
b1011101 (
b1011101 H
b1011101 ^
b1011101 q
b1011101 v
b1011101 G
b1011101 ]
b1011101 p
b1011101 w
b100 M
b100 h
b100 i
1A
#215000
0A
#220000
b1000 F
b1000 g
b1101101 D
b1101101 >
b1101101 N
b1101101 X
b1101101 o
b1101101 u
b100 f
b1101101 ?
b1 n
b1 t
1m
b1100000 /
b1100000 _
b1100000 ,
b1100000 Y
b1011101 '
b1011101 )
b1011101 \
b100001000000 I
b100001000000 j
b1011101 0
b1011101 a
b1011101 4
b1011101 c
b1101101 =
b1101101 e
b101 T
b10 S
b10 P
b10 V
0+
0&
b1100000 *
b1100000 .
b1100000 O
b1100000 U
b101 M
b101 h
b101 i
1A
#225000
0A
#230000
b10110010 D
b10110010 >
b10110010 N
b10110010 X
b10110010 o
b10110010 u
b10110010 ?
b1000101 8
b1000101 <
b1000101 `
b1000101 ;
b10000 F
b10000 g
b1000101 2
b1000101 :
b1000101 [
b101 f
b10 k
b10 r
b1000000 /
b1000000 _
b1000000 ,
b1000000 Y
0m
b10001011100000 3
b101000010100 I
b101000010100 j
b1000 P
b1000 V
b1000000 *
b1000000 .
b1000000 O
b1000000 U
b0 S
b1100000 1
b1100000 b
b110 M
b110 h
b110 i
1A
#235000
0A
#240000
b11100000 D
b11100000 >
b11100000 N
b11100000 X
b11100000 o
b11100000 u
b11100000 ?
b1110011 8
b1110011 <
b1110011 `
b1110011 ;
b101 F
b101 g
1E
b101110 6
b101110 9
b101110 Z
b1 f
b1 l
b1 s
b0 k
b0 r
b0 '
b0 )
b0 \
b1011101000000 7
b10100 /
b10100 _
b10100 ,
b10100 Y
b1010000001 I
b1010000001 j
b0 (
b0 H
b0 ^
b0 q
b0 v
b1000000 5
b1000000 d
b100 T
b10000 P
b10000 V
b10100 *
b10100 .
b10100 O
b10100 U
b111 M
b111 h
b111 i
1A
#245000
0A
#250000
b10 F
b10 g
0E
b10000111 D
b10000111 >
b10000111 N
b10000111 X
b10000111 o
b10000111 u
b11 f
b0 l
b0 s
b10000001 /
b10000001 _
b10000001 ,
b10000001 Y
b0 n
b0 t
b10000111 ?
b1011101 '
b1011101 )
b1011101 \
b11011000000 I
b11011000000 j
b101 P
b101 V
b10000001 *
b10000001 .
b10000001 O
b10000001 U
b10 T
b1 S
b10100 =
b10100 e
b1011101 (
b1011101 H
b1011101 ^
b1011101 q
b1011101 v
b1101101 G
b1101101 ]
b1101101 p
b1101101 w
b1000 M
b1000 h
b1000 i
1A
#255000
0A
#260000
b10001111 D
b10001111 >
b10001111 N
b10001111 X
b10001111 o
b10001111 u
b10001111 ?
b1111011 8
b1111011 <
b1111011 `
b1111011 ;
b1000 F
b1000 g
b110110 6
b110110 9
b110110 Z
b100 f
b1101101000000 7
b10 n
b10 t
1m
b11000000 /
b11000000 _
b11000000 ,
b11000000 Y
b100001100000 I
b100001100000 j
b1011101 G
b1011101 ]
b1011101 p
b1011101 w
b1101101 4
b1101101 c
b1011 T
b10 S
b10 P
b10 V
b11000000 *
b11000000 .
b11000000 O
b11000000 U
b1001 M
b1001 h
b1001 i
1A
#265000
0A
#270000
b11011 D
b11011 >
b11011 N
b11011 X
b11011 o
b11011 u
b11011 ?
b111 8
b111 <
b111 `
b111 ;
b10000 F
b10000 g
b11010001 2
b11010001 :
b11010001 [
b101 f
b1 k
b1 r
1#
b1100000 /
b1100000 _
b1100000 ,
b1100000 Y
b11 n
b11 t
0m
b1110100011000000 3
b101011101100 I
b101011101100 j
b1000 P
b1000 V
b1100000 *
b1100000 .
b1100000 O
b1100000 U
b1101 T
b0 S
b11000000 1
b11000000 b
b1010 M
b1010 h
b1010 i
1A
#275000
0A
#280000
b110110 D
b110110 >
b110110 N
b110110 X
b110110 o
b110110 u
b110110 ?
b100010 8
b100010 <
b100010 `
b100010 ;
b101 F
b101 g
1E
b1010001 6
b1010001 9
b1010001 Z
b1 f
b1 l
b1 s
b0 k
b0 r
0#
b1101101 '
b1101101 )
b1101101 \
b10100011100000 7
b1 n
b1 t
b11101100 /
b11101100 _
b11101100 ,
b11101100 Y
b1001000001 I
b1001000001 j
b1101101 (
b1101101 H
b1101101 ^
b1101101 q
b1101101 v
b1100000 5
b1100000 d
b111 T
b10000 P
b10000 V
b11101100 *
b11101100 .
b11101100 O
b11101100 U
b1011 M
b1011 h
b1011 i
1A
#285000
0A
#290000
b11111 F
b11111 g
1K
b1110 D
b1110 >
b1110 N
b1110 X
b1110 o
b1110 u
b0 f
b0 l
b0 s
b10 k
b10 r
b1000001 /
b1000001 _
b1000001 ,
b1000001 Y
b11 n
b11 t
b1110 ?
b1011101 '
b1011101 )
b1011101 \
b10000 I
b10000 j
b101 P
b101 V
b1000001 *
b1000001 .
b1000001 O
b1000001 U
b1101 T
b1 S
b11101100 =
b11101100 e
b1011101 (
b1011101 H
b1011101 ^
b1011101 q
b1011101 v
b1101101 G
b1101101 ]
b1101101 p
b1101101 w
b1100 M
b1100 h
b1100 i
1A
#295000
0A
#300000
0@
b0 F
b0 g
0E
1L
0K
b111 f
b1 l
b1 s
b0 k
b0 r
b10001111 '
b10001111 )
b10001111 \
b1 n
b1 t
1m
b0 /
b0 _
b10001111 ,
b10001111 Y
b111000000001 I
b111000000001 j
b10001111 (
b10001111 H
b10001111 ^
b10001111 q
b10001111 v
b1011101 G
b1011101 ]
b1011101 p
b1011101 w
b100 T
b11 S
b11111 P
b11111 V
1+
b10000 *
b10000 .
b10000 O
b10000 U
b1101 M
b1101 h
b1101 i
1A
#305000
0A
#310000
b0 8
b0 <
b0 `
b0 ;
b10001111 D
b10001111 >
b10001111 N
b10001111 X
b10001111 o
b10001111 u
b0 6
b0 9
b0 Z
b0 2
b0 :
b0 [
b1 /
b1 _
b1 ,
b1 Y
b0 n
b0 t
b110001111 ?
b0 7
b0 3
b1011101 '
b1011101 )
b1011101 \
b0 P
b0 V
0+
b1 *
b1 .
b1 O
b1 U
b0 T
b10 S
b10001111 =
b10001111 e
b0 5
b0 d
b1011101 4
b1011101 c
b0 1
b0 b
b10001111 0
b10001111 a
b1011101 (
b1011101 H
b1011101 ^
b1011101 q
b1011101 v
b1101101 G
b1101101 ]
b1101101 p
b1101101 w
1A
#315000
0A
#320000
1@
1!
1$
1"
0m
b1110 G
b1110 ]
b1110 p
b1110 w
b0 S
1A
#325000
0A
#330000
b11111 F
b11111 g
1E
0L
1K
0$
0!
b0 f
b0 l
b0 s
b1 k
b1 r
1#
b10001111 '
b10001111 )
b10001111 \
b1000 I
b1000 j
1Q
b10001111 (
b10001111 H
b10001111 ^
b10001111 q
b10001111 v
b1110 M
b1110 h
b1110 i
1A
#335000
0A
#340000
0@
b0 F
b0 g
0E
1L
0K
1$
b111 f
b0 k
b0 r
0#
b1110 '
b1110 )
b1110 \
b0 /
b0 _
b1110 ,
b1110 Y
b111000000000 I
b111000000000 j
b1110 (
b1110 H
b1110 ^
b1110 q
b1110 v
b10001111 G
b10001111 ]
b10001111 p
b10001111 w
b1 S
b11111 P
b11111 V
1+
b1000 *
b1000 .
b1000 O
b1000 U
b1111 M
b1111 h
b1111 i
1A
#345000
0A
#350000
b1110 D
b1110 >
b1110 N
b1110 X
b1110 o
b1110 u
b0 ,
b0 Y
1m
b1110 ?
b10001111 '
b10001111 )
b10001111 \
b0 P
b0 V
0+
b0 *
b0 .
b0 O
b0 U
b10 S
b1110 =
b1110 e
b10001111 4
b10001111 c
b1110 0
b1110 a
b10001111 (
b10001111 H
b10001111 ^
b10001111 q
b10001111 v
1A
#355000
0A
#360000
1@
0$
0"
0m
b0 S
1A
#365000
0A
#370000
0@
b1 l
b1 s
b1 k
b1 r
1#
b1110 '
b1110 )
b1110 \
b111000001001 I
b111000001001 j
0Q
b1110 (
b1110 H
b1110 ^
b1110 q
b1110 v
b1110 G
b1110 ]
b1110 p
b1110 w
b0 M
b0 h
b0 i
1A
#375000
0A
#380000
b1001 /
b1001 _
b1001 ,
b1001 Y
b1001 *
b1001 .
b1001 O
b1001 U
1A
#385000
0A
#390000
1A
#395000
0A
#400000
1A
#405000
0A
#410000
1@
1$
1!
1"
b10010111 B
1A
#415000
0A
#420000
0$
0"
b11111 F
b11111 g
1E
0L
1K
1J
0!
b110 f
b0 l
b0 s
b0 k
b0 r
0#
b110000000000 I
b110000000000 j
1Q
b110110110010111 R
b1 M
b1 h
b1 i
1A
#425000
0A
#430000
0@
b0 F
b0 g
0E
1L
0K
0J
b111 f
b1 l
b1 s
b1 k
b1 r
1#
b10010111 '
b10010111 )
b10010111 \
b0 /
b0 _
b10010111 ,
b10010111 Y
b10010111 %
b10010111 W
b111000001001 I
b111000001001 j
b11111 P
b11111 V
1+
1&
b0 *
b0 .
b0 O
b0 U
b1 S
b1001011110010111 R
0Q
b10 M
b10 h
b10 i
1A
#435000
0A
#440000
b10010111 D
b10010111 >
b10010111 N
b10010111 X
b10010111 o
b10010111 u
b110010111 ?
1m
b1001 /
b1001 _
b1001 ,
b1001 Y
b1110 '
b1110 )
b1110 \
b1110 4
b1110 c
b10010111 =
b10010111 e
b10 S
b0 P
b0 V
0+
0&
b1001 *
b1001 .
b1001 O
b1001 U
1A
#445000
0A
