rtl/v7/sfixed_adder.sv
import datatypes::max;

module sfixed_adder #(
    parameter A_LEFT    = 3, 
    parameter A_RIGHT   = 4, 
    parameter B_LEFT    = 3, 
    parameter B_RIGHT   = 4,
    parameter OUT_LEFT  = 4, 
    parameter OUT_RIGHT = 4
) (   
    input  logic signed [(A_LEFT+A_RIGHT+1)-1:0]     a,
    input  logic signed [(B_LEFT+B_RIGHT+1)-1:0]     b,
    output logic signed [(OUT_LEFT+OUT_RIGHT+1)-1:0] out
);

`ifdef COCOTB_SIM
initial begin
    $dumpfile ("sfixed_adder.vcd");
    $dumpvars (0, sfixed_adder);
    #1;
end
`endif

localparam OUTPUT_SIZE = (max(A_LEFT,B_LEFT)+1)+max(A_RIGHT,B_RIGHT)+1; 

logic signed [OUTPUT_SIZE-1:0] add_out;

always_comb
    add_out = a + b;

assign out = add_out[max(A_RIGHT,B_RIGHT)+OUT_LEFT:max(A_RIGHT,B_RIGHT)-OUT_RIGHT];

endmodule

rtl/v7/sfixed_mult.sv
module sfixed_mult #(
    parameter A_LEFT    = 3, 
    parameter A_RIGHT   = 4,
    parameter B_LEFT    = 3, 
    parameter B_RIGHT   = 4,
    parameter OUT_LEFT  = 7, 
    parameter OUT_RIGHT = 8
) (
    input  logic signed [(A_LEFT+A_RIGHT+1)-1:0]     a,
    input  logic signed [(B_LEFT+B_RIGHT+1)-1:0]     b,
    output logic signed [(OUT_LEFT+OUT_RIGHT+1)-1:0] out
);
`ifdef COCOTB_SIM
initial begin
    $dumpfile ("sfixed_mult.vcd");
    $dumpvars (0, sfixed_mult);
    #1;
end
`endif

localparam OUTPUT_SIZE = (A_LEFT+B_LEFT+1)+(A_RIGHT+B_RIGHT)+1; 
                                                                
logic signed [OUTPUT_SIZE-1:0] mult_out;

always_comb
    mult_out = a * b;

assign out = mult_out[(A_RIGHT+B_RIGHT)+OUT_LEFT:(A_RIGHT+B_RIGHT)-OUT_RIGHT];

endmodule

rtl/v6/mux_21.sv
module mux_21 #(
    parameter BIT_WIDTH = 8
) (   
    input  logic s, 
    input  logic [BIT_WIDTH-1:0] a, b,
    output logic [BIT_WIDTH-1:0] out
);
    `ifdef COCOTB_SIM
    initial begin
        $dumpfile ("mux_21.vcd");
        $dumpvars (0, mux_21);
        #1;
    end
    `endif 
    assign out = s ? a : b;
endmodule

rtl/v2/ALU.sv
module ALU #(
    parameter BUS_WIDTH  = 8
) (
    input  logic                      clk, 
    input  logic [4:0][BUS_WIDTH-1:0] ops,    
    input  logic [4:0]                reg_en,
    input  logic                      f_add,
    output logic [BUS_WIDTH-1:0]      result 
);       

// setting up of add/subtract inputs
logic [BUS_WIDTH-1:0] op_e;
logic [BUS_WIDTH-1:0] op_a_reg, op_b_reg, op_c_reg, op_d_reg, op_e_reg;

mux_21 #(
    BUS_WIDTH
) e_mux (   
    .s  (f_add     ), 
    .a  (ops[0]    ), 
    .b  (ops[4]    ),
    .out(op_e      )
);

// input registers

always_ff @( posedge clk ) begin 
    if (reg_en[0]) begin
        op_a_reg <= ops[0];
    end
end

always_ff @( posedge clk ) begin 
    if (reg_en[1]) begin
        if (f_add)
            op_b_reg <= '0;
        else 
            op_b_reg <= ops[1];
    end
end

always_ff @( posedge clk ) begin 
    if (reg_en[2]) begin
        op_c_reg <= ops[2];
    end
end

always_ff @( posedge clk ) begin 
    if (reg_en[3]) begin
        if (f_add)
            op_d_reg <= '0;
        else 
            op_d_reg <= ops[3];
    end
end

always_ff @(posedge clk)  
begin
    if (reg_en[4])
        op_e_reg <= op_e;
end

// the computational part
logic[BUS_WIDTH-1:0] mult_a, mult_b, add_a, add_b;

sfixed_mult #(
    7, 
    0,
    0, 
    7,
    7,
    0 
) m0 (
    .a  (op_a_reg), // int
    .b  (op_b_reg), // tf
    .out(mult_a  )
);

sfixed_mult #(
    7, 
    0,
    0, 
    7,
    7, 
    0
) m1 (
    .a  (op_c_reg), // int
    .b  (op_d_reg), // tf
    .out(mult_b   )
);

sfixed_adder #(
    7, 
    0, 
    7, 
    0,
    7, 
    0 
) a0 (   
    .a  (mult_a), // int
    .b  (mult_b), // int
    .out(add_a )
);

sfixed_adder #(
    7, 
    0, 
    7, 
    0,
    7, 
    0
) a1 (   
    .a  (add_a   ), // int
    .b  (op_e_reg), // int
    .out(result  )
);

endmodule

include/opcodes.sv
//-----------------------------------------------------
// File Name : opcodes.sv
// Function : pMIPS instr opcode definitions
// Author: jf
//-----------------------------------------------------
//
`define NOP  6'b000000
`define ADD  6'b000001
`define SUB  6'b000010
`define ADDI 6'b000011
`define SUBI 6'b000100
`define BEQ  6'b000101
`define BNE  6'b000110
`define BGE  6'b000111
`define BLO  6'b001000

rtl/v3/instruction_decoder.sv
`include "opcodes.sv"

module instruction_decoder #(
    parameter OPCODE_WIDTH = 3
) (
    input  logic [OPCODE_WIDTH-1:0] opcode,                  
    output logic                    f_add,            
    output logic                    f_wait,            
    output logic                    wr_res,         
    output logic [4:0]              ALU_reg_en
);

always_comb 
begin
    case(opcode)    
        `MOV : begin
            f_add      = '1; 
            f_wait     = '0;
            wr_res     = '1; 
            ALU_reg_en = 5'b11111; // C, A
        end
        `MAC : begin 
            f_add      = '0;
            f_wait     = '0;
            wr_res     = '1; 
            ALU_reg_en = 5'b00101; // C, A
        end
        `WAIT: begin
            f_add      = '0;
            f_wait     = '1;
            wr_res     = '0;
            ALU_reg_en = 5'b00000;
        end
        `SETB: begin
            f_add      = '0;
            f_wait     = '0;
            wr_res     = '0;
            ALU_reg_en = 5'b00010; 
        end
        `SETD: begin
            f_add      = '0;
            f_wait     = '0;
            wr_res     = '0;
            ALU_reg_en = 5'b01000;
        end
        `SETE: begin
            f_add      = '0;
            f_wait     = '0;
            wr_res     = '0;
            ALU_reg_en = 5'b10000;
        end
        default : begin
            f_add      = '0;
            f_wait     = '0;
            wr_res     = '0;
            ALU_reg_en = '0;
        end
    endcase 
end 

endmodule

rtl/v3/register_file.sv
module register_file #(
    parameter BUS_WIDTH  = 8,
    parameter ADDR_WIDTH = 3
) (
	input  logic                  clk, 
	input  logic                  we,
 	input  logic [ADDR_WIDTH-1:0] wr_addr,
	input  logic [BUS_WIDTH-1:0]  wr_data,
 	input  logic [ADDR_WIDTH-1:0] rd_addr_a, rd_addr_b,
 	output logic [BUS_WIDTH-1:0]  rd_data_a, rd_data_b
);

localparam N = (1 << ADDR_WIDTH);

logic [BUS_WIDTH-1:0] gpr [N-1:0];

initial begin
	for (int i = 0; i < N; i = i + 1)
		gpr[i] = '0;
end

// syncrhonous RAM write
always_ff @ (posedge clk)
begin
	if (we) begin 
		gpr[wr_addr] <= wr_data;
	end
	rd_data_b <= gpr[rd_addr_b];
	rd_data_a <= gpr[rd_addr_a];
end	
	

endmodule

rtl/memory/program_memory.sv
module program_memory #(
    parameter ADDR_WIDTH  = 4,
    parameter INSTR_WIDTH = 12
) (
    input  logic [ADDR_WIDTH-1:0]  addr,
    output logic [INSTR_WIDTH-1:0] instr
); 

(* ramstyle = "MLAB" *)  logic [INSTR_WIDTH-1:0] prog_mem [(1<<ADDR_WIDTH)-1:0];

initial
    $readmemh("/home/jonahfoley/ELEC6234/a_fine_CPU/programs/prog.hex", prog_mem);
   
always_comb
    instr = prog_mem[addr]; 
  
endmodule

rtl/memory/program_counter.sv
module program_counter #(
    parameter ADDR_WIDTH = 3
) (
    input  logic                  clk, n_reset,
    input  logic                  en,
    output logic [ADDR_WIDTH-1:0] count
);
 
always_ff @(posedge clk) 
begin
    if (~n_reset) 
        count <= '0;
    else begin
        if (count == (2<<ADDR_WIDTH)-1) 
            count <= '0;
        else begin
            if (en)
                count <= count + { {ADDR_WIDTH-1{1'b0}}, 1'b1 };
        end
    end
end


endmodule

rtl/v3/CPU.sv
module CPU #(
    parameter INSTR_WIDTH      = 12,
    parameter OPCODE_WIDTH     = 3,
    parameter INSTR_ADDR_WIDTH = 4, 
    parameter REG_ADDR_WIDTH   = 2, 
    parameter BUS_WIDTH        = 8
) (
    input  logic                 clk,  
    input  logic                 n_reset,
    input  logic [BUS_WIDTH-1:0] sw,
    input  logic                 ready_in,
    output logic [BUS_WIDTH-1:0] out_port
);       

//the macro to dump signals   
`ifdef COCOTB_SIM
initial begin
    $dumpfile ("CPU.vcd");
    $dumpvars (0, CPU);
    #1;
end
`endif

// input switch handshaking
logic ready_in_p, pattern_match;
always_ff @(posedge clk)
    ready_in_p <= ready_in;

logic [BUS_WIDTH-1:0] sw_p, sw_pp;
always_ff @(posedge clk)
begin
    sw_p  <= sw;
    sw_pp <= sw_p;
end

assign pattern_match = ({ready_in_p, ready_in} == 2'b01);

// -- instr counter
logic [INSTR_ADDR_WIDTH-1:0] PC_count;
logic PC_en, PC_comparator;

mux_21 #(
    1
) PC_en_mux (
    .s  (instr[3]     ), // differentiate between instr[5:3] == 001 (pattern) / 000 (rdy)
    .a  (pattern_match), // 001 -> pattern
    .b  (ready_in     ), // 000 -> ready in 
    .out(PC_comparator)
);

assign PC_en = (PC_wait & ~(PC_comparator ^ instr[0])) | ~PC_wait;

program_counter #(
   INSTR_ADDR_WIDTH
) pc (
   .clk    (clk     ),
   .n_reset(n_reset ),
   .en     (PC_en   ),
   .count  (PC_count)
);

// -- program ROM
logic [INSTR_WIDTH-1:0] instr;

program_memory #(
    INSTR_ADDR_WIDTH,
    INSTR_WIDTH
) pm (
    .addr (PC_count),
    .instr(instr   )
);

// -- reg file
logic wr_res, we, we_p;
logic [REG_ADDR_WIDTH-1:0] wr_addr, wr_addr_p;
logic [BUS_WIDTH-1:0] data_a, data_b;
logic [BUS_WIDTH-1:0] rd_data_a, rd_data_b;

always_ff @(posedge clk) 
begin
    we        <= wr_res;
    we_p      <= we;
    wr_addr   <= instr[8:6];
    wr_addr_p <= wr_addr;
end

register_file #(
    BUS_WIDTH,
    REG_ADDR_WIDTH
) rf (
	.clk          (clk       ),  
    .we           (we_p      ),
 	.wr_addr      (wr_addr_p ),
	.wr_data      (ALU_result),
 	.rd_addr_a    (instr[4:3]), 
    .rd_addr_b    (instr[1:0]),
 	.rd_data_a    (data_a    ), 
    .rd_data_b    (data_b    )
);

logic [REG_ADDR_WIDTH-1:0] addr_a_p, addr_b_p;
logic pattern_match_p;
always_ff @(posedge clk)
begin
    addr_a_p <= instr[4:3];
    addr_b_p <= instr[1:0];
end 

// multiplex the rd_data_a output based on the asked for addr
always_comb
begin
	if(addr_a_p == 0)
		rd_data_a = sw_pp;
	else 
        rd_data_a = data_a;
end

// multiplex the rd_data_b output based on the asked for addr
always_comb
begin
	if (addr_b_p == 0)
		rd_data_b = sw_pp;
	else
        rd_data_b = data_b;
end

// -- decoder
logic f_add, PC_wait;
logic [4:0] reg_en; 

instruction_decoder #(
    OPCODE_WIDTH
) id (
    .opcode    (instr[11:9]),                  
    .f_add     (f_add      ), 
    .f_wait    (PC_wait    ),            
    .wr_res    (wr_res     ),         
    .ALU_reg_en(reg_en     )
);

// -- ALU
logic [BUS_WIDTH-1:0] ALU_result;
logic [BUS_WIDTH-1:0] ALU_imm;
logic [4:0]           ALU_reg_en; 
logic                 ALU_add;

always_ff @(posedge clk) begin
    ALU_imm    <= instr[7:0];
    ALU_add    <= f_add;
    ALU_reg_en <= reg_en;
end

ALU #(
    BUS_WIDTH
) alu (
    .clk    (clk                                          ),
    .ops    ({ALU_imm,ALU_imm,rd_data_b,ALU_imm,rd_data_a}),   
    .reg_en (ALU_reg_en                                   ),
    .f_add  (ALU_add                                      ),
    .result (ALU_result                                   )
);    

assign out_port = ALU_result;

endmodule

simulation/v3/CPU/mux_21.vcd
$date
	Sun Apr 16 11:32:39 2023
$end
$version
	Icarus Verilog
$end
$timescale
	1ps
$end
$scope module CPU $end
$scope module PC_en_mux $end
$var wire 1 ! a $end
$var wire 1 " b $end
$var wire 1 # s $end
$var wire 1 $ out $end
$upscope $end
$upscope $end
$scope module CPU $end
$scope module alu $end
$scope module e_mux $end
$var wire 8 % a [7:0] $end
$var wire 8 & b [7:0] $end
$var wire 1 ' s $end
$var wire 8 ( out [7:0] $end
$upscope $end
$upscope $end
$upscope $end
$scope module CPU $end
$scope module alu $end
$scope module m0 $end
$var wire 8 ) a [7:0] $end
$var wire 8 * b [7:0] $end
$var wire 8 + out [7:0] $end
$var reg 16 , mult_out [15:0] $end
$upscope $end
$upscope $end
$upscope $end
$scope module CPU $end
$scope module alu $end
$scope module m1 $end
$var wire 8 - a [7:0] $end
$var wire 8 . b [7:0] $end
$var wire 8 / out [7:0] $end
$var reg 16 0 mult_out [15:0] $end
$upscope $end
$upscope $end
$upscope $end
$scope module CPU $end
$scope module alu $end
$scope module a0 $end
$var wire 8 1 out [7:0] $end
$var wire 8 2 b [7:0] $end
$var wire 8 3 a [7:0] $end
$var reg 9 4 add_out [8:0] $end
$upscope $end
$upscope $end
$upscope $end
$scope module CPU $end
$scope module alu $end
$scope module a1 $end
$var wire 8 5 a [7:0] $end
$var wire 8 6 b [7:0] $end
$var wire 8 7 out [7:0] $end
$var reg 9 8 add_out [8:0] $end
$upscope $end
$upscope $end
$upscope $end
$scope module CPU $end
$var wire 1 9 PC_en $end
$var wire 1 : clk $end
$var wire 1 ; n_reset $end
$var wire 8 < out_port [7:0] $end
$var wire 1 " ready_in $end
$var wire 8 = sw [7:0] $end
$var wire 1 > wr_res $end
$var wire 5 ? reg_en [4:0] $end
$var wire 1 ! pattern_match $end
$var wire 12 @ instr [11:0] $end
$var wire 1 A f_add $end
$var wire 8 B data_b [7:0] $end
$var wire 8 C data_a [7:0] $end
$var wire 1 D PC_wait $end
$var wire 4 E PC_count [3:0] $end
$var wire 1 $ PC_comparator $end
$var wire 8 F ALU_result [7:0] $end
$var reg 1 ' ALU_add $end
$var reg 8 G ALU_imm [7:0] $end
$var reg 5 H ALU_reg_en [4:0] $end
$var reg 2 I addr_a_p [1:0] $end
$var reg 2 J addr_b_p [1:0] $end
$var reg 8 K rd_data_a [7:0] $end
$var reg 8 L rd_data_b [7:0] $end
$var reg 1 M ready_in_p $end
$var reg 8 N sw_p [7:0] $end
$var reg 8 O sw_pp [7:0] $end
$var reg 1 P we $end
$var reg 1 Q we_p $end
$var reg 2 R wr_addr [1:0] $end
$var reg 2 S wr_addr_p [1:0] $end
$scope module PC_en_mux $end
$upscope $end
$scope module alu $end
$var wire 1 : clk $end
$var wire 1 ' f_add $end
$var wire 40 T ops [39:0] $end
$var wire 5 U reg_en [4:0] $end
$var wire 8 V result [7:0] $end
$var wire 8 W op_e [7:0] $end
$var wire 8 X mult_b [7:0] $end
$var wire 8 Y mult_a [7:0] $end
$var wire 8 Z add_a [7:0] $end
$var reg 8 [ op_a_reg [7:0] $end
$var reg 8 \ op_b_reg [7:0] $end
$var reg 8 ] op_c_reg [7:0] $end
$var reg 8 ^ op_d_reg [7:0] $end
$var reg 8 _ op_e_reg [7:0] $end
$scope module a0 $end
$upscope $end
$scope module a1 $end
$upscope $end
$scope module e_mux $end
$upscope $end
$scope module m0 $end
$upscope $end
$scope module m1 $end
$upscope $end
$upscope $end
$scope module id $end
$var wire 3 ` opcode [2:0] $end
$var reg 5 a ALU_reg_en [4:0] $end
$var reg 1 A f_add $end
$var reg 1 D f_wait $end
$var reg 1 > wr_res $end
$upscope $end
$scope module pc $end
$var wire 1 : clk $end
$var wire 1 9 en $end
$var wire 1 ; n_reset $end
$var reg 4 b count [3:0] $end
$upscope $end
$scope module pm $end
$var wire 4 c addr [3:0] $end
$var reg 12 d instr [11:0] $end
$upscope $end
$scope module rf $end
$var wire 1 : clk $end
$var wire 2 e rd_addr_a [1:0] $end
$var wire 2 f rd_addr_b [1:0] $end
$var wire 1 Q we $end
$var wire 2 g wr_addr [1:0] $end
$var wire 8 h wr_data [7:0] $end
$var reg 8 i rd_data_a [7:0] $end
$var reg 8 j rd_data_b [7:0] $end
$scope begin $ivl_for_loop0 $end
$var integer 32 k i [31:0] $end
$upscope $end
$upscope $end
$upscope $end
$enddefinitions $end
#0
$dumpvars
b100 k
bx j
bx i
bx h
bx g
b1 f
b1 e
b10000001001 d
b0 c
b0 b
b0 a
b10 `
bx _
bx ^
bx ]
bx \
bx [
bx Z
bx Y
bx X
bx W
bx V
b0 U
bx T
bx S
bx R
xQ
0P
bx O
b0 N
0M
bx L
bx K
bx J
bx I
b0 H
bx G
bx F
b0 E
1D
bx C
bx B
0A
b10000001001 @
b0 ?
0>
b0 =
bx <
0;
1:
09
bx 8
bx 7
bx 6
bx 5
bx 4
bx 3
bx 2
bx 1
bx 0
bx /
bx .
bx -
bx ,
bx +
bx *
bx )
bx (
0'
bx &
bx %
0$
1#
0"
0!
$end
#5000
0:
#10000
b1001 (
b1001 W
b0 %
b1001 &
b0 K
b0 L
b100100001001000000000000100100000000 T
b1001 G
b1 J
b1 I
b0 R
0Q
b0 O
b0 C
b0 i
b0 B
b0 j
1:
#15000
0:
#20000
1;
b0 S
b0 g
1:
#25000
0:
#30000
1:
#35000
0:
#40000
1:
#45000
0:
#50000
1:
#55000
0:
#60000
1:
#65000
0:
#70000
1:
#75000
0:
#80000
1:
#85000
0:
#90000
1:
#95000
0:
#100000
1:
#105000
0:
#110000
1:
#115000
0:
#120000
19
1$
1!
1"
b1010011 =
1:
#125000
0:
#130000
0"
b11111 ?
b11111 a
1>
0D
1A
b0 `
b0 f
b0 e
0#
0$
b1000000 @
b1000000 d
b1010011 N
0!
1M
b1 E
b1 b
b1 c
1:
#135000
0:
#140000
09
b0 ?
b0 a
0>
1D
0A
b10 `
b1 f
b1 e
1#
b1010011 %
b1010011 L
b10000001001 @
b10000001001 d
b1010011 K
b1010011 (
b1010011 W
b1000000 &
b10 E
b10 b
b10 c
0M
b1010011 O
b1 R
1P
b0 J
b0 I
b11111 H
b11111 U
1'
b100000001000000010100110100000001010011 T
b1000000 G
1:
#145000
0:
#150000
b1010011 <
b1010011 7
b1010011 F
b1010011 V
b1010011 h
b1010011 8
b0 1
b0 5
b0 Z
b0 4
b0 %
b0 /
b0 2
b0 X
b0 +
b0 3
b0 Y
b1001 (
b1001 W
b1001 &
b0 L
b0 K
b0 0
b0 ,
b0 H
b0 U
0'
b100100001001000000000000100100000000 T
b1001 G
b1 J
b1 I
b1 S
b1 g
b0 R
1Q
0P
b1010011 6
b1010011 _
b0 .
b0 ^
b1010011 -
b1010011 ]
b0 *
b0 \
b1010011 )
b1010011 [
1:
#155000
0:
#160000
b0 S
b0 g
0Q
1:
#165000
0:
#170000
b1010011 %
b1010011 K
b100100001001010100110000100101010011 T
b1010011 L
b1010011 C
b1010011 i
b1010011 B
b1010011 j
1:
#175000
0:
#180000
1:
#185000
0:
#190000
19
1$
1!
1"
b1011010 =
1:
#195000
0:
#200000
0"
b11111 ?
b11111 a
1>
0D
1A
b0 `
b0 f
b0 e
0#
b10000000 @
b10000000 d
0$
b11 E
b11 b
b11 c
0!
1M
b1011010 N
1:
#205000
0:
#210000
b10 ?
b10 a
0>
0A
b1011010 %
b11 `
b1011010 (
b1011010 W
b10000000 &
b1011010 K
b1011010 L
b11001100000 @
b11001100000 d
b11111 H
b11111 U
1'
b1000000010000000010110101000000001011010 T
b10000000 G
b0 J
b0 I
b10 R
1P
b1011010 O
0M
b0 C
b0 i
b0 B
b0 j
b100 E
b100 b
b100 c
1:
#215000
0:
#220000
b1000 ?
b1000 a
b100 `
b1011010 <
b1011010 7
b1011010 F
b1011010 V
b1011010 h
b100001000000 @
b100001000000 d
b1011010 8
b1100000 (
b1100000 W
b1100000 &
b101 E
b101 b
b101 c
b1011010 )
b1011010 [
b1011010 -
b1011010 ]
b1011010 6
b1011010 _
b10 S
b10 g
b1 R
1Q
0P
b10 H
b10 U
0'
b110000001100000010110100110000001011010 T
b1100000 G
1:
#225000
0:
#230000
b10011101 <
b10011101 7
b10011101 F
b10011101 V
b10011101 h
b10011101 8
b1000011 1
b1000011 5
b1000011 Z
b1000011 4
b10000 ?
b10000 a
b1000000 (
b1000000 W
b1000011 +
b1000011 3
b1000011 Y
b101 `
b10 e
b1000000 &
b10000111000000 ,
b101000010100 @
b101000010100 d
b1000 H
b1000 U
b100000001000000010110100100000001011010 T
b1000000 G
b1 S
b1 g
0Q
b1100000 *
b1100000 \
b110 E
b110 b
b110 c
1:
#235000
0:
#240000
b11001010 <
b11001010 7
b11001010 F
b11001010 V
b11001010 h
b11001010 8
b1110000 1
b1110000 5
b1110000 Z
b101 ?
b101 a
1>
b1110000 4
b1 `
b10 f
b1 e
1#
b101101 /
b101101 2
b101101 X
b10100 (
b10100 W
b1011001010 @
b1011001010 d
b1011010000000 0
b10100 &
b111 E
b111 b
b111 c
b1011010 C
b1011010 i
b1000000 .
b1000000 ^
b0 R
b10 I
b10000 H
b10000 U
b1010000010100010110100001010001011010 T
b10100 G
1:
#245000
0:
#250000
b10 ?
b10 a
0>
b11001010 (
b11001010 W
b10000100 <
b10000100 7
b10000100 F
b10000100 V
b10000100 h
b1010011 %
b11 `
b0 f
b0 e
0#
b11001010 &
b10000100 8
b1010011 K
b11011000000 @
b11011000000 d
b101 H
b101 U
b1100101011001010010110101100101001010011 T
b11001010 G
b10 J
b1 I
b0 S
b0 g
b11 R
1P
b10100 6
b10100 _
b1010011 C
b1010011 i
b1011010 B
b1011010 j
b1000 E
b1000 b
b1000 c
1:
#255000
0:
#260000
b1111111 <
b1111111 7
b1111111 F
b1111111 V
b1111111 h
b1111111 8
b1101011 1
b1101011 5
b1101011 Z
b1000 ?
b1000 a
b1101011 4
b100 `
b111110 +
b111110 3
b111110 Y
b1011010 %
b11000000 (
b11000000 W
b100001100000 @
b100001100000 d
b1111100100000 ,
b1011010 K
b11000000 &
b1001 E
b1001 b
b1001 c
b0 C
b0 i
b0 B
b0 j
b1010011 )
b1010011 [
b11 S
b11 g
1Q
0P
b0 J
b0 I
b10 H
b10 U
b1100000011000000010110101100000001011010 T
b11000000 G
1:
#265000
0:
#270000
b10111 <
b10111 7
b10111 F
b10111 V
b10111 h
b10111 8
b11 1
b11 5
b11 Z
b11 4
b10000 ?
b10000 a
b1100000 (
b1100000 W
b11010110 +
b11010110 3
b11010110 Y
b101 `
b1 e
1#
b1100000 &
b1110101101000000 ,
b101011101100 @
b101011101100 d
b1000 H
b1000 U
b110000001100000010110100110000001011010 T
b1100000 G
b1 R
0Q
b11000000 *
b11000000 \
b1010 E
b1010 b
b1010 c
1:
#275000
0:
#280000
b101101 <
b101101 7
b101101 F
b101101 V
b101101 h
b101101 8
b11001 1
b11001 5
b11001 Z
b101 ?
b101 a
1>
b11001 4
b1 `
b10 f
b1000011 /
b1000011 2
b1000011 X
b1010011 %
b11101100 (
b11101100 W
b1010001010 @
b1010001010 d
b10000111000000 0
b1010011 K
b11101100 &
b1011 E
b1011 b
b1011 c
b1010011 C
b1010011 i
b1100000 .
b1100000 ^
b1 S
b1 g
b11 R
b1 I
b10000 H
b10000 U
b1110110011101100010110101110110001010011 T
b11101100 G
1:
#285000
0:
#290000
b11111 ?
b11111 a
1A
b10001010 (
b10001010 W
b101 <
b101 7
b101 F
b101 V
b101 h
b0 `
b0 f
b11 e
b10001010 &
b101 8
b1011000 @
b1011000 d
b101 H
b101 U
b1000101010001010010110101000101001010011 T
b10001010 G
b10 J
b11 S
b11 g
b10 R
1P
b11101100 6
b11101100 _
b1011010 B
b1011010 j
b1100 E
b1100 b
b1100 c
1:
#295000
0:
#300000
09
b0 ?
b0 a
0>
1D
0A
b10 `
b1 f
b0 e
0#
b1111111 %
b10000000001 @
b10000000001 d
b1111111 K
b1111111 (
b1111111 W
b1011000 &
b1101 E
b1101 b
b1101 c
b1111111 C
b1111111 i
b0 B
b0 j
b10 S
b10 g
b1 R
1Q
b0 J
b11 I
b11111 H
b11111 U
1'
b101100001011000010110100101100001111111 T
b1011000 G
1:
#305000
0:
#310000
b0 1
b0 5
b0 Z
b0 4
b0 +
b0 3
b0 Y
b0 /
b0 2
b0 X
b1111111 <
b1111111 7
b1111111 F
b1111111 V
b1111111 h
b1011010 %
b1 (
b1 W
b1 &
b0 ,
b0 0
b1111111 8
b1011010 K
b1010011 L
b0 H
b0 U
0'
b100000001010100110000000101011010 T
b1 G
b1 J
b0 I
b1 S
b1 g
b0 R
0P
b1111111 6
b1111111 _
b0 .
b0 ^
b0 *
b0 \
b1111111 )
b1111111 [
b0 C
b0 i
b1010011 B
b1010011 j
1:
#315000
0:
#320000
b0 S
b0 g
0Q
1:
#325000
0:
#330000
19
1$
1!
1"
b100000001011111110000000101011010 T
b1111111 L
b1111111 B
b1111111 j
1:
#335000
0:
#340000
b11111 ?
b11111 a
1>
0D
1A
b0 `
b0 f
b10 e
b1010000 @
b1010000 d
b1110 E
b1110 b
b1110 c
0!
1M
1:
#345000
0:
#350000
09
b0 ?
b0 a
0>
1D
0A
b101 %
b10 `
b0 e
b101 (
b101 W
b1010000 &
b101 K
b1011010 L
b10000000000 @
b10000000000 d
b11111 H
b11111 U
1'
b101000001010000010110100101000000000101 T
b1010000 G
b0 J
b10 I
b1 R
1P
b101 C
b101 i
b0 B
b0 j
b1111 E
b1111 b
b1111 c
1:
#355000
0:
#360000
b101 <
b101 7
b101 F
b101 V
b101 h
b1011010 %
b101 8
b1011010 K
b0 (
b0 W
b0 &
b0 C
b0 i
b101 )
b101 [
b101 6
b101 _
b1 S
b1 g
b0 R
1Q
0P
b0 I
b0 H
b0 U
0'
b10110100000000001011010 T
b0 G
1:
#365000
0:
#370000
b0 S
b0 g
0Q
1:
#375000
0:
#380000
19
0$
0"
1:
#385000
0:
#390000
09
b1 f
b1 e
1#
b10000001001 @
b10000001001 d
0M
b0 E
b0 b
b0 c
1:
#395000
0:
#400000
b101 %
b1001 (
b1001 W
b101 L
b101 K
b1001 &
b101 C
b101 i
b101 B
b101 j
b1 J
b1 I
b100100001001000001010000100100000101 T
b1001 G
1:
#405000
0:
#410000
1:
#415000
0:
#420000
1:
#425000
0:
#430000
19
1$
1!
1"
b11110001 =
1:
#435000
0:
#440000
0"
b11111 ?
b11111 a
1>
0D
1A
b0 `
b0 f
b0 e
0#
b1000000 @
b1000000 d
0$
b1 E
b1 b
b1 c
0!
1M
b11110001 N
1:
#445000
0:
#450000
09
b0 ?
b0 a
0>
1D
0A
b11110001 %
b10 `
b1 f
b1 e
1#
b11110001 (
b11110001 W
b1000000 &
b11110001 K
b11110001 L
b10000001001 @
b10000001001 d
b11111 H
b11111 U
1'
b100000001000000111100010100000011110001 T
b1000000 G
b0 J
b0 I
b1 R
1P
b11110001 O
0M
b0 C
b0 i
b0 B
b0 j
b10 E
b10 b
b10 c
1:
#455000
0:
#460000
b11110001 <
b11110001 7
b11110001 F
b11110001 V
b11110001 h
b101 %
b101 L
b111110001 8
b101 K
b1001 (
b1001 W
b1001 &
b101 C
b101 i
b101 B
b101 j
b11110001 )
b11110001 [
b11110001 -
b11110001 ]
b11110001 6
b11110001 _
b1 S
b1 g
b0 R
1Q
0P
b1 J
b1 I
b0 H
b0 U
0'
b100100001001000001010000100100000101 T
b1001 G
1:
#465000
0:
#470000
19
1$
1!
1"
b10010111 =
b0 S
b0 g
0Q
1:
#475000
0:
#480000
0"
b11111 ?
b11111 a
1>
0D
1A
b0 `
b0 f
b0 e
0#
b11110001 %
b10000000 @
b10000000 d
b11110001 K
b100100001001111100010000100111110001 T
b11110001 L
0$
b11 E
b11 b
b11 c
b11110001 C
b11110001 i
b11110001 B
b11110001 j
0!
1M
b10010111 N
1:
#485000
0:
#490000
b10 ?
b10 a
0>
0A
b10010111 %
b11 `
b10010111 (
b10010111 W
b10000000 &
b10010111 K
b10010111 L
b11001100000 @
b11001100000 d
b11111 H
b11111 U
1'
b1000000010000000100101111000000010010111 T
b10000000 G
b0 J
b0 I
b10 R
1P
b10010111 O
0M
b0 C
b0 i
b0 B
b0 j
b100 E
b100 b
b100 c
1:
#495000
0:
#500000
b1000 ?
b1000 a
b100 `
b10010111 <
b10010111 7
b10010111 F
b10010111 V
b10010111 h
b100001000000 @
b100001000000 d
b110010111 8
b1100000 (
b1100000 W
b1100000 &
b101 E
b101 b
b101 c
b10010111 )
b10010111 [
b10010111 -
b10010111 ]
b10010111 6
b10010111 _
b10 S
b10 g
b1 R
1Q
0P
b10 H
b10 U
0'
b110000001100000100101110110000010010111 T
b1100000 G
1:
#505000
0:
#510000
b1001000 <
b1001000 7
b1001000 F
b1001000 V
b1001000 h
b101001000 8
b10110001 1
b10110001 5
b10110001 Z
b110110001 4
b10000 ?
b10000 a
b1000000 (
b1000000 W
b10110001 +
b10110001 3
b10110001 Y
b101 `
b10 e
b1000000 &
b1101100010100000 ,
b101000010100 @
b101000010100 d
b1000 H
b1000 U
b100000001000000100101110100000010010111 T
b1000000 G
b1 S
b1 g
0Q
b1100000 *
b1100000 \
b110 E
b110 b
b110 c
1:
#515000
0:
#520000
b10011 <
b10011 7
b10011 F
b10011 V
b10011 h
b10011 8
b1111100 1
b1111100 5
b1111100 Z
b101 ?
b101 a
1>
b101111100 4
b1 `
b10 f
b1 e
1#
b11001011 /
b11001011 2
b11001011 X
b10100 (
b10100 W
b1011001010 @
b1011001010 d
b1110010111000000 0
b10100 &
b111 E
b111 b
b111 c
b10010111 C
b10010111 i
b1000000 .
b1000000 ^
b0 R
b10 I
b10000 H
b10000 U
b1010000010100100101110001010010010111 T
b10100 G
1:
#525000
0:
