rtl/v7/sfixed_adder.sv
import datatypes::max;

module sfixed_adder #(
    parameter A_LEFT    = 3, 
    parameter A_RIGHT   = 4, 
    parameter B_LEFT    = 3, 
    parameter B_RIGHT   = 4,
    parameter OUT_LEFT  = 4, 
    parameter OUT_RIGHT = 4
) (   
    input  logic signed [(A_LEFT+A_RIGHT+1)-1:0]     a,
    input  logic signed [(B_LEFT+B_RIGHT+1)-1:0]     b,
    output logic signed [(OUT_LEFT+OUT_RIGHT+1)-1:0] out
);

`ifdef COCOTB_SIM
initial begin
    $dumpfile ("sfixed_adder.vcd");
    $dumpvars (0, sfixed_adder);
    #1;
end
`endif

localparam OUTPUT_SIZE = (max(A_LEFT,B_LEFT)+1)+max(A_RIGHT,B_RIGHT)+1; 

logic signed [OUTPUT_SIZE-1:0] add_out;

always_comb
    add_out = a + b;

assign out = add_out[max(A_RIGHT,B_RIGHT)+OUT_LEFT:max(A_RIGHT,B_RIGHT)-OUT_RIGHT];

endmodule

rtl/v7/sfixed_mult.sv
module sfixed_mult #(
    parameter A_LEFT    = 3, 
    parameter A_RIGHT   = 4,
    parameter B_LEFT    = 3, 
    parameter B_RIGHT   = 4,
    parameter OUT_LEFT  = 7, 
    parameter OUT_RIGHT = 8
) (
    input  logic signed [(A_LEFT+A_RIGHT+1)-1:0]     a,
    input  logic signed [(B_LEFT+B_RIGHT+1)-1:0]     b,
    output logic signed [(OUT_LEFT+OUT_RIGHT+1)-1:0] out
);
`ifdef COCOTB_SIM
initial begin
    $dumpfile ("sfixed_mult.vcd");
    $dumpvars (0, sfixed_mult);
    #1;
end
`endif

localparam OUTPUT_SIZE = (A_LEFT+B_LEFT+1)+(A_RIGHT+B_RIGHT)+1; 
                                                                
logic signed [OUTPUT_SIZE-1:0] mult_out;

always_comb
    mult_out = a * b;

assign out = mult_out[(A_RIGHT+B_RIGHT)+OUT_LEFT:(A_RIGHT+B_RIGHT)-OUT_RIGHT];

endmodule

rtl/v6/mux_21.sv
module mux_21 #(
    parameter BIT_WIDTH = 8
) (   
    input  logic s, 
    input  logic [BIT_WIDTH-1:0] a, b,
    output logic [BIT_WIDTH-1:0] out
);
    `ifdef COCOTB_SIM
    initial begin
        $dumpfile ("mux_21.vcd");
        $dumpvars (0, mux_21);
        #1;
    end
    `endif 
    assign out = s ? a : b;
endmodule

rtl/v1/ALU.sv
//-----------------------------------------------------
// File Name   : alu.sv
// Function    : ALU module for picoMIPS
//-----------------------------------------------------
import datatypes::operand_pack_t;

module ALU #(
    parameter BUS_WIDTH  = 8
) (
    input  logic                      clock, n_reset,
    input  logic [4:0][BUS_WIDTH-1:0] ops,    
    input  logic [4:0]                reg_en,
    input  logic                      f_add,
    output logic [BUS_WIDTH-1:0]      result 
);       

// enable registered inputs
logic [4:0][BUS_WIDTH-1:0] ops_reg;

always_ff @(posedge clock) 
begin
    if (~n_reset) 
        ops_reg <= '0;
    else begin
        for (int i = 0; i < 5; i=i+1) begin
            if (reg_en[i] == 1'b1)
                ops_reg[i] <= ops[i];
        end
    end
end

// setting up of add/subtract inputs
logic [4:0][BUS_WIDTH-1:0] ops_in;

mux_21 #(
    BUS_WIDTH
) b_mux (   
    .s(f_add), 
    .a({1'b1, {BUS_WIDTH-1{1'b0}}}), 
    .b(ops_reg[1]),
    .out(ops_in[1])
);

mux_21 #(
    BUS_WIDTH
) d_mux (   
    .s(f_add), 
    .a({1'b1, {BUS_WIDTH-1{1'b0}}}), 
    .b(ops_reg[3]),
    .out(ops_in[3])
);

mux_21 #(
    BUS_WIDTH
) e_mux (   
    .s(f_add), 
    .a({BUS_WIDTH{1'b0}}), 
    .b(ops_reg[4]),
    .out(ops_in[4])
);

assign ops_in[0] = ops_reg[0];
assign ops_in[2] = ops_reg[2];

// the computational part
logic[BUS_WIDTH-1:0] mult_a, mult_b, add_a, add_b;
sfixed_mult #(
    7, 
    0,
    0, 
    7,
    7, 
    0
) m0 (
    .a(ops_in[0]), // int
    .b(ops_in[1]), // tf
    .out(mult_a)
);

sfixed_mult #(
    7, 
    0,
    0, 
    7,
    7, 
    0
) m1 (
    .a(ops_in[2]),  // int
    .b(ops_in[3]),  // tf
    .out(mult_b)
);

sfixed_adder #(
    7, 
    0, 
    7, 
    0,
    7, 
    0 
) a0 (   
    .a(mult_a), // int
    .b(mult_b), // int
    .out(add_a)
);

sfixed_adder #(
    7, 
    0, 
    7, 
    0,
    7, 
    0
) a1 (   
    .a(add_a),      // int
    .b(ops_in[4]),  // int
    .out(add_b)
);

assign result = f_add ? ~add_b + 1'b1 : add_b;

endmodule

include/opcodes.sv
//-----------------------------------------------------
// File Name : opcodes.sv
// Function : pMIPS instr opcode definitions
// Author: jf
//-----------------------------------------------------
//
`define NOP  6'b000000
`define ADD  6'b000001
`define SUB  6'b000010
`define ADDI 6'b000011
`define SUBI 6'b000100
`define BEQ  6'b000101
`define BNE  6'b000110
`define BGE  6'b000111
`define BLO  6'b001000

rtl/v1/instruction_decoder.sv
`include "opcodes.sv"

module instruction_decoder #(
    parameter OPCODE_WIDTH = 3
) (
    input  logic [OPCODE_WIDTH-1:0] opcode,                  
    output logic                    f_add,            
    output logic                    f_wait,            
    output logic                    wr_res,         
    output logic [4:0]              ALU_reg_en
);

always_comb 
begin
    case(opcode)    
        `ADD : begin
            f_add      = '1; 
            f_wait     = '0;
            wr_res     = '1; 
            ALU_reg_en = 5'b00101; // C, A
        end
        `MAC : begin 
            f_add      = '0;
            f_wait     = '0;
            wr_res     = '1; 
            ALU_reg_en = 5'b00101; // C, A
        end
        `WAIT: begin
            f_add      = '0;
            f_wait     = '1;
            wr_res     = '0;
            ALU_reg_en = 5'b00000;
        end
        `SETB: begin
            f_add      = '0;
            f_wait     = '0;
            wr_res     = '0;
            ALU_reg_en = 5'b00010; 
        end
        `SETD: begin
            f_add      = '0;
            f_wait     = '0;
            wr_res     = '0;
            ALU_reg_en = 5'b01000;
        end
        `SETE: begin
            f_add      = '0;
            f_wait     = '0;
            wr_res     = '0;
            ALU_reg_en = 5'b10000;
        end
        default : begin
            f_add      = '0;
            f_wait     = '0;
            wr_res     = '0;
            ALU_reg_en = '0;
        end
    endcase 
end 

endmodule

rtl/v1/register_file.sv
module register_file #(
    parameter BUS_WIDTH  = 8,
    parameter ADDR_WIDTH = 3
) (
	input  logic                  clock, we, 
	input  logic [BUS_WIDTH-1:0]  sw,
	input  logic 				  ready_in,
	input  logic 				  pattern_match,
 	input  logic [ADDR_WIDTH-1:0] wr_addr,
	input  logic [BUS_WIDTH-1:0]  wr_data,
 	input  logic [ADDR_WIDTH-1:0] rd_addr_a, rd_addr_b,
 	output logic [BUS_WIDTH-1:0]  rd_data_a, rd_data_b
);


localparam N = (1 << ADDR_WIDTH);

logic [BUS_WIDTH-1:0] gpr [N-1:0];

integer i;
initial 
begin
	for (i = 0; i < N; i = i + 1)
		gpr[i] = '0;
end

always_ff @ (posedge clock)
begin
	if (we) begin 
		gpr[wr_addr] <= wr_data;
	end
end

always_comb
begin
	if (rd_addr_a == 0)       // zero 
		rd_data_a = {BUS_WIDTH{1'b0}};
	else if (rd_addr_a == 1)	// sw 
		rd_data_a = sw;
	else if (rd_addr_a == 2)  // ready in
		rd_data_a = {{BUS_WIDTH-1{1'b0}}, ready_in};
	else if (rd_addr_a == 3)  // pattern match
		rd_data_a = {{BUS_WIDTH-1{1'b0}}, pattern_match};
	else  
		rd_data_a = gpr[rd_addr_a];
end

always_comb
begin
	if (rd_addr_b == 0)       // zero 
		rd_data_b = {BUS_WIDTH{1'b0}};
	else if (rd_addr_b == 1)	// sw 
		rd_data_b = sw;
	else if (rd_addr_b == 2)  // ready in
		rd_data_b = {{BUS_WIDTH-1{1'b0}}, ready_in};
	else if (rd_addr_b == 3)  // pattern match
		rd_data_b = {{BUS_WIDTH-1{1'b0}}, pattern_match};
	else  
		rd_data_b = gpr[rd_addr_b];
end

endmodule

rtl/v1/program_memory.sv
module program_memory #(
    parameter ADDR_WIDTH  = 4,
    parameter INSTR_WIDTH = 12
) (
    input  logic [ADDR_WIDTH-1:0]  addr,
    output logic [INSTR_WIDTH-1:0] instr
); 

logic [INSTR_WIDTH-1:0] prog_mem [(1<<ADDR_WIDTH)-1:0];

initial
    $readmemh("/home/jonahfoley/ELEC6234/a_fine_CPU/programs/prog.hex", prog_mem);
   
always_comb
    instr = prog_mem[addr]; 
  
endmodule

rtl/v1/program_counter.sv
module program_counter #(
    parameter ADDR_WIDTH = 3
) (
    input  logic                  clock, n_reset,
    input  logic                  en,
    output logic [ADDR_WIDTH-1:0] count
);
 
always_ff @(posedge clock) 
begin
    if (~n_reset) 
        count <= '0;
    else begin
        if (count == (2<<ADDR_WIDTH)-1) 
            count <= '0;
        else begin
            if (en)
                count <= count + { {ADDR_WIDTH-1{1'b0}}, 1'b1 };
        end
    end
end


endmodule

rtl/v1/CPU.sv
module CPU #(
    parameter INSTR_WIDTH      = 12,
    parameter OPCODE_WIDTH     = 3,
    parameter INSTR_ADDR_WIDTH = 4, 
    parameter REG_ADDR_WIDTH   = 3, 
    parameter BUS_WIDTH        = 8
) (
    input  logic                 clock,  
    input  logic                 n_reset,
    input  logic [BUS_WIDTH-1:0] sw,
    input  logic                 ready_in,
    output logic [BUS_WIDTH-1:0] out_port
);       

//the "macro" to dump signals   
`ifdef COCOTB_SIM
initial begin
    $dumpfile ("CPU.vcd");
    $dumpvars (0, CPU);
    #1;
end
`endif

// input switch handshaking
logic ready_in_p, pattern_match;
always_ff @(posedge clock)
    ready_in_p <= ready_in;

logic [BUS_WIDTH-1:0] sw_p;
always_ff @(posedge clock)
    sw_p <= sw;

assign pattern_match = ({ready_in_p, ready_in} == 2'b01);

// -- instr counter
logic [INSTR_ADDR_WIDTH-1:0] PC_count;
logic PC_en;
assign PC_en  = (PC_wait & ~(rd_data_a[0] ^ instr[0])) | ~PC_wait;

program_counter #(
   INSTR_ADDR_WIDTH
) pc (
   .clock(clock),
   .n_reset(n_reset),
   .en(PC_en),
   .count(PC_count)
);

// program ROM
logic [INSTR_WIDTH-1:0] instr;

program_memory #(
    INSTR_ADDR_WIDTH,
    INSTR_WIDTH
) pm (
    .addr(PC_count),
    .instr(instr)
);

// -- reg file
logic wr_res, wr_res_p;
logic [REG_ADDR_WIDTH-1:0] wr_addr;
logic [BUS_WIDTH-1:0] rd_data_a, rd_data_b;

always_ff @(posedge clock) 
begin
    wr_res_p <= wr_res;
    wr_addr  <= instr[8:6];
end

register_file #(
    BUS_WIDTH,
    REG_ADDR_WIDTH
) rf (
	.clock(clock),  
	.sw(sw_p),
    .ready_in(ready_in),
	.pattern_match(pattern_match),
    .we(wr_res_p),
 	.wr_addr(wr_addr),
	.wr_data(ALU_result),
 	.rd_addr_a(instr[5:3]), 
    .rd_addr_b(instr[2:0]),
 	.rd_data_a(rd_data_a), 
    .rd_data_b(rd_data_b)
);

// -- decoder
logic ALU_add, ALU_add_p, PC_wait;

instruction_decoder #(
    OPCODE_WIDTH
) id (
    .opcode(instr[11:9]),                  
    .f_add(ALU_add), 
    .f_wait(PC_wait),            
    .wr_res(wr_res),         
    .ALU_reg_en(ALU_reg_en)
);

// -- ALU
logic [BUS_WIDTH-1:0] ALU_result;
logic [4:0] ALU_reg_en; 

always_ff @(posedge clock)
    ALU_add_p <= ALU_add;

ALU #(
    BUS_WIDTH
) alu (
    .clock(clock),
    .n_reset(n_reset),
    .ops({instr[7:0],instr[7:0],rd_data_b,instr[7:0],rd_data_a}),   
    .reg_en(ALU_reg_en),
    .f_add(ALU_add_p),
    .result(ALU_result)
);    

assign out_port = '0;

endmodule

simulation/v1/CPU/mux_21.vcd
$date
	Sat Apr 15 20:37:34 2023
$end
$version
	Icarus Verilog
$end
$timescale
	1ps
$end
$scope module CPU $end
$scope module alu $end
$scope module b_mux $end
$var wire 8 ! a [7:0] $end
$var wire 8 " b [7:0] $end
$var wire 1 # s $end
$var wire 8 $ out [7:0] $end
$upscope $end
$upscope $end
$upscope $end
$scope module CPU $end
$scope module alu $end
$scope module d_mux $end
$var wire 8 % a [7:0] $end
$var wire 8 & b [7:0] $end
$var wire 1 # s $end
$var wire 8 ' out [7:0] $end
$upscope $end
$upscope $end
$upscope $end
$scope module CPU $end
$scope module alu $end
$scope module e_mux $end
$var wire 8 ( a [7:0] $end
$var wire 8 ) b [7:0] $end
$var wire 1 # s $end
$var wire 8 * out [7:0] $end
$upscope $end
$upscope $end
$upscope $end
$scope module CPU $end
$scope module alu $end
$scope module m0 $end
$var wire 8 + a [7:0] $end
$var wire 8 , b [7:0] $end
$var wire 8 - out [7:0] $end
$var reg 16 . mult_out [15:0] $end
$upscope $end
$upscope $end
$upscope $end
$scope module CPU $end
$scope module alu $end
$scope module m1 $end
$var wire 8 / a [7:0] $end
$var wire 8 0 b [7:0] $end
$var wire 8 1 out [7:0] $end
$var reg 16 2 mult_out [15:0] $end
$upscope $end
$upscope $end
$upscope $end
$scope module CPU $end
$scope module alu $end
$scope module a0 $end
$var wire 8 3 out [7:0] $end
$var wire 8 4 b [7:0] $end
$var wire 8 5 a [7:0] $end
$var reg 9 6 add_out [8:0] $end
$upscope $end
$upscope $end
$upscope $end
$scope module CPU $end
$scope module alu $end
$scope module a1 $end
$var wire 8 7 a [7:0] $end
$var wire 8 8 b [7:0] $end
$var wire 8 9 out [7:0] $end
$var reg 9 : add_out [8:0] $end
$upscope $end
$upscope $end
$upscope $end
$scope module CPU $end
$var wire 1 ; PC_en $end
$var wire 1 < clock $end
$var wire 1 = n_reset $end
$var wire 8 > out_port [7:0] $end
$var wire 1 ? ready_in $end
$var wire 8 @ sw [7:0] $end
$var wire 1 A wr_res $end
$var wire 8 B rd_data_b [7:0] $end
$var wire 8 C rd_data_a [7:0] $end
$var wire 1 D pattern_match $end
$var wire 12 E instr [11:0] $end
$var wire 1 F PC_wait $end
$var wire 4 G PC_count [3:0] $end
$var wire 8 H ALU_result [7:0] $end
$var wire 5 I ALU_reg_en [4:0] $end
$var wire 1 J ALU_add $end
$var reg 1 # ALU_add_p $end
$var reg 1 K ready_in_p $end
$var reg 8 L sw_p [7:0] $end
$var reg 3 M wr_addr [2:0] $end
$var reg 1 N wr_res_p $end
$scope module alu $end
$var wire 1 < clock $end
$var wire 1 # f_add $end
$var wire 1 = n_reset $end
$var wire 40 O ops [39:0] $end
$var wire 8 P result [7:0] $end
$var wire 5 Q reg_en [4:0] $end
$var wire 40 R ops_in [39:0] $end
$var wire 8 S mult_b [7:0] $end
$var wire 8 T mult_a [7:0] $end
$var wire 8 U add_b [7:0] $end
$var wire 8 V add_a [7:0] $end
$var reg 40 W ops_reg [39:0] $end
$scope module a0 $end
$upscope $end
$scope module a1 $end
$upscope $end
$scope module b_mux $end
$upscope $end
$scope module d_mux $end
$upscope $end
$scope module e_mux $end
$upscope $end
$scope module m0 $end
$upscope $end
$scope module m1 $end
$upscope $end
$scope begin $ivl_for_loop0 $end
$var integer 32 X i [31:0] $end
$upscope $end
$upscope $end
$scope module id $end
$var wire 3 Y opcode [2:0] $end
$var reg 5 Z ALU_reg_en [4:0] $end
$var reg 1 J f_add $end
$var reg 1 F f_wait $end
$var reg 1 A wr_res $end
$upscope $end
$scope module pc $end
$var wire 1 < clock $end
$var wire 1 ; en $end
$var wire 1 = n_reset $end
$var reg 4 [ count [3:0] $end
$upscope $end
$scope module pm $end
$var wire 4 \ addr [3:0] $end
$var reg 12 ] instr [11:0] $end
$upscope $end
$scope module rf $end
$var wire 1 < clock $end
$var wire 1 D pattern_match $end
$var wire 3 ^ rd_addr_a [2:0] $end
$var wire 3 _ rd_addr_b [2:0] $end
$var wire 1 ? ready_in $end
$var wire 8 ` sw [7:0] $end
$var wire 1 N we $end
$var wire 3 a wr_addr [2:0] $end
$var wire 8 b wr_data [7:0] $end
$var reg 8 c rd_data_a [7:0] $end
$var reg 8 d rd_data_b [7:0] $end
$var integer 32 e i [31:0] $end
$upscope $end
$upscope $end
$enddefinitions $end
#0
$dumpvars
b1000 e
b0 d
b0 c
b0 b
bx a
b0 `
b1 _
b11 ^
b10000011001 ]
b0 \
b0 [
b0 Z
b10 Y
b0 X
b0 W
b0 V
b0 U
b0 T
b0 S
b0 R
b0 Q
b0 P
b1100100011001000000000001100100000000 O
0N
bx M
b0 L
0K
0J
b0 I
b0 H
b0 G
1F
b10000011001 E
0D
b0 C
b0 B
0A
b0 @
0?
b0 >
0=
1<
0;
b0 :
b0 9
b0 8
b0 7
b0 6
b0 5
b0 4
b0 3
b0 2
b0 1
b0 0
b0 /
b0 .
b0 -
b0 ,
b0 +
b0 *
b0 )
b0 (
b0 '
b0 &
b10000000 %
b0 $
0#
b0 "
b10000000 !
$end
#5000
0<
#10000
b0 M
b0 a
1<
#15000
0<
#20000
1;
b1100100011001000000000001100100000001 O
b1 C
b1 c
1D
1?
b1000000 @
1=
1<
#25000
0<
#30000
b101 I
b101 Q
b101 Z
1A
0F
1J
b0 Y
b0 _
b1 ^
b0 B
b0 d
b100000001000000000000000100001000000 O
b1000000 C
b1000000 c
b100001000 E
b100001000 ]
b1000000 L
b1000000 `
0D
1K
b1 G
b1 [
b1 \
b101 X
1<
#35000
0<
#40000
b100 @
b1000000 H
b1000000 P
b1000000 b
b11000000 9
b11000000 U
b111000000 :
0;
b11000000 3
b11000000 7
b11000000 V
b111000000 6
b11000000 -
b11000000 5
b11000000 T
b0 C
b0 c
b1000000 B
b1000000 d
b0 I
b0 Q
b0 Z
0A
1F
0J
b1110000000000000 .
b1000000 +
b1100100011001010000000001100100000000 O
b10 Y
b1 _
b11 ^
b10000000 ,
b10000000 0
b10000011001 E
b10000011001 ]
b10000000 $
b10000000000000001000000001000000 R
b10000000 '
b1000000 W
b10 G
b10 [
b10 \
b100 M
b100 a
1N
1#
b101 X
1<
#45000
0<
#50000
b110 @
b0 9
b0 U
b0 :
b0 3
b0 7
b0 V
b0 6
b0 -
b0 5
b0 T
b0 .
b0 ,
b0 0
b0 H
b0 P
b0 b
b0 $
b1000000 R
b0 '
b1100100011001000001000001100100000000 O
b100 B
b100 d
0#
b0 M
b0 a
0N
b100 L
b100 `
b101 X
1<
#55000
0<
#60000
0?
b101 @
b1100100011001000001100001100100000000 O
b110 B
b110 d
b110 L
b110 `
b101 X
1<
#65000
0<
#70000
b1 @
b1100100011001000001010001100100000000 O
b101 B
b101 d
b101 L
b101 `
0K
b101 X
1<
#75000
0<
#80000
b1000000 @
b1100100011001000000010001100100000000 O
b1 B
b1 d
b1 L
b1 `
b101 X
1<
#85000
0<
#90000
1;
b1 C
b1 c
1D
1?
b1100100011001010000000001100100000001 O
b1000000 B
b1000000 d
b1000000 L
b1000000 `
b101 X
1<
#95000
0<
#100000
b100 @
b101 I
b101 Q
b101 Z
1A
0F
1J
b0 B
b0 d
b0 Y
b0 _
b1 ^
b101001000 E
b101001000 ]
b100100001001000000000000100100001000000 O
b1000000 C
b1000000 c
b11 G
b11 [
b11 \
0D
1K
b101 X
1<
#105000
0<
#110000
b110 @
b1000000 H
b1000000 P
b1000000 b
b11000000 9
b11000000 U
b111000000 :
b11000000 3
b11000000 7
b11000000 V
b111000000 6
b11000000 -
b11000000 5
b11000000 T
b1110000000000000 .
b10 I
b10 Q
b10 Z
0A
0J
b10000000 ,
b10000000 0
b11 Y
b0 ^
b10000000 $
b10000000000000001000000001000000 R
b10000000 '
b100000001000000000000000100000000000000 O
b0 C
b0 c
b11001000000 E
b11001000000 ]
1#
b101 M
b101 a
1N
b100 L
b100 `
b100 G
b100 [
b100 \
b101 X
1<
#115000
0<
#120000
0?
b101 @
b100000 9
b100000 U
b100000 :
b100000 3
b100000 7
b100000 V
b100000 6
b100000 -
b100000 5
b100000 T
b1000000 C
b1000000 c
b1000 I
b1000 Q
b1000 Z
b1000000000000 .
b110000001100000000000000110000001000000 O
b100 Y
b100 ^
b1000000 ,
b0 0
b1000000 "
b100001100000 E
b100001100000 ]
b100000 H
b100000 P
b100000 b
b1000000 $
b100000001000000 R
b0 '
b100000001000000 W
b101 G
b101 [
b101 \
b110 L
b110 `
b1 M
b1 a
0N
0#
b101 X
1<
#125000
0<
#130000
b1 @
b1100000 0
b10000 I
b10000 Q
b10000 Z
b101 C
b101 c
b1100000000000000100000001000000 R
b1100000 '
b101000001010000000000000101000000101 O
b101 Y
b10 _
b1 ^
b1100000 &
b101000001010 E
b101000001010 ]
b1100000000000000100000001000000 W
b101 L
b101 `
0K
b110 G
b110 [
b110 \
b101 X
1<
#135000
0<
#140000
1D
1?
b1000000 @
b101010 H
b101010 P
b101010 b
b101010 9
b101010 U
b101010 :
b1010 8
b101 I
b101 Q
b101 Z
1A
b1000000 B
b1000000 d
b101001100000000000000100000001000000 R
b1010 *
b1 Y
b101 _
b100 ^
b1010 )
b1110100101 E
b1110100101 ]
b1010010110100101010000001010010101000000 O
b1000000 C
b1000000 c
b101001100000000000000100000001000000 W
b111 G
b111 [
b111 \
b1 L
b1 `
b0 M
b0 a
b101 X
1<
#145000
0<
#150000
0?
b1011010 H
b1011010 P
b1011010 b
b1011010 9
b1011010 U
b1011010 :
b1010000 3
b1010000 7
b1010000 V
b1010000 6
b110000 1
b110000 4
b110000 S
b1100000000000 2
b10 I
b10 Q
b10 Z
0A
b0 B
b0 d
b1000000 /
b110000001100000000000000110000001000000 O
b11 Y
b0 _
b101001100000010000000100000001000000 R
b11001100000 E
b11001100000 ]
b101001100000010000000100000001000000 W
b110 M
b110 a
1N
b1000000 L
b1000000 `
0D
1K
b1000 G
b1000 [
b1000 \
b101 X
1<
#155000
0<
#160000
b100 @
b1101010 H
b1101010 P
b1101010 b
b1101010 9
b1101010 U
b1101010 :
b1100000 3
b1100000 7
b1100000 V
b1100000 6
b110000 -
b110000 5
b110000 T
b1100000000000 .
b1100000 ,
b101001100000010000000110000001000000 R
b1100000 $
b1100000 "
b101001100000010000000110000001000000 W
b1001 G
b1001 [
b1001 \
0K
b1 M
b1 a
0N
b101 X
1<
#165000
0<
#170000
1D
1?
b110 @
b10000 I
b10000 Q
b10000 Z
b1000000 B
b1000000 d
b1 C
b1 c
b1010000010100010000000001010000000001 O
b101 Y
b100 _
b10 ^
b101000010100 E
b101000010100 ]
b100 L
b100 `
b1010 G
b1010 [
b1010 \
b101 X
1<
#175000
0<
#180000
0?
b101 @
b1110100 H
b1110100 P
b1110100 b
b1110100 9
b1110100 U
b1110100 :
b10100 8
b101 I
b101 Q
b101 Z
1A
b1000000 C
b1000000 c
b1010001100000010000000110000001000000 R
b10100 *
b110010101100101010000000110010101000000 O
b1 Y
b101 _
b100 ^
b10100 )
b1101100101 E
b1101100101 ]
b1010001100000010000000110000001000000 W
b1011 G
b1011 [
b1011 \
0D
1K
b110 L
b110 `
b0 M
b0 a
b101 X
1<
#185000
0<
#190000
b1 @
1J
b0 B
b0 d
b1011010 C
b1011010 c
b1111000011110000000000001111000001011010 O
b0 Y
b0 _
b110 ^
b111110000 E
b111110000 ]
b101 M
b101 a
1N
b101 L
b101 `
0K
b1100 G
b1100 [
b1100 \
b101 X
1<
#195000
0<
#200000
b1000000 @
0;
b10100110 3
b10100110 7
b10100110 V
b110100110 6
b10100110 -
b10100110 5
b10100110 T
b0 1
b0 4
b0 S
b10100110 9
b10100110 U
b0 C
b0 c
b1 B
b1 d
b0 I
b0 Q
b0 Z
0A
1F
0J
b1101001100000000 .
b0 2
b110100110 :
b0 /
b1011010 +
b1000100010001000000010001000100000000 O
b10 Y
b1 _
b10 ^
b10000000 ,
b10000000 0
b0 8
b10000010001 E
b10000010001 ]
b1011010 H
b1011010 P
b1011010 b
b10000000 $
b10000000 '
b10000000000000001000000001011010 R
b0 *
b1010001100000000000000110000001011010 W
b1101 G
b1101 [
b1101 \
b1 L
b1 `
b111 M
b111 a
1#
b101 X
1<
#205000
0<
#210000
b1000011 3
b1000011 7
b1000011 V
b1000011 6
b1000011 -
b1000011 5
b1000011 T
b1010111 9
b1010111 U
b10000111000000 .
b1010111 :
b1100000 ,
b1100000 0
b10100 8
b1010111 H
b1010111 P
b1010111 b
b1100000 $
b1100000 '
b1010001100000000000000110000001011010 R
b10100 *
b1000100010001010000000001000100000000 O
b1000000 B
b1000000 d
0#
b0 M
b0 a
0N
b1000000 L
b1000000 `
b101 X
1<
#215000
0<
#220000
1;
b1000100010001010000000001000100000001 O
b1 C
b1 c
1D
1?
b100 @
b101 X
1<
#225000
0<
#230000
b110 @
b101 I
b101 Q
b101 Z
1A
0F
1J
b1110100 C
b1110100 c
b0 Y
b0 _
b101 ^
b1110100011101000000000001110100001110100 O
b0 B
b0 d
b111101000 E
b111101000 ]
b100 L
b100 `
0D
1K
b1110 G
b1110 [
b1110 \
b101 X
1<
#235000
0<
#240000
b101 @
0;
b10001100 3
b10001100 7
b10001100 V
b110001100 6
b10001100 -
b10001100 5
b10001100 T
b10001100 9
b10001100 U
b1 C
b1 c
b0 I
b0 Q
b0 Z
0A
1F
0J
b1100011000000000 .
b110001100 :
b1110100 +
b1000000010000000000000001000000000001 O
b10 Y
b10 ^
b10000000 ,
b10000000 0
b0 8
b10000010000 E
b10000010000 ]
b1110100 H
b1110100 P
b1110100 b
b10000000 $
b10000000 '
b10000000000000001000000001110100 R
b0 *
b1010001100000000000000110000001110100 W
b1111 G
b1111 [
b1111 \
b110 L
b110 `
b111 M
b111 a
1N
1#
b101 X
1<
#245000
0<
#250000
b1 @
b1010111 3
b1010111 7
b1010111 V
b1010111 6
b1010111 -
b1010111 5
b1010111 T
b1101011 9
b1101011 U
b10101110000000 .
b1101011 :
b1100000 ,
b1100000 0
b10100 8
b1101011 H
b1101011 P
b1101011 b
b1100000 $
b1100000 '
b1010001100000000000000110000001110100 R
b10100 *
0#
b0 M
b0 a
0N
b101 L
b101 `
b101 X
1<
#255000
0<
#260000
b1000000 @
b1 L
b1 `
b101 X
1<
#265000
0<
#270000
b1000000 L
b1000000 `
b101 X
1<
#275000
0<
#280000
1;
b1000000010000000000000001000000000000 O
b0 C
b0 c
0?
b100 @
b101 X
1<
#285000
0<
#290000
b1 C
b1 c
1D
1?
b110 @
1;
b100 B
b100 d
b1100100011001000001000001100100000001 O
b1 _
b11 ^
b10000011001 E
b10000011001 ]
b100 L
b100 `
0K
b0 G
b0 [
b0 \
b101 X
1<
#295000
0<
#300000
0?
b101 @
b101 I
b101 Q
b101 Z
1A
0F
1J
b0 Y
b0 _
b1 ^
b0 B
b0 d
b100001000 E
b100001000 ]
b100000001000000000000000100000000110 O
b110 C
b110 c
b1 G
b1 [
b1 \
0D
1K
b110 L
b110 `
b101 X
1<
#305000
0<
#310000
1D
1?
b1 @
1;
b11111010 3
b11111010 7
b11111010 V
b111111010 6
b11111010 -
b11111010 5
b11111010 T
b11111010 9
b11111010 U
b1111110100000000 .
b111111010 :
b0 I
b0 Q
b0 Z
0A
1F
0J
b101 B
b101 d
b110 +
b10000000 ,
b10000000 0
b0 8
b10 Y
b1 _
b11 ^
b110 H
b110 P
b110 b
b10000000 $
b10000000 '
b10000000000000001000000000000110 R
b0 *
b1100100011001000001010001100100000001 O
b1 C
b1 c
b10000011001 E
b10000011001 ]
b1010001100000000000000110000000000110 W
1#
b100 M
b100 a
1N
b101 L
b101 `
0K
b10 G
b10 [
b10 \
b101 X
1<
#315000
0<
#320000
0?
b1000000 @
b100 3
b100 7
b100 V
b100 6
b100 -
b100 5
b100 T
b11000 9
b11000 U
b101 I
b101 Q
b101 Z
1A
0F
1J
b1001000000 .
b11000 :
b0 Y
b0 _
b1 ^
b1100000 ,
b1100000 0
b10100 8
b0 B
b0 d
b101001000 E
b101001000 ]
b100100001001000000000000100100000000001 O
b1 C
b1 c
b11000 H
b11000 P
b11000 b
b1100000 $
b1100000 '
b1010001100000000000000110000000000110 R
b10100 *
b11 G
b11 [
b11 \
0D
1K
b1 L
b1 `
b0 M
b0 a
0N
0#
b101 X
1<
#325000
0<
#330000
1D
1?
b11111111 3
b11111111 7
b11111111 V
b111111111 6
b11111111 -
b11111111 5
b11111111 T
b11111111 9
b11111111 U
b1111111110000000 .
b111111111 :
b10 I
b10 Q
b10 Z
0A
0J
b1 +
b10000000 ,
b10000000 0
b0 8
b11 Y
b0 ^
b1 H
b1 P
b1 b
b10000000 $
b10000000 '
b10000000000000001000000000000001 R
b0 *
b100000001000000000000000100000000000000 O
b0 C
b0 c
b11001000000 E
b11001000000 ]
b1010001100000000000000110000000000001 W
1#
b101 M
b101 a
1N
b1000000 L
b1000000 `
0K
b100 G
b100 [
b100 \
b101 X
1<
#335000
0<
#340000
b100 @
b0 3
b0 7
b0 V
b0 6
b0 -
b0 5
b0 T
b10100 9
b10100 U
b110 C
b110 c
b1000 I
b1000 Q
b1000 Z
b1000000 .
b10100 :
b110000001100000000000000110000000000110 O
b100 Y
b100 ^
b1000000 ,
b1100000 0
b10100 8
b1000000 "
b100001100000 E
b100001100000 ]
b10100 H
b10100 P
b10100 b
b1000000 $
b1100000 '
b1010001100000000000000100000000000001 R
b10100 *
b1010001100000000000000100000000000001 W
b101 G
b101 [
b101 \
0D
1K
b1 M
b1 a
0N
0#
b101 X
1<
#345000
0<
#350000
0?
b110 @
b10000 I
b10000 Q
b10000 Z
b0 B
b0 d
b100 C
b100 c
b101000001010000000000000101000000100 O
b101 Y
b10 _
b1 ^
b101000001010 E
b101000001010 ]
b100 L
b100 `
b110 G
b110 [
b110 \
b101 X
1<
#355000
0<
