rtl/v6/mux_21.sv
module mux_21 #(
    parameter BIT_WIDTH = 8
) (   
    input  logic s, 
    input  logic [BIT_WIDTH-1:0] a, b,
    output logic [BIT_WIDTH-1:0] out
);
    `ifdef COCOTB_SIM
    initial begin
        $dumpfile ("mux_21.vcd");
        $dumpvars (0, mux_21);
        #1;
    end
    `endif 
    assign out = s ? a : b;
endmodule

rtl/v7/sfixed_adder.sv
import datatypes::max;

module sfixed_adder #(
    parameter A_LEFT    = 3, 
    parameter A_RIGHT   = 4, 
    parameter B_LEFT    = 3, 
    parameter B_RIGHT   = 4,
    parameter OUT_LEFT  = 4, 
    parameter OUT_RIGHT = 4
) (   
    input  logic signed [(A_LEFT+A_RIGHT+1)-1:0]     a,
    input  logic signed [(B_LEFT+B_RIGHT+1)-1:0]     b,
    output logic signed [(OUT_LEFT+OUT_RIGHT+1)-1:0] out
);

`ifdef COCOTB_SIM
initial begin
    $dumpfile ("sfixed_adder.vcd");
    $dumpvars (0, sfixed_adder);
    #1;
end
`endif

localparam OUTPUT_SIZE = (max(A_LEFT,B_LEFT)+1)+max(A_RIGHT,B_RIGHT)+1; 

logic signed [OUTPUT_SIZE-1:0] add_out;

always_comb
    add_out = a + b;

assign out = add_out[max(A_RIGHT,B_RIGHT)+OUT_LEFT:max(A_RIGHT,B_RIGHT)-OUT_RIGHT];

endmodule

rtl/v7/sfixed_mult.sv
module sfixed_mult #(
    parameter A_LEFT    = 3, 
    parameter A_RIGHT   = 4,
    parameter B_LEFT    = 3, 
    parameter B_RIGHT   = 4,
    parameter OUT_LEFT  = 7, 
    parameter OUT_RIGHT = 8
) (
    input  logic signed [(A_LEFT+A_RIGHT+1)-1:0]     a,
    input  logic signed [(B_LEFT+B_RIGHT+1)-1:0]     b,
    output logic signed [(OUT_LEFT+OUT_RIGHT+1)-1:0] out
);
`ifdef COCOTB_SIM
initial begin
    $dumpfile ("sfixed_mult.vcd");
    $dumpvars (0, sfixed_mult);
    #1;
end
`endif

localparam OUTPUT_SIZE = (A_LEFT+B_LEFT+1)+(A_RIGHT+B_RIGHT)+1; 
                                                                
logic signed [OUTPUT_SIZE-1:0] mult_out;

always_comb
    mult_out = a * b;

assign out = mult_out[(A_RIGHT+B_RIGHT)+OUT_LEFT:(A_RIGHT+B_RIGHT)-OUT_RIGHT];

endmodule

rtl/v3/input_regs.sv
module input_regs #(
    parameter BUS_WIDTH = 8
) (
    input  logic                      clk, n_reset,
    input  logic [4:0]                reg_en,
    input  logic [4:0][BUS_WIDTH-1:0] ops,
    output logic [4:0][BUS_WIDTH-1:0] ops_reg
);

// enable registered inputs
always_ff @(posedge clk) 
begin
    if (~n_reset) 
        ops_reg <= '0;
    else begin
        for (int i = 0; i < 5; i=i+1) begin
            if (reg_en[i] == 1'b1)
                ops_reg[i] <= ops[i];
        end
    end
end

endmodule

rtl/v1/ALU.sv
module ALU #(
    parameter BUS_WIDTH  = 8
) (
    input  logic                      clk, n_reset,
    input  logic [4:0][BUS_WIDTH-1:0] ops,    
    input  logic [4:0]                reg_en,
    input  logic                      f_add,
    output logic [BUS_WIDTH-1:0]      result 
);       

logic [4:0][BUS_WIDTH-1:0] ops_reg;

input_regs #(
    BUS_WIDTH
) regs (
    .clk(clk),
    .n_reset(n_reset),
    .reg_en(reg_en),
    .ops(ops),
    .ops_reg(ops_reg)
);

// setting up of add/subtract inputs
logic [4:0][BUS_WIDTH-1:0] ops_in;

mux_21 #(
    BUS_WIDTH
) b_mux (   
    .s(f_add), 
    .a({1'b1, {BUS_WIDTH-1{1'b0}}}), 
    .b(ops_reg[1]),
    .out(ops_in[1])
);

mux_21 #(
    BUS_WIDTH
) d_mux (   
    .s(f_add), 
    .a({1'b1, {BUS_WIDTH-1{1'b0}}}), 
    .b(ops_reg[3]),
    .out(ops_in[3])
);

mux_21 #(
    BUS_WIDTH
) e_mux (   
    .s(f_add), 
    .a({BUS_WIDTH{1'b0}}), 
    .b(ops_reg[4]),
    .out(ops_in[4])
);

assign ops_in[0] = ops_reg[0];
assign ops_in[2] = ops_reg[2];

// the computational part
logic[BUS_WIDTH-1:0] mult_a, mult_b, add_a, add_b;
sfixed_mult #(
    7, 
    0,
    0, 
    7,
    7, 
    0
) m0 (
    .a(ops_in[0]), // int
    .b(ops_in[1]), // tf
    .out(mult_a)
);

sfixed_mult #(
    7, 
    0,
    0, 
    7,
    7, 
    0
) m1 (
    .a(ops_in[2]),  // int
    .b(ops_in[3]),  // tf
    .out(mult_b)
);

sfixed_adder #(
    7, 
    0, 
    7, 
    0,
    7, 
    0 
) a0 (   
    .a(mult_a), // int
    .b(mult_b), // int
    .out(add_a)
);

sfixed_adder #(
    7, 
    0, 
    7, 
    0,
    7, 
    0
) a1 (   
    .a(add_a),      // int
    .b(ops_in[4]),  // int
    .out(add_b)
);

mux_21 #(
    BUS_WIDTH
) out_mux (   
    .s(f_add), 
    .a(~add_b + 1'b1), 
    .b(add_b),
    .out(result)
);

endmodule

include/opcodes.sv
//-----------------------------------------------------
// File Name : opcodes.sv
// Function : pMIPS instr opcode definitions
// Author: jf
//-----------------------------------------------------
//
`define NOP  6'b000000
`define ADD  6'b000001
`define SUB  6'b000010
`define ADDI 6'b000011
`define SUBI 6'b000100
`define BEQ  6'b000101
`define BNE  6'b000110
`define BGE  6'b000111
`define BLO  6'b001000

rtl/v3/instruction_decoder.sv
`include "opcodes.sv"

module instruction_decoder #(
    parameter OPCODE_WIDTH = 3
) (
    input  logic [OPCODE_WIDTH-1:0] opcode,                  
    output logic                    f_add,            
    output logic                    f_wait,            
    output logic                    wr_res,         
    output logic [4:0]              ALU_reg_en
);

always_comb 
begin
    case(opcode)    
        `MOV : begin
            f_add      = '1; 
            f_wait     = '0;
            wr_res     = '1; 
            ALU_reg_en = 5'b11111; // C, A
        end
        `MAC : begin 
            f_add      = '0;
            f_wait     = '0;
            wr_res     = '1; 
            ALU_reg_en = 5'b00101; // C, A
        end
        `WAIT: begin
            f_add      = '0;
            f_wait     = '1;
            wr_res     = '0;
            ALU_reg_en = 5'b00000;
        end
        `SETB: begin
            f_add      = '0;
            f_wait     = '0;
            wr_res     = '0;
            ALU_reg_en = 5'b00010; 
        end
        `SETD: begin
            f_add      = '0;
            f_wait     = '0;
            wr_res     = '0;
            ALU_reg_en = 5'b01000;
        end
        `SETE: begin
            f_add      = '0;
            f_wait     = '0;
            wr_res     = '0;
            ALU_reg_en = 5'b10000;
        end
        default : begin
            f_add      = '0;
            f_wait     = '0;
            wr_res     = '0;
            ALU_reg_en = '0;
        end
    endcase 
end 

endmodule

rtl/memory/register_file.sv
module register_file #(
    parameter BUS_WIDTH  = 8,
    parameter ADDR_WIDTH = 3
) (
	input  logic                  clk, 
	input  logic [BUS_WIDTH-1:0]  sw,
	input  logic 				  ready_in,
	input  logic 				  pattern_match,
	input  logic                  we,
 	input  logic [ADDR_WIDTH-1:0] wr_addr,
	input  logic [BUS_WIDTH-1:0]  wr_data,
 	input  logic [ADDR_WIDTH-1:0] rd_addr_a, rd_addr_b,
 	output logic [BUS_WIDTH-1:0]  rd_data_a, rd_data_b,
	output logic [BUS_WIDTH-1:0]  out_port
);

localparam N = (1 << ADDR_WIDTH);

logic [BUS_WIDTH-1:0] gpr [N-1:0];

// syncrhonous RAM write
always_ff @ (posedge clk)
begin
	if (we) begin 
		gpr[wr_addr] <= wr_data;
	end
end

// asynchronous RAM read
logic [BUS_WIDTH-1:0] data_a, data_b;
always_comb
	data_a = gpr[rd_addr_a];

always_comb
	data_b = gpr[rd_addr_b];

// multiplex the rd_data_a output based on the asked for addr
always_comb
begin
	case(rd_addr_a)
		0       : rd_data_a = {BUS_WIDTH{1'b0}};
		1       : rd_data_a = sw;
		2       : rd_data_a = {{BUS_WIDTH-1{1'b0}}, ready_in};
		3       : rd_data_a = {{BUS_WIDTH-1{1'b0}}, pattern_match};
		default : rd_data_a = data_a;
	endcase
end

// multiplex the rd_data_b output based on the asked for addr
always_comb
begin
	case(rd_addr_b)
		0       : rd_data_b = {BUS_WIDTH{1'b0}};
		1       : rd_data_b = sw;
		2       : rd_data_b = {{BUS_WIDTH-1{1'b0}}, ready_in};
		3       : rd_data_b = {{BUS_WIDTH-1{1'b0}}, pattern_match};
		default : rd_data_b = data_b;
	endcase
end

// register $7 is the output register
assign out_port = gpr[7];

endmodule

rtl/memory/program_memory.sv
module program_memory #(
    parameter ADDR_WIDTH  = 4,
    parameter INSTR_WIDTH = 12
) (
    input  logic [ADDR_WIDTH-1:0]  addr,
    output logic [INSTR_WIDTH-1:0] instr
); 

(* ramstyle = "MLAB" *)  logic [INSTR_WIDTH-1:0] prog_mem [(1<<ADDR_WIDTH)-1:0];

initial
    $readmemh("/home/jonahfoley/ELEC6234/a_fine_CPU/programs/prog.hex", prog_mem);
   
always_comb
    instr = prog_mem[addr]; 
  
endmodule

rtl/memory/program_counter.sv
module program_counter #(
    parameter ADDR_WIDTH = 3
) (
    input  logic                  clk, n_reset,
    input  logic                  en,
    output logic [ADDR_WIDTH-1:0] count
);
 
always_ff @(posedge clk) 
begin
    if (~n_reset) 
        count <= '0;
    else begin
        if (count == (2<<ADDR_WIDTH)-1) 
            count <= '0;
        else begin
            if (en)
                count <= count + { {ADDR_WIDTH-1{1'b0}}, 1'b1 };
        end
    end
end


endmodule

rtl/v1/CPU.sv
module CPU #(
    parameter INSTR_WIDTH      = 12,
    parameter OPCODE_WIDTH     = 3,
    parameter INSTR_ADDR_WIDTH = 4, 
    parameter REG_ADDR_WIDTH   = 3, 
    parameter BUS_WIDTH        = 8
) (
    input  logic                 clk,  
    input  logic                 n_reset,
    input  logic [BUS_WIDTH-1:0] sw,
    input  logic                 ready_in,
    output logic [BUS_WIDTH-1:0] out_port
);       

//the macro to dump signals   
`ifdef COCOTB_SIM
initial begin
    $dumpfile ("CPU.vcd");
    $dumpvars (0, CPU);
    #1;
end
`endif

// input switch handshaking
logic ready_in_p, pattern_match;
always_ff @(posedge clk)
    ready_in_p <= ready_in;

logic [BUS_WIDTH-1:0] sw_p;
always_ff @(posedge clk)
    sw_p <= sw;

assign pattern_match = ({ready_in_p, ready_in} == 2'b01);

// -- instr counter
logic [INSTR_ADDR_WIDTH-1:0] PC_count;
logic PC_en;
assign PC_en = (PC_wait & ~(rd_data_a[0] ^ instr[0])) | ~PC_wait;

program_counter #(
   INSTR_ADDR_WIDTH
) pc (
   .clk    (clk     ),
   .n_reset(n_reset ),
   .en     (PC_en   ),
   .count  (PC_count)
);

// -- program ROM
logic [INSTR_WIDTH-1:0] instr;

program_memory #(
    INSTR_ADDR_WIDTH,
    INSTR_WIDTH
) pm (
    .addr (PC_count),
    .instr(instr   )
);

// -- reg file
logic wr_res, we;
logic [REG_ADDR_WIDTH-1:0] wr_addr;
logic [BUS_WIDTH-1:0] rd_data_a, rd_data_b;

always_ff @(posedge clk) 
begin
    we      <= wr_res;
    wr_addr <= instr[8:6];
end

register_file #(
    BUS_WIDTH,
    REG_ADDR_WIDTH
) rf (
	.clk          (clk          ),  
	.sw           (sw_p         ),
    .ready_in     (ready_in     ),
	.pattern_match(pattern_match),
    .we           (we           ),
 	.wr_addr      (wr_addr      ),
	.wr_data      (ALU_result   ),
 	.rd_addr_a    (instr[5:3]   ), 
    .rd_addr_b    (instr[2:0]   ),
 	.rd_data_a    (rd_data_a    ), 
    .rd_data_b    (rd_data_b    ),
    .out_port     (out_port     )
);

// -- decoder
logic ALU_add, ALU_add_p, PC_wait;

instruction_decoder #(
    OPCODE_WIDTH
) id (
    .opcode    (instr[11:9]),                  
    .f_add     (ALU_add    ), 
    .f_wait    (PC_wait    ),            
    .wr_res    (wr_res     ),         
    .ALU_reg_en(ALU_reg_en )
);

// -- ALU
logic [BUS_WIDTH-1:0] ALU_result;
logic [4:0] ALU_reg_en; 

always_ff @(posedge clk)
    ALU_add_p <= ALU_add;

ALU #(
    BUS_WIDTH
) alu (
    .clk    (clk                                                   ),
    .n_reset(n_reset                                               ),
    .ops    ({instr[7:0],instr[7:0],rd_data_b,instr[7:0],rd_data_a}),   
    .reg_en (ALU_reg_en                                            ),
    .f_add  (ALU_add_p                                             ),
    .result (ALU_result                                            )
);    

endmodule

simulation/v1/CPU/mux_21.vcd
$date
	Sun Apr 16 04:44:27 2023
$end
$version
	Icarus Verilog
$end
$timescale
	1ps
$end
$scope module CPU $end
$scope module alu $end
$scope module b_mux $end
$var wire 8 ! a [7:0] $end
$var wire 8 " b [7:0] $end
$var wire 1 # s $end
$var wire 8 $ out [7:0] $end
$upscope $end
$upscope $end
$upscope $end
$scope module CPU $end
$scope module alu $end
$scope module d_mux $end
$var wire 8 % a [7:0] $end
$var wire 8 & b [7:0] $end
$var wire 1 # s $end
$var wire 8 ' out [7:0] $end
$upscope $end
$upscope $end
$upscope $end
$scope module CPU $end
$scope module alu $end
$scope module e_mux $end
$var wire 8 ( a [7:0] $end
$var wire 8 ) b [7:0] $end
$var wire 1 # s $end
$var wire 8 * out [7:0] $end
$upscope $end
$upscope $end
$upscope $end
$scope module CPU $end
$scope module alu $end
$scope module m0 $end
$var wire 8 + a [7:0] $end
$var wire 8 , b [7:0] $end
$var wire 8 - out [7:0] $end
$var reg 16 . mult_out [15:0] $end
$upscope $end
$upscope $end
$upscope $end
$scope module CPU $end
$scope module alu $end
$scope module m1 $end
$var wire 8 / a [7:0] $end
$var wire 8 0 b [7:0] $end
$var wire 8 1 out [7:0] $end
$var reg 16 2 mult_out [15:0] $end
$upscope $end
$upscope $end
$upscope $end
$scope module CPU $end
$scope module alu $end
$scope module a0 $end
$var wire 8 3 out [7:0] $end
$var wire 8 4 b [7:0] $end
$var wire 8 5 a [7:0] $end
$var reg 9 6 add_out [8:0] $end
$upscope $end
$upscope $end
$upscope $end
$scope module CPU $end
$scope module alu $end
$scope module a1 $end
$var wire 8 7 a [7:0] $end
$var wire 8 8 b [7:0] $end
$var wire 8 9 out [7:0] $end
$var reg 9 : add_out [8:0] $end
$upscope $end
$upscope $end
$upscope $end
$scope module CPU $end
$scope module alu $end
$scope module out_mux $end
$var wire 8 ; a [7:0] $end
$var wire 8 < b [7:0] $end
$var wire 1 # s $end
$var wire 8 = out [7:0] $end
$upscope $end
$upscope $end
$upscope $end
$scope module CPU $end
$var wire 1 > PC_en $end
$var wire 1 ? clk $end
$var wire 1 @ n_reset $end
$var wire 1 A ready_in $end
$var wire 8 B sw [7:0] $end
$var wire 1 C wr_res $end
$var wire 8 D rd_data_b [7:0] $end
$var wire 8 E rd_data_a [7:0] $end
$var wire 1 F pattern_match $end
$var wire 8 G out_port [7:0] $end
$var wire 12 H instr [11:0] $end
$var wire 1 I PC_wait $end
$var wire 4 J PC_count [3:0] $end
$var wire 8 K ALU_result [7:0] $end
$var wire 5 L ALU_reg_en [4:0] $end
$var wire 1 M ALU_add $end
$var reg 1 # ALU_add_p $end
$var reg 1 N ready_in_p $end
$var reg 8 O sw_p [7:0] $end
$var reg 1 P we $end
$var reg 3 Q wr_addr [2:0] $end
$scope module alu $end
$var wire 1 ? clk $end
$var wire 1 # f_add $end
$var wire 1 @ n_reset $end
$var wire 40 R ops [39:0] $end
$var wire 8 S result [7:0] $end
$var wire 5 T reg_en [4:0] $end
$var wire 40 U ops_reg [39:0] $end
$var wire 40 V ops_in [39:0] $end
$var wire 8 W mult_b [7:0] $end
$var wire 8 X mult_a [7:0] $end
$var wire 8 Y add_b [7:0] $end
$var wire 8 Z add_a [7:0] $end
$scope module a0 $end
$upscope $end
$scope module a1 $end
$upscope $end
$scope module b_mux $end
$upscope $end
$scope module d_mux $end
$upscope $end
$scope module e_mux $end
$upscope $end
$scope module m0 $end
$upscope $end
$scope module m1 $end
$upscope $end
$scope module out_mux $end
$upscope $end
$scope module regs $end
$var wire 1 ? clk $end
$var wire 1 @ n_reset $end
$var wire 40 [ ops [39:0] $end
$var wire 5 \ reg_en [4:0] $end
$var reg 40 ] ops_reg [39:0] $end
$scope begin $ivl_for_loop0 $end
$var integer 32 ^ i [31:0] $end
$upscope $end
$upscope $end
$upscope $end
$scope module id $end
$var wire 3 _ opcode [2:0] $end
$var reg 5 ` ALU_reg_en [4:0] $end
$var reg 1 M f_add $end
$var reg 1 I f_wait $end
$var reg 1 C wr_res $end
$upscope $end
$scope module pc $end
$var wire 1 ? clk $end
$var wire 1 > en $end
$var wire 1 @ n_reset $end
$var reg 4 a count [3:0] $end
$upscope $end
$scope module pm $end
$var wire 4 b addr [3:0] $end
$var reg 12 c instr [11:0] $end
$upscope $end
$scope module rf $end
$var wire 1 ? clk $end
$var wire 8 d out_port [7:0] $end
$var wire 1 F pattern_match $end
$var wire 3 e rd_addr_a [2:0] $end
$var wire 3 f rd_addr_b [2:0] $end
$var wire 1 A ready_in $end
$var wire 8 g sw [7:0] $end
$var wire 1 P we $end
$var wire 3 h wr_addr [2:0] $end
$var wire 8 i wr_data [7:0] $end
$var reg 8 j data_a [7:0] $end
$var reg 8 k data_b [7:0] $end
$var reg 8 l rd_data_a [7:0] $end
$var reg 8 m rd_data_b [7:0] $end
$upscope $end
$upscope $end
$enddefinitions $end
#0
$dumpvars
b0 m
b0 l
bx k
bx j
b0 i
bx h
b0 g
b1 f
b11 e
bx d
b10000011001 c
b0 b
b0 a
b0 `
b10 _
b0 ^
b0 ]
b0 \
b1100100011001000000000001100100000000 [
b0 Z
b0 Y
b0 X
b0 W
b0 V
b0 U
b0 T
b0 S
b1100100011001000000000001100100000000 R
bx Q
0P
b0 O
0N
0M
b0 L
b0 K
b0 J
1I
b10000011001 H
bx G
0F
b0 E
b0 D
0C
b0 B
0A
0@
1?
0>
b0 =
b0 <
b0 ;
b0 :
b0 9
b0 8
b0 7
b0 6
b0 5
b0 4
b0 3
b0 2
b0 1
b0 0
b0 /
b0 .
b0 -
b0 ,
b0 +
b0 *
b0 )
b0 (
b0 '
b0 &
b10000000 %
b0 $
0#
b0 "
b10000000 !
$end
#5000
0?
#10000
b0 Q
b0 h
1?
#15000
0?
#20000
1@
1?
#25000
0?
#30000
b101 ^
1?
#35000
0?
#40000
b101 ^
1?
#45000
0?
#50000
b101 ^
1?
#55000
0?
#60000
b101 ^
1?
#65000
0?
#70000
b101 ^
1?
#75000
0?
#80000
b101 ^
1?
#85000
0?
#90000
b101 ^
1?
#95000
0?
#100000
b101 ^
1?
#105000
0?
#110000
b101 ^
1?
#115000
0?
#120000
1>
b1100100011001000000000001100100000001 R
b1100100011001000000000001100100000001 [
b1 E
b1 l
1F
1A
b11100101 B
b101 ^
1?
#125000
0?
#130000
0A
b101 L
b101 T
b101 \
b101 `
1C
0I
1M
b0 _
b0 f
b1 e
b0 D
b0 m
b100000001000000000000000100011100101 R
b100000001000000000000000100011100101 [
b11100101 E
b11100101 l
b100001000 H
b100001000 c
b11100101 O
b11100101 g
0F
1N
b1 J
b1 a
b1 b
b101 ^
1?
#135000
0?
#140000
b11100101 =
b11100101 K
b11100101 S
b11100101 i
b11100101 ;
b11011 9
b11011 <
b11011 Y
b11011 :
b11011 3
b11011 7
b11011 Z
0>
b11011 6
b11011 -
b11011 5
b11011 X
b0 E
b0 l
b11100101 D
b11100101 m
b0 L
b0 T
b0 \
b0 `
0C
1I
0M
b110110000000 .
b11100101 +
b1100100011001111001010001100100000000 R
b1100100011001111001010001100100000000 [
b10 _
b1 f
b11 e
b10000000 ,
b10000000 0
b10000011001 H
b10000011001 c
b10000000 $
b10000000000000001000000011100101 V
b10000000 '
b11100101 U
b11100101 ]
b10 J
b10 a
b10 b
0N
b100 Q
b100 h
1P
1#
b101 ^
1?
#145000
0?
#150000
b0 ;
b0 9
b0 <
b0 Y
b0 :
b0 3
b0 7
b0 Z
b0 6
b0 -
b0 5
b0 X
b0 .
b0 ,
b0 0
b0 $
b11100101 V
b0 '
b0 =
b0 K
b0 S
b0 i
0#
b0 Q
b0 h
0P
b101 ^
1?
#155000
0?
#160000
b101 ^
1?
#165000
0?
#170000
b101 ^
1?
#175000
0?
#180000
b101 ^
1?
#185000
0?
#190000
1>
b1100100011001111001010001100100000001 R
b1100100011001111001010001100100000001 [
b1 E
b1 l
1F
1A
b1100001 B
b101 ^
1?
#195000
0?
#200000
0A
b101 L
b101 T
b101 \
b101 `
1C
0I
1M
b0 _
b0 f
b1 e
b0 D
b0 m
b101001000 H
b101001000 c
b100100001001000000000000100100001100001 R
b100100001001000000000000100100001100001 [
b1100001 E
b1100001 l
b11 J
b11 a
b11 b
0F
1N
b1100001 O
b1100001 g
b101 ^
1?
#205000
0?
#210000
b1100001 =
b1100001 K
b1100001 S
b1100001 i
b1100001 ;
b10011111 9
b10011111 <
b10011111 Y
b110011111 :
b10011111 3
b10011111 7
b10011111 Z
b110011111 6
b10011111 -
b10011111 5
b10011111 X
b1100111110000000 .
b10 L
b10 T
b10 \
b10 `
0C
0M
b11100101 E
b11100101 l
b11100101 j
b1100001 +
b10000000 ,
b10000000 0
b110000001100000000000000110000011100101 R
b110000001100000000000000110000011100101 [
b11 _
b100 e
b10000000 $
b10000000000000001000000001100001 V
b10000000 '
b11001100000 H
b11001100000 c
b1100001 U
b1100001 ]
1#
b101 Q
b101 h
1P
0N
b100 J
b100 a
b100 b
b101 ^
1?
#215000
0?
#220000
b10111000 ;
b1001000 9
b1001000 <
b1001000 Y
b1001000 :
b1001000 3
b1001000 7
b1001000 Z
b1001000 6
b1001000 -
b1001000 5
b1001000 X
bx j
b0 E
b0 l
b1000 L
b1000 T
b1000 \
b1000 `
b10010001100000 .
b100000001000000000000000100000000000000 R
b100000001000000000000000100000000000000 [
b100 _
b0 e
b1100000 ,
b0 0
b1100000 "
b100001000000 H
b100001000000 c
b1100000 $
b110000001100001 V
b0 '
b1001000 =
b1001000 K
b1001000 S
b1001000 i
b110000001100001 U
b110000001100001 ]
b101 J
b101 a
b101 b
b1 Q
b1 h
0P
0#
b101 ^
1?
#225000
0?
#230000
b1000000 0
b10000 L
b10000 T
b10000 \
b10000 `
b11100101 D
b11100101 m
b11100101 k
b1000000000000000110000001100001 V
b1000000 '
b1010000010100111001010001010000000000 R
b1010000010100111001010001010000000000 [
b101 _
b100 f
b10 e
b1000000 &
b101000010100 H
b101000010100 c
b1000000000000000110000001100001 U
b1000000000000000110000001100001 ]
b110 J
b110 a
b110 b
b101 ^
1?
#235000
0?
#240000
b1011100 =
b1011100 K
b1011100 S
b1011100 i
b10100100 ;
b1011100 9
b1011100 <
b1011100 Y
b1011100 :
b10100 8
b101 L
b101 T
b101 \
b101 `
1C
b1100001 D
b1100001 m
b1100001 k
b11100101 E
b11100101 l
b11100101 j
b1010001000000000000000110000001100001 V
b10100 *
b1010010110100101011000011010010111100101 R
b1010010110100101011000011010010111100101 [
b1 _
b101 f
b100 e
b10100 )
b1110100101 H
b1110100101 c
b1010001000000000000000110000001100001 U
b1010001000000000000000110000001100001 ]
b111 J
b111 a
b111 b
b0 Q
b0 h
b101 ^
1?
#245000
0?
#250000
b101111 =
b101111 K
b101111 S
b101111 i
b11010001 ;
b101111 9
b101111 <
b101111 Y
b101111 :
b11011 3
b11011 7
b11011 Z
b11011 6
b110000 1
b110000 4
b110000 W
b11101011 -
b11101011 5
b11101011 X
b1100001000000 2
b1111010111100000 .
b10 L
b10 T
b10 \
b10 `
0C
b0 D
b0 m
bx k
b0 E
b0 l
bx j
b1100001 /
b11100101 +
b1100000011000000000000001100000000000000 R
b1100000011000000000000001100000000000000 [
b11 _
b0 f
b0 e
b1010001000000011000010110000011100101 V
b11011000000 H
b11011000000 c
b1010001000000011000010110000011100101 U
b1010001000000011000010110000011100101 ]
b110 Q
b110 h
1P
b1000 J
b1000 a
b1000 b
b101 ^
1?
#255000
0?
#260000
b1010001 =
b1010001 K
b1010001 S
b1010001 i
b10101111 ;
b1010001 9
b1010001 <
b1010001 Y
b1010001 :
b111101 3
b111101 7
b111101 Z
b111101 6
b1101 -
b1101 5
b1101 X
b11011000000 .
b11000000 ,
b1000 L
b1000 T
b1000 \
b1000 `
b11100101 E
b11100101 l
b11100101 j
b1010001000000011000011100000011100101 V
b11000000 $
b110000001100000000000000110000011100101 R
b110000001100000000000000110000011100101 [
b100 _
b100 e
b11000000 "
b100001100000 H
b100001100000 c
b1010001000000011000011100000011100101 U
b1010001000000011000011100000011100101 ]
b1001 J
b1001 a
b1001 b
b11 Q
b11 h
0P
b101 ^
1?
#265000
0?
#270000
b1101001 =
b1101001 K
b1101001 S
b1101001 i
b10010111 ;
b1101001 9
b1101001 <
b1101001 Y
b1101001 :
b1010101 3
b1010101 7
b1010101 Z
b1010101 6
b1001000 1
b1001000 4
b1001000 W
b10010001100000 2
b1100000 0
b10000 L
b10000 T
b10000 \
b10000 `
b11100101 D
b11100101 m
b11100101 k
b1100001 E
b1100001 l
b1100001 j
b1010001100000011000011100000011100101 V
b1100000 '
b1110110011101100111001011110110001100001 R
b1110110011101100111001011110110001100001 [
b101 _
b100 f
b101 e
b1100000 &
b101011101100 H
b101011101100 c
b1010001100000011000011100000011100101 U
b1010001100000011000011100000011100101 ]
b1 Q
b1 h
b1010 J
b1010 a
b1010 b
b101 ^
1?
#275000
0?
#280000
b1000001 =
b1000001 K
b1000001 S
b1000001 i
b10111111 ;
b1000001 9
b1000001 <
b1000001 Y
b1000001 :
b11101100 8
b101 L
b101 T
b101 \
b101 `
1C
b1100001 D
b1100001 m
b1100001 k
b11100101 E
b11100101 l
b11100101 j
b1110110001100000011000011100000011100101 V
b11101100 *
b110010101100101011000010110010111100101 R
b110010101100101011000010110010111100101 [
b1 _
b101 f
b100 e
b11101100 )
b1101100101 H
b1101100101 c
b1110110001100000011000011100000011100101 U
b1110110001100000011000011100000011100101 ]
b1011 J
b1011 a
b1011 b
b11 Q
b11 h
b101 ^
1?
#285000
0?
#290000
1M
b0 D
b0 m
bx k
b101111 E
b101111 l
b101111 j
b1111000011110000000000001111000000101111 R
b1111000011110000000000001111000000101111 [
b0 _
b0 f
b110 e
b111110000 H
b111110000 c
b101 Q
b101 h
1P
b1100 J
b1100 a
b1100 b
b101 ^
1?
#295000
0?
#300000
b11010001 3
b11010001 7
b11010001 Z
0>
b111010001 6
b101111 ;
b11010001 -
b11010001 5
b11010001 X
b0 1
b0 4
b0 W
b11010001 9
b11010001 <
b11010001 Y
bx j
b0 E
b0 l
b1100001 D
b1100001 m
b0 L
b0 T
b0 \
b0 `
0C
1I
0M
b1110100010000000 .
b0 2
b111010001 :
b0 /
b101111 +
b1000100010001011000010001000100000000 R
b1000100010001011000010001000100000000 [
b10 _
b1 f
b10 e
b10000000 ,
b10000000 0
b0 8
b10000010001 H
b10000010001 c
b10000000 $
b10000000 '
b10000000000000001000000000101111 V
b0 *
b101111 =
b101111 K
b101111 S
b101111 i
b1110110001100000000000001100000000101111 U
b1110110001100000000000001100000000101111 ]
b1101 J
b1101 a
b1101 b
b111 Q
b111 h
1#
b101 ^
1?
#305000
0?
#310000
b11101000 3
b11101000 7
b11101000 Z
b111101000 6
b101100 ;
b11101000 -
b11101000 5
b11101000 X
b11010100 9
b11010100 <
b11010100 Y
b1111010001000000 .
b111010100 :
b11000000 ,
b1100000 0
b11101100 8
b11000000 $
b1100000 '
b1110110001100000000000001100000000101111 V
b11101100 *
b11010100 =
b11010100 K
b11010100 S
b11010100 i
0#
b0 Q
b0 h
0P
b101111 G
b101111 d
b101 ^
1?
#315000
0?
#320000
1>
b1000100010001011000010001000100000001 R
b1000100010001011000010001000100000001 [
b1 E
b1 l
1F
1A
b101 ^
1?
#325000
0?
#330000
b101 L
b101 T
b101 \
b101 `
1C
0I
1M
b0 D
b0 m
b1000001 E
b1000001 l
b1000001 j
b1110100011101000000000001110100001000001 R
b1110100011101000000000001110100001000001 [
b0 _
b0 f
b101 e
b111101000 H
b111101000 c
0F
1N
b1110 J
b1110 a
b1110 b
b101 ^
1?
#335000
0?
#340000
b10111111 3
b10111111 7
b10111111 Z
0>
b110111111 6
b1000001 ;
b10111111 -
b10111111 5
b10111111 X
b10111111 9
b10111111 <
b10111111 Y
bx j
b1 E
b1 l
b0 L
b0 T
b0 \
b0 `
0C
1I
0M
b1101111110000000 .
b110111111 :
b1000001 +
b1000000010000000000000001000000000001 R
b1000000010000000000000001000000000001 [
b10 _
b10 e
b10000000 ,
b10000000 0
b0 8
b10000010000 H
b10000010000 c
b10000000 $
b10000000 '
b10000000000000001000000001000001 V
b0 *
b1000001 =
b1000001 K
b1000001 S
b1000001 i
b1110110001100000000000001100000001000001 U
b1110110001100000000000001100000001000001 ]
b1111 J
b1111 a
b1111 b
b111 Q
b111 h
1P
1#
b101 ^
1?
#345000
0?
#350000
b11011111 3
b11011111 7
b11011111 Z
b111011111 6
b110101 ;
b11011111 -
b11011111 5
b11011111 X
b11001011 9
b11001011 <
b11001011 Y
b1110111111000000 .
b111001011 :
b11000000 ,
b1100000 0
b11101100 8
b11000000 $
b1100000 '
b1110110001100000000000001100000001000001 V
b11101100 *
b11001011 =
b11001011 K
b11001011 S
b11001011 i
0#
b0 Q
b0 h
0P
b1000001 G
b1000001 d
b101 ^
1?
#355000
0?
#360000
1>
b1000000010000000000000001000000000000 R
b1000000010000000000000001000000000000 [
b0 E
b0 l
0A
b101 ^
1?
#365000
0?
#370000
0>
b1100001 D
b1100001 m
b1100100011001011000010001100100000000 R
b1100100011001011000010001100100000000 [
b1 f
b11 e
b10000011001 H
b10000011001 c
0N
b0 J
b0 a
b0 b
b101 ^
1?
#375000
0?
#380000
b101 ^
1?
#385000
0?
#390000
b101 ^
1?
#395000
0?
#400000
b101 ^
1?
#405000
0?
#410000
1>
b1100100011001011000010001100100000001 R
b1100100011001011000010001100100000001 [
b1 E
b1 l
1F
1A
b1011110 B
b101 ^
1?
#415000
0?
