rtl/v7/sfixed_adder.sv
import datatypes::max;

module sfixed_adder #(
    parameter A_LEFT    = 3, 
    parameter A_RIGHT   = 4, 
    parameter B_LEFT    = 3, 
    parameter B_RIGHT   = 4,
    parameter OUT_LEFT  = 4, 
    parameter OUT_RIGHT = 4
) (   
    input  logic signed [(A_LEFT+A_RIGHT+1)-1:0]     a,
    input  logic signed [(B_LEFT+B_RIGHT+1)-1:0]     b,
    output logic signed [(OUT_LEFT+OUT_RIGHT+1)-1:0] out
);

`ifdef COCOTB_SIM
initial begin
    $dumpfile ("sfixed_adder.vcd");
    $dumpvars (0, sfixed_adder);
    #1;
end
`endif

localparam OUTPUT_SIZE = (max(A_LEFT,B_LEFT)+1)+max(A_RIGHT,B_RIGHT)+1; 

logic signed [OUTPUT_SIZE-1:0] add_out;

always_comb
    add_out = a + b;

assign out = add_out[max(A_RIGHT,B_RIGHT)+OUT_LEFT:max(A_RIGHT,B_RIGHT)-OUT_RIGHT];

endmodule

rtl/v7/sfixed_mult.sv
module sfixed_mult #(
    parameter A_LEFT    = 3, 
    parameter A_RIGHT   = 4,
    parameter B_LEFT    = 3, 
    parameter B_RIGHT   = 4,
    parameter OUT_LEFT  = 7, 
    parameter OUT_RIGHT = 8
) (
    input  logic signed [(A_LEFT+A_RIGHT+1)-1:0]     a,
    input  logic signed [(B_LEFT+B_RIGHT+1)-1:0]     b,
    output logic signed [(OUT_LEFT+OUT_RIGHT+1)-1:0] out
);
`ifdef COCOTB_SIM
initial begin
    $dumpfile ("sfixed_mult.vcd");
    $dumpvars (0, sfixed_mult);
    #1;
end
`endif

localparam OUTPUT_SIZE = (A_LEFT+B_LEFT+1)+(A_RIGHT+B_RIGHT)+1; 
                                                                
logic signed [OUTPUT_SIZE-1:0] mult_out;

always_comb
    mult_out = a * b;

assign out = mult_out[(A_RIGHT+B_RIGHT)+OUT_LEFT:(A_RIGHT+B_RIGHT)-OUT_RIGHT];

endmodule

rtl/v6/mux_21.sv
module mux_21 #(
    parameter BIT_WIDTH = 8
) (   
    input  logic s, 
    input  logic [BIT_WIDTH-1:0] a, b,
    output logic [BIT_WIDTH-1:0] out
);
    `ifdef COCOTB_SIM
    initial begin
        $dumpfile ("mux_21.vcd");
        $dumpvars (0, mux_21);
        #1;
    end
    `endif 
    assign out = s ? a : b;
endmodule

rtl/v2/ALU.sv
module ALU #(
    parameter BUS_WIDTH  = 8
) (
    input  logic                      clk, 
    input  logic [4:0][BUS_WIDTH-1:0] ops,    
    input  logic [4:0]                reg_en,
    input  logic                      f_add,
    output logic [BUS_WIDTH-1:0]      result 
);       

// setting up of add/subtract inputs
logic [BUS_WIDTH-1:0] op_e;
logic [BUS_WIDTH-1:0] op_a_reg, op_b_reg, op_c_reg, op_d_reg, op_e_reg;

mux_21 #(
    BUS_WIDTH
) e_mux (   
    .s  (f_add     ), 
    .a  (ops[0]    ), 
    .b  (ops[4]    ),
    .out(op_e      )
);

// input registers

always_ff @( posedge clk ) begin 
    if (reg_en[0]) begin
        op_a_reg <= ops[0];
    end
end

always_ff @( posedge clk ) begin 
    if (reg_en[1]) begin
        if (f_add)
            op_b_reg <= '0;
        else 
            op_b_reg <= ops[1];
    end
end

always_ff @( posedge clk ) begin 
    if (reg_en[2]) begin
        op_c_reg <= ops[2];
    end
end

always_ff @( posedge clk ) begin 
    if (reg_en[3]) begin
        if (f_add)
            op_d_reg <= '0;
        else 
            op_d_reg <= ops[3];
    end
end

always_ff @(posedge clk)  
begin
    if (reg_en[4])
        op_e_reg <= op_e;
end

// the computational part
logic[BUS_WIDTH-1:0] mult_a, mult_b, add_a, add_b;

sfixed_mult #(
    7, 
    0,
    0, 
    7,
    7,
    0 
) m0 (
    .a  (op_a_reg), // int
    .b  (op_b_reg), // tf
    .out(mult_a  )
);

sfixed_mult #(
    7, 
    0,
    0, 
    7,
    7, 
    0
) m1 (
    .a  (op_c_reg), // int
    .b  (op_d_reg), // tf
    .out(mult_b   )
);

sfixed_adder #(
    7, 
    0, 
    7, 
    0,
    7, 
    0 
) a0 (   
    .a  (mult_a), // int
    .b  (mult_b), // int
    .out(add_a )
);

sfixed_adder #(
    7, 
    0, 
    7, 
    0,
    7, 
    0
) a1 (   
    .a  (add_a   ), // int
    .b  (op_e_reg), // int
    .out(result  )
);

endmodule

include/opcodes.sv
//-----------------------------------------------------
// File Name : opcodes.sv
// Function : pMIPS instr opcode definitions
// Author: jf
//-----------------------------------------------------
//
`define NOP  6'b000000
`define ADD  6'b000001
`define SUB  6'b000010
`define ADDI 6'b000011
`define SUBI 6'b000100
`define BEQ  6'b000101
`define BNE  6'b000110
`define BGE  6'b000111
`define BLO  6'b001000

rtl/v3/instruction_decoder.sv
`include "opcodes.sv"

module instruction_decoder #(
    parameter OPCODE_WIDTH = 3
) (
    input  logic [OPCODE_WIDTH-1:0] opcode,                  
    output logic                    f_add,            
    output logic                    f_wait,            
    output logic                    wr_res,         
    output logic [4:0]              ALU_reg_en
);

always_comb 
begin
    case(opcode)    
        `MOV : begin
            f_add      = '1; 
            f_wait     = '0;
            wr_res     = '1; 
            ALU_reg_en = 5'b11111; // C, A
        end
        `MAC : begin 
            f_add      = '0;
            f_wait     = '0;
            wr_res     = '1; 
            ALU_reg_en = 5'b00101; // C, A
        end
        `WAIT: begin
            f_add      = '0;
            f_wait     = '1;
            wr_res     = '0;
            ALU_reg_en = 5'b00000;
        end
        `SETB: begin
            f_add      = '0;
            f_wait     = '0;
            wr_res     = '0;
            ALU_reg_en = 5'b00010; 
        end
        `SETD: begin
            f_add      = '0;
            f_wait     = '0;
            wr_res     = '0;
            ALU_reg_en = 5'b01000;
        end
        `SETE: begin
            f_add      = '0;
            f_wait     = '0;
            wr_res     = '0;
            ALU_reg_en = 5'b10000;
        end
        default : begin
            f_add      = '0;
            f_wait     = '0;
            wr_res     = '0;
            ALU_reg_en = '0;
        end
    endcase 
end 

endmodule

rtl/memory/register_file.sv
module register_file #(
    parameter BUS_WIDTH  = 8,
    parameter ADDR_WIDTH = 3
) (
	input  logic                  clk, 
	input  logic [BUS_WIDTH-1:0]  sw,
	input  logic 				  ready_in,
	input  logic 				  pattern_match,
	input  logic                  we,
 	input  logic [ADDR_WIDTH-1:0] wr_addr,
	input  logic [BUS_WIDTH-1:0]  wr_data,
 	input  logic [ADDR_WIDTH-1:0] rd_addr_a, rd_addr_b,
 	output logic [BUS_WIDTH-1:0]  rd_data_a, rd_data_b,
	output logic [BUS_WIDTH-1:0]  out_port
);

localparam N = (1 << ADDR_WIDTH);

logic [BUS_WIDTH-1:0] gpr [N-1:0];

// syncrhonous RAM write
always_ff @ (posedge clk)
begin
	if (we) begin 
		gpr[wr_addr] <= wr_data;
	end
end

// asynchronous RAM read
logic [BUS_WIDTH-1:0] data_a, data_b;
always_comb
	data_a = gpr[rd_addr_a];

always_comb
	data_b = gpr[rd_addr_b];

// multiplex the rd_data_a output based on the asked for addr
always_comb
begin
	case(rd_addr_a)
		0       : rd_data_a = {BUS_WIDTH{1'b0}};
		1       : rd_data_a = sw;
		2       : rd_data_a = {{BUS_WIDTH-1{1'b0}}, ready_in};
		3       : rd_data_a = {{BUS_WIDTH-1{1'b0}}, pattern_match};
		default : rd_data_a = data_a;
	endcase
end

// multiplex the rd_data_b output based on the asked for addr
always_comb
begin
	case(rd_addr_b)
		0       : rd_data_b = {BUS_WIDTH{1'b0}};
		1       : rd_data_b = sw;
		2       : rd_data_b = {{BUS_WIDTH-1{1'b0}}, ready_in};
		3       : rd_data_b = {{BUS_WIDTH-1{1'b0}}, pattern_match};
		default : rd_data_b = data_b;
	endcase
end

// register $7 is the output register
assign out_port = gpr[7];

endmodule

rtl/memory/program_memory.sv
module program_memory #(
    parameter ADDR_WIDTH  = 4,
    parameter INSTR_WIDTH = 12
) (
    input  logic [ADDR_WIDTH-1:0]  addr,
    output logic [INSTR_WIDTH-1:0] instr
); 

(* ramstyle = "MLAB" *)  logic [INSTR_WIDTH-1:0] prog_mem [(1<<ADDR_WIDTH)-1:0];

initial
    $readmemh("/home/jonahfoley/ELEC6234/a_fine_CPU/programs/prog.hex", prog_mem);
   
always_comb
    instr = prog_mem[addr]; 
  
endmodule

rtl/memory/program_counter.sv
module program_counter #(
    parameter ADDR_WIDTH = 3
) (
    input  logic                  clk, n_reset,
    input  logic                  en,
    output logic [ADDR_WIDTH-1:0] count
);
 
always_ff @(posedge clk) 
begin
    if (~n_reset) 
        count <= '0;
    else begin
        if (count == (2<<ADDR_WIDTH)-1) 
            count <= '0;
        else begin
            if (en)
                count <= count + { {ADDR_WIDTH-1{1'b0}}, 1'b1 };
        end
    end
end


endmodule

rtl/v2/CPU.sv
module CPU #(
    parameter INSTR_WIDTH      = 12,
    parameter OPCODE_WIDTH     = 3,
    parameter INSTR_ADDR_WIDTH = 4, 
    parameter REG_ADDR_WIDTH   = 3, 
    parameter BUS_WIDTH        = 8
) (
    input  logic                 clk,  
    input  logic                 n_reset,
    input  logic [BUS_WIDTH-1:0] sw,
    input  logic                 ready_in,
    output logic [BUS_WIDTH-1:0] out_port
);       

//the macro to dump signals   
`ifdef COCOTB_SIM
initial begin
    $dumpfile ("CPU.vcd");
    $dumpvars (0, CPU);
    #1;
end
`endif

// input switch handshaking
logic ready_in_p, pattern_match;
always_ff @(posedge clk)
    ready_in_p <= ready_in;

logic [BUS_WIDTH-1:0] sw_p;
always_ff @(posedge clk)
    sw_p <= sw;

assign pattern_match = ({ready_in_p, ready_in} == 2'b01);

// -- instr counter
logic [INSTR_ADDR_WIDTH-1:0] PC_count;
logic PC_en;
assign PC_en = (PC_wait & ~(rd_data_a[0] ^ instr[0])) | ~PC_wait;

program_counter #(
   INSTR_ADDR_WIDTH
) pc (
   .clk    (clk     ),
   .n_reset(n_reset ),
   .en     (PC_en   ),
   .count  (PC_count)
);

// -- program ROM
logic [INSTR_WIDTH-1:0] instr;

program_memory #(
    INSTR_ADDR_WIDTH,
    INSTR_WIDTH
) pm (
    .addr (PC_count),
    .instr(instr   )
);

// -- reg file
logic wr_res, we;
logic [REG_ADDR_WIDTH-1:0] wr_addr;
logic [BUS_WIDTH-1:0] rd_data_a, rd_data_b;

always_ff @(posedge clk) 
begin
    we      <= wr_res;
    wr_addr <= instr[8:6];
end

register_file #(
    BUS_WIDTH,
    REG_ADDR_WIDTH
) rf (
	.clk          (clk          ),  
	.sw           (sw_p         ),
    .ready_in     (ready_in     ),
	.pattern_match(pattern_match),
    .we           (we           ),
 	.wr_addr      (wr_addr      ),
	.wr_data      (ALU_result   ),
 	.rd_addr_a    (instr[5:3]   ), 
    .rd_addr_b    (instr[2:0]   ),
 	.rd_data_a    (rd_data_a    ), 
    .rd_data_b    (rd_data_b    ),
    .out_port     (out_port     )
);

// -- decoder
logic ALU_add, PC_wait;

instruction_decoder #(
    OPCODE_WIDTH
) id (
    .opcode    (instr[11:9]),                  
    .f_add     (ALU_add    ), 
    .f_wait    (PC_wait    ),            
    .wr_res    (wr_res     ),         
    .ALU_reg_en(ALU_reg_en )
);

// -- ALU
logic [BUS_WIDTH-1:0] ALU_result;
logic [4:0] ALU_reg_en; 

ALU #(
    BUS_WIDTH
) alu (
    .clk    (clk                                                   ),
    .ops    ({instr[7:0],instr[7:0],rd_data_b,instr[7:0],rd_data_a}),   
    .reg_en (ALU_reg_en                                            ),
    .f_add  (ALU_add                                               ),
    .result (ALU_result                                            )
);    

endmodule

simulation/v2/CPU/mux_21.vcd
$date
	Sun Apr 16 08:07:58 2023
$end
$version
	Icarus Verilog
$end
$timescale
	1ps
$end
$scope module CPU $end
$scope module alu $end
$scope module e_mux $end
$var wire 8 ! a [7:0] $end
$var wire 8 " b [7:0] $end
$var wire 1 # s $end
$var wire 8 $ out [7:0] $end
$upscope $end
$upscope $end
$upscope $end
$scope module CPU $end
$scope module alu $end
$scope module m0 $end
$var wire 8 % a [7:0] $end
$var wire 8 & b [7:0] $end
$var wire 8 ' out [7:0] $end
$var reg 16 ( mult_out [15:0] $end
$upscope $end
$upscope $end
$upscope $end
$scope module CPU $end
$scope module alu $end
$scope module m1 $end
$var wire 8 ) a [7:0] $end
$var wire 8 * b [7:0] $end
$var wire 8 + out [7:0] $end
$var reg 16 , mult_out [15:0] $end
$upscope $end
$upscope $end
$upscope $end
$scope module CPU $end
$scope module alu $end
$scope module a0 $end
$var wire 8 - out [7:0] $end
$var wire 8 . b [7:0] $end
$var wire 8 / a [7:0] $end
$var reg 9 0 add_out [8:0] $end
$upscope $end
$upscope $end
$upscope $end
$scope module CPU $end
$scope module alu $end
$scope module a1 $end
$var wire 8 1 a [7:0] $end
$var wire 8 2 b [7:0] $end
$var wire 8 3 out [7:0] $end
$var reg 9 4 add_out [8:0] $end
$upscope $end
$upscope $end
$upscope $end
$scope module CPU $end
$var wire 1 5 PC_en $end
$var wire 1 6 clk $end
$var wire 1 7 n_reset $end
$var wire 1 8 ready_in $end
$var wire 8 9 sw [7:0] $end
$var wire 1 : wr_res $end
$var wire 8 ; rd_data_b [7:0] $end
$var wire 8 < rd_data_a [7:0] $end
$var wire 1 = pattern_match $end
$var wire 8 > out_port [7:0] $end
$var wire 12 ? instr [11:0] $end
$var wire 1 @ PC_wait $end
$var wire 4 A PC_count [3:0] $end
$var wire 8 B ALU_result [7:0] $end
$var wire 5 C ALU_reg_en [4:0] $end
$var wire 1 # ALU_add $end
$var reg 1 D ready_in_p $end
$var reg 8 E sw_p [7:0] $end
$var reg 1 F we $end
$var reg 3 G wr_addr [2:0] $end
$scope module alu $end
$var wire 1 6 clk $end
$var wire 40 H ops [39:0] $end
$var wire 8 I result [7:0] $end
$var wire 5 J reg_en [4:0] $end
$var wire 8 K op_e [7:0] $end
$var wire 8 L mult_b [7:0] $end
$var wire 8 M mult_a [7:0] $end
$var wire 1 # f_add $end
$var wire 8 N add_a [7:0] $end
$var reg 8 O op_a_reg [7:0] $end
$var reg 8 P op_b_reg [7:0] $end
$var reg 8 Q op_c_reg [7:0] $end
$var reg 8 R op_d_reg [7:0] $end
$var reg 8 S op_e_reg [7:0] $end
$scope module a0 $end
$upscope $end
$scope module a1 $end
$upscope $end
$scope module e_mux $end
$upscope $end
$scope module m0 $end
$upscope $end
$scope module m1 $end
$upscope $end
$upscope $end
$scope module id $end
$var wire 3 T opcode [2:0] $end
$var reg 5 U ALU_reg_en [4:0] $end
$var reg 1 # f_add $end
$var reg 1 @ f_wait $end
$var reg 1 : wr_res $end
$upscope $end
$scope module pc $end
$var wire 1 6 clk $end
$var wire 1 5 en $end
$var wire 1 7 n_reset $end
$var reg 4 V count [3:0] $end
$upscope $end
$scope module pm $end
$var wire 4 W addr [3:0] $end
$var reg 12 X instr [11:0] $end
$upscope $end
$scope module rf $end
$var wire 1 6 clk $end
$var wire 8 Y out_port [7:0] $end
$var wire 1 = pattern_match $end
$var wire 3 Z rd_addr_a [2:0] $end
$var wire 3 [ rd_addr_b [2:0] $end
$var wire 1 8 ready_in $end
$var wire 8 \ sw [7:0] $end
$var wire 1 F we $end
$var wire 3 ] wr_addr [2:0] $end
$var wire 8 ^ wr_data [7:0] $end
$var reg 8 _ data_a [7:0] $end
$var reg 8 ` data_b [7:0] $end
$var reg 8 a rd_data_a [7:0] $end
$var reg 8 b rd_data_b [7:0] $end
$upscope $end
$upscope $end
$enddefinitions $end
#0
$dumpvars
b0 b
b0 a
bx `
bx _
bx ^
bx ]
b0 \
b1 [
b11 Z
bx Y
b10000011001 X
b0 W
b0 V
b0 U
b10 T
bx S
bx R
bx Q
bx P
bx O
bx N
bx M
bx L
b11001 K
b0 J
bx I
b1100100011001000000000001100100000000 H
bx G
0F
b0 E
0D
b0 C
bx B
b0 A
1@
b10000011001 ?
bx >
0=
b0 <
b0 ;
0:
b0 9
08
07
16
05
bx 4
bx 3
bx 2
bx 1
bx 0
bx /
bx .
bx -
bx ,
bx +
bx *
bx )
bx (
bx '
bx &
bx %
b11001 $
0#
b11001 "
b0 !
$end
#5000
06
#10000
b0 G
b0 ]
16
#15000
06
#20000
17
16
#25000
06
#30000
16
#35000
06
#40000
16
#45000
06
#50000
16
#55000
06
#60000
16
#65000
06
#70000
16
#75000
06
#80000
16
#85000
06
#90000
16
#95000
06
#100000
16
#105000
06
#110000
16
#115000
06
#120000
15
b1 !
b1100100011001000000000001100100000001 H
b1 <
b1 a
1=
18
b1010111 9
16
#125000
06
#130000
08
b1010111 $
b1010111 K
b1000 "
b11111 C
b11111 J
b11111 U
1:
0@
1#
b1010111 !
b0 T
b0 [
b1 Z
b0 ;
b0 b
b100000001000000000000000100001010111 H
b1010111 <
b1010111 a
b100001000 ?
b100001000 X
b1010111 E
b1010111 \
0=
1D
b1 A
b1 V
b1 W
16
#135000
06
#140000
b1010111 3
b1010111 B
b1010111 I
b1010111 ^
05
b1010111 4
b0 !
b11001 $
b11001 K
b0 -
b0 1
b0 N
b11001 "
b0 <
b0 a
b1010111 ;
b1010111 b
b0 C
b0 J
b0 U
0:
1@
0#
b0 0
b1100100011001010101110001100100000000 H
b10 T
b1 [
b11 Z
b0 '
b0 /
b0 M
b0 +
b0 .
b0 L
b10000011001 ?
b10000011001 X
b0 (
b0 ,
b10 A
b10 V
b10 W
b1010111 %
b1010111 O
b0 &
b0 P
b0 )
b0 Q
b0 *
b0 R
b1010111 2
b1010111 S
0D
b100 G
b100 ]
1F
16
#145000
06
#150000
b0 G
b0 ]
0F
16
#155000
06
#160000
16
#165000
06
#170000
16
#175000
06
#180000
16
#185000
06
#190000
15
b1 !
b1100100011001010101110001100100000001 H
b1 <
b1 a
1=
18
b110001 9
16
#195000
06
#200000
08
b110001 $
b110001 K
b1001000 "
b11111 C
b11111 J
b11111 U
1:
0@
1#
b0 T
b0 [
b1 Z
b110001 !
b0 ;
b0 b
b101001000 ?
b101001000 X
b100100001001000000000000100100000110001 H
b110001 <
b110001 a
b11 A
b11 V
b11 W
0=
1D
b110001 E
b110001 \
16
#205000
06
#210000
b1100000 $
b1100000 K
b1010111 !
b1100000 "
b10 C
b10 J
b10 U
0:
0#
b1010111 <
b1010111 a
b1010111 _
b110001 3
b110001 B
b110001 I
b110001 ^
b110000001100000000000000110000001010111 H
b11 T
b100 Z
b110001 4
b11001100000 ?
b11001100000 X
b101 G
b101 ]
1F
0D
b110001 2
b110001 S
b110001 %
b110001 O
b100 A
b100 V
b100 W
16
#215000
06
#220000
b1010101 3
b1010101 B
b1010101 I
b1010101 ^
b1010101 4
b1000000 $
b1000000 K
b0 !
b100100 -
b100100 1
b100100 N
b1000000 "
bx _
b0 <
b0 a
b1000 C
b1000 J
b1000 U
b100100 0
b100000001000000000000000100000000000000 H
b100 T
b0 Z
b100100 '
b100100 /
b100100 M
b100001000000 ?
b100001000000 X
b1001001100000 (
b101 A
b101 V
b101 W
b1100000 &
b1100000 P
b1 G
b1 ]
0F
16
#225000
06
#230000
b10100 $
b10100 K
b10100 "
b10000 C
b10000 J
b10000 U
b1010111 ;
b1010111 b
b1010111 `
b1010000010100010101110001010000000000 H
b101 T
b100 [
b10 Z
b101000010100 ?
b101000010100 X
b1000000 *
b1000000 R
b110 A
b110 V
b110 W
16
#235000
06
#240000
b10100101 $
b10100101 K
b1010111 !
b10100101 "
b101 C
b101 J
b101 U
1:
b110001 ;
b110001 b
b110001 `
b1010111 <
b1010111 a
b1010111 _
b1010010110100101001100011010010101010111 H
b1 T
b101 [
b100 Z
b111000 3
b111000 B
b111000 I
b111000 ^
b1110100101 ?
b1110100101 X
b111000 4
b111 A
b111 V
b111 W
b10100 2
b10100 S
b0 G
b0 ]
16
#245000
06
#250000
b1101101 3
b1101101 B
b1101101 I
b1101101 ^
b1101101 4
b1011001 -
b1011001 1
b1011001 N
b11000000 $
b11000000 K
b0 !
b1011001 0
b11000000 "
b10 C
b10 J
b10 U
0:
b0 ;
b0 b
bx `
b0 <
b0 a
bx _
b11000 +
b11000 .
b11000 L
b1000001 '
b1000001 /
b1000001 M
b1100000011000000000000001100000000000000 H
b11 T
b0 [
b0 Z
b110001000000 ,
b10000010100000 (
b11011000000 ?
b11011000000 X
b110 G
b110 ]
1F
b110001 )
b110001 Q
b1010111 %
b1010111 O
b1000 A
b1000 V
b1000 W
16
#255000
06
#260000
b0 3
b0 B
b0 I
b0 ^
b0 4
b1100000 $
b1100000 K
b1010111 !
b11101100 -
b11101100 1
b11101100 N
b1100000 "
b1010111 _
b1010111 <
b1010111 a
b1000 C
b1000 J
b1000 U
b111101100 0
b110000001100000000000000110000001010111 H
b100 T
b100 Z
b11010100 '
b11010100 /
b11010100 M
b100001100000 ?
b100001100000 X
b1110101001000000 (
b1001 A
b1001 V
b1001 W
b11000000 &
b11000000 P
b11 G
b11 ]
0F
16
#265000
06
#270000
b1100 3
b1100 B
b1100 I
b1100 ^
b1100 4
b11111000 -
b11111000 1
b11111000 N
b11101100 $
b11101100 K
b110001 !
b111111000 0
b11101100 "
b10000 C
b10000 J
b10000 U
b1010111 ;
b1010111 b
b1010111 `
b110001 <
b110001 a
b110001 _
b100100 +
b100100 .
b100100 L
b1110110011101100010101111110110000110001 H
b101 T
b100 [
b101 Z
b1001001100000 ,
b101011101100 ?
b101011101100 X
b1 G
b1 ]
b1100000 *
b1100000 R
b1010 A
b1010 V
b1010 W
16
#275000
06
#280000
b1100101 $
b1100101 K
b1010111 !
b1100101 "
b101 C
b101 J
b101 U
1:
b110001 ;
b110001 b
b110001 `
b1010111 <
b1010111 a
b1010111 _
b110010101100101001100010110010101010111 H
b1 T
b101 [
b100 Z
b11100100 3
b11100100 B
b11100100 I
b11100100 ^
b1101100101 ?
b1101100101 X
b111100100 4
b1011 A
b1011 V
b1011 W
b11101100 2
b11101100 S
b11 G
b11 ]
16
#285000
06
#290000
b1101101 $
b1101101 K
b1101101 !
b11110000 "
b11111 C
b11111 J
b11111 U
1#
b0 ;
b0 b
bx `
b1101101 <
b1101101 a
b1101101 _
b1111000011110000000000001111000001101101 H
b0 T
b0 [
b110 Z
b111110000 ?
b111110000 X
b101 G
b101 ]
1F
b1100 A
b1100 V
b1100 W
16
#295000
06
#300000
05
b0 !
b10001 $
b10001 K
b0 -
b0 1
b0 N
b10001 "
bx _
b0 <
b0 a
b110001 ;
b110001 b
b0 C
b0 J
b0 U
0:
1@
0#
b0 0
b1000100010001001100010001000100000000 H
b10 T
b1 [
b10 Z
b0 '
b0 /
b0 M
b0 +
b0 .
b0 L
b1101101 3
b1101101 B
b1101101 I
b1101101 ^
b10000010001 ?
b10000010001 X
b0 (
b0 ,
b1101101 4
b1101 A
b1101 V
b1101 W
b1101101 %
b1101101 O
b0 &
b0 P
b0 )
b0 Q
b0 *
b0 R
b1101101 2
b1101101 S
b111 G
b111 ]
16
#305000
06
#310000
b0 G
b0 ]
0F
b1101101 >
b1101101 Y
16
#315000
06
#320000
15
b1 !
b1000100010001001100010001000100000001 H
b1 <
b1 a
1=
18
16
#325000
06
#330000
b11100100 $
b11100100 K
b11100100 !
b11101000 "
b11111 C
b11111 J
b11111 U
1:
0@
1#
b0 ;
b0 b
b11100100 <
b11100100 a
b11100100 _
b1110100011101000000000001110100011100100 H
b0 T
b0 [
b101 Z
b111101000 ?
b111101000 X
0=
1D
b1110 A
b1110 V
b1110 W
16
#335000
06
#340000
05
b10000 $
b10000 K
b1 !
b10000 "
b0 C
b0 J
b0 U
0:
1@
0#
b1 <
b1 a
bx _
b1000000010000000000000001000000000001 H
b10 T
b10 Z
b11100100 3
b11100100 B
b11100100 I
b11100100 ^
b10000010000 ?
b10000010000 X
b111100100 4
b1111 A
b1111 V
b1111 W
b11100100 %
b11100100 O
b11100100 2
b11100100 S
b111 G
b111 ]
1F
16
#345000
06
#350000
b0 G
b0 ]
0F
b11100100 >
b11100100 Y
16
#355000
06
#360000
15
b0 !
b1000000010000000000000001000000000000 H
b0 <
b0 a
08
16
#365000
06
#370000
05
b11001 $
b11001 K
b11001 "
b110001 ;
b110001 b
b1100100011001001100010001100100000000 H
b1 [
b11 Z
b10000011001 ?
b10000011001 X
0D
b0 A
b0 V
b0 W
16
#375000
06
#380000
16
#385000
06
#390000
16
#395000
06
#400000
16
#405000
06
#410000
15
b1 !
b1100100011001001100010001100100000001 H
b1 <
b1 a
1=
18
b11000001 9
16
#415000
06
#420000
08
b11000001 $
b11000001 K
b1000 "
b11111 C
b11111 J
b11111 U
1:
0@
1#
b0 T
b0 [
b1 Z
b11000001 !
b0 ;
b0 b
b100001000 ?
b100001000 X
b100000001000000000000000100011000001 H
b11000001 <
b11000001 a
b1 A
b1 V
b1 W
0=
1D
b11000001 E
b11000001 \
16
#425000
06
#430000
05
b11001 $
b11001 K
b0 !
b11001 "
b0 C
b0 J
b0 U
0:
1@
0#
b11000001 ;
b11000001 b
b0 <
b0 a
b11000001 3
b11000001 B
b11000001 I
b11000001 ^
b1100100011001110000010001100100000000 H
b10 T
b1 [
b11 Z
b111000001 4
b10000011001 ?
b10000011001 X
b100 G
b100 ]
1F
0D
b11000001 2
b11000001 S
b11000001 %
b11000001 O
b10 A
b10 V
b10 W
16
#435000
06
#440000
b0 G
b0 ]
0F
16
#445000
06
#450000
15
b1 !
b1100100011001110000010001100100000001 H
b1 <
b1 a
1=
18
b1010111 9
16
#455000
06
#460000
08
b1010111 $
b1010111 K
b1001000 "
b11111 C
b11111 J
b11111 U
1:
0@
1#
b0 T
b0 [
b1 Z
b1010111 !
b0 ;
b0 b
b101001000 ?
b101001000 X
b100100001001000000000000100100001010111 H
b1010111 <
b1010111 a
b11 A
b11 V
b11 W
0=
1D
b1010111 E
b1010111 \
16
#465000
06
#470000
b1100000 $
b1100000 K
b11000001 !
b1100000 "
b10 C
b10 J
b10 U
0:
0#
b11000001 <
b11000001 a
b11000001 _
b1010111 3
b1010111 B
b1010111 I
b1010111 ^
b110000001100000000000000110000011000001 H
b11 T
b100 Z
b1010111 4
b11001100000 ?
b11001100000 X
b101 G
b101 ]
1F
0D
b1010111 2
b1010111 S
b1010111 %
b1010111 O
b100 A
b100 V
b100 W
16
#475000
06
#480000
b10011000 3
b10011000 B
b10011000 I
b10011000 ^
b10011000 4
b1000000 $
b1000000 K
b0 !
b1000001 -
b1000001 1
b1000001 N
b1000000 "
bx _
b0 <
b0 a
b1000 C
b1000 J
b1000 U
b1000001 0
b100000001000000000000000100000000000000 H
b100 T
b0 Z
b1000001 '
b1000001 /
b1000001 M
b100001000000 ?
b100001000000 X
b10000010100000 (
b101 A
b101 V
b101 W
b1100000 &
b1100000 P
b1 G
b1 ]
0F
16
#485000
06
#490000
b10100 $
b10100 K
b10100 "
b10000 C
b10000 J
b10000 U
b11000001 ;
b11000001 b
b11000001 `
b1010000010100110000010001010000000000 H
b101 T
b100 [
b10 Z
b101000010100 ?
b101000010100 X
b1000000 *
b1000000 R
b110 A
b110 V
b110 W
16
#495000
06
#500000
b10100101 $
b10100101 K
b11000001 !
b10100101 "
b101 C
b101 J
b101 U
1:
b1010111 ;
b1010111 b
b1010111 `
b11000001 <
b11000001 a
b11000001 _
b1010010110100101010101111010010111000001 H
b1 T
b101 [
b100 Z
b1010101 3
b1010101 B
b1010101 I
b1010101 ^
b1110100101 ?
b1110100101 X
b1010101 4
b111 A
b111 V
b111 W
b10100 2
b10100 S
b0 G
b0 ]
16
#505000
06
#510000
b1111 3
b1111 B
b1111 I
b1111 ^
b1111 4
b11111011 -
b11111011 1
b11111011 N
b11000000 $
b11000000 K
b0 !
b111111011 0
b11000000 "
b10 C
b10 J
b10 U
0:
b0 ;
b0 b
bx `
b0 <
b0 a
bx _
b101011 +
b101011 .
b101011 L
b11010000 '
b11010000 /
b11010000 M
b1100000011000000000000001100000000000000 H
b11 T
b0 [
b0 Z
b1010111000000 ,
b1110100001100000 (
b11011000000 ?
b11011000000 X
b110 G
b110 ]
1F
b1010111 )
b1010111 Q
b11000001 %
b11000001 O
b1000 A
b1000 V
b1000 W
16
#515000
06
#520000
b1011110 3
b1011110 B
b1011110 I
b1011110 ^
b1011110 4
b1100000 $
b1100000 K
b11000001 !
b1001010 -
b1001010 1
b1001010 N
b1100000 "
b11000001 _
b11000001 <
b11000001 a
b1000 C
b1000 J
b1000 U
b1001010 0
b110000001100000000000000110000011000001 H
b100 T
b100 Z
b11111 '
b11111 /
b11111 M
b100001100000 ?
b100001100000 X
b111111000000 (
b1001 A
b1001 V
b1001 W
b11000000 &
b11000000 P
b11 G
b11 ]
0F
16
#525000
06
#530000
b1110100 3
b1110100 B
b1110100 I
b1110100 ^
b1110100 4
b1100000 -
b1100000 1
b1100000 N
b11101100 $
b11101100 K
b1010111 !
b1100000 0
b11101100 "
b10000 C
b10000 J
b10000 U
b11000001 ;
b11000001 b
b11000001 `
b1010111 <
b1010111 a
b1010111 _
b1000001 +
b1000001 .
b1000001 L
b1110110011101100110000011110110001010111 H
b101 T
b100 [
b101 Z
b10000010100000 ,
b101011101100 ?
b101011101100 X
b1 G
b1 ]
b1100000 *
b1100000 R
b1010 A
b1010 V
b1010 W
16
#535000
06
#540000
b1100101 $
b1100101 K
b11000001 !
b1100101 "
b101 C
b101 J
b101 U
1:
b1010111 ;
b1010111 b
b1010111 `
b11000001 <
b11000001 a
b11000001 _
b110010101100101010101110110010111000001 H
b1 T
b101 [
b100 Z
b1001100 3
b1001100 B
b1001100 I
b1001100 ^
b1101100101 ?
b1101100101 X
b1001100 4
b1011 A
b1011 V
b1011 W
b11101100 2
b11101100 S
b11 G
b11 ]
16
#545000
06
#550000
b1111 $
b1111 K
b1111 !
b11110000 "
b11111 C
b11111 J
b11111 U
1#
b0 ;
b0 b
bx `
b1111 <
b1111 a
b1111 _
b1111000011110000000000001111000000001111 H
b0 T
b0 [
b110 Z
b111110000 ?
b111110000 X
b101 G
b101 ]
1F
b1100 A
b1100 V
b1100 W
16
#555000
06
