rtl/v6/mux_21.sv
module mux_21 #(
    parameter BIT_WIDTH = 8
) (   
    input  logic s, 
    input  logic [BIT_WIDTH-1:0] a, b,
    output logic [BIT_WIDTH-1:0] out
);
    `ifdef COCOTB_SIM
    initial begin
        $dumpfile ("mux_21.vcd");
        $dumpvars (0, mux_21);
        #1;
    end
    `endif 
    assign out = s ? a : b;
endmodule

rtl/v7/sfixed_adder.sv
import datatypes::max;

module sfixed_adder #(
    parameter A_LEFT    = 3, 
    parameter A_RIGHT   = 4, 
    parameter B_LEFT    = 3, 
    parameter B_RIGHT   = 4,
    parameter OUT_LEFT  = 4, 
    parameter OUT_RIGHT = 4
) (   
    input  logic signed [(A_LEFT+A_RIGHT+1)-1:0]     a,
    input  logic signed [(B_LEFT+B_RIGHT+1)-1:0]     b,
    output logic signed [(OUT_LEFT+OUT_RIGHT+1)-1:0] out
);

`ifdef COCOTB_SIM
initial begin
    $dumpfile ("sfixed_adder.vcd");
    $dumpvars (0, sfixed_adder);
    #1;
end
`endif

localparam OUTPUT_SIZE = (max(A_LEFT,B_LEFT)+1)+max(A_RIGHT,B_RIGHT)+1; 

logic signed [OUTPUT_SIZE-1:0] add_out;

always_comb
    add_out = a + b;

assign out = add_out[max(A_RIGHT,B_RIGHT)+OUT_LEFT:max(A_RIGHT,B_RIGHT)-OUT_RIGHT];

endmodule

rtl/v7/sfixed_mult.sv
module sfixed_mult #(
    parameter A_LEFT    = 3, 
    parameter A_RIGHT   = 4,
    parameter B_LEFT    = 3, 
    parameter B_RIGHT   = 4,
    parameter OUT_LEFT  = 7, 
    parameter OUT_RIGHT = 8
) (
    input  logic signed [(A_LEFT+A_RIGHT+1)-1:0]     a,
    input  logic signed [(B_LEFT+B_RIGHT+1)-1:0]     b,
    output logic signed [(OUT_LEFT+OUT_RIGHT+1)-1:0] out
);
`ifdef COCOTB_SIM
initial begin
    $dumpfile ("sfixed_mult.vcd");
    $dumpvars (0, sfixed_mult);
    #1;
end
`endif

localparam OUTPUT_SIZE = (A_LEFT+B_LEFT+1)+(A_RIGHT+B_RIGHT)+1; 
                                                                
logic signed [OUTPUT_SIZE-1:0] mult_out;

always_comb
    mult_out = a * b;

assign out = mult_out[(A_RIGHT+B_RIGHT)+OUT_LEFT:(A_RIGHT+B_RIGHT)-OUT_RIGHT];

endmodule

rtl/v8/ALU_mult_stage.sv
module ALU_mult_stage #(
    parameter BUS_WIDTH = 8
) (
    input  logic clk,
    input  logic a_en, b_en, c_en, d_en,
    input  logic [BUS_WIDTH-1:0] data_a, data_b, coeff,
    output logic [BUS_WIDTH-1:0] mult_a, mult_b
);
`ifdef COCOTB_SIM
initial begin
    $dumpfile ("ALU_mult_stage.vcd");
    $dumpvars (0, ALU_mult_stage);
    #1;
end
`endif

// input registers
logic [BUS_WIDTH-1:0] op_b_reg, op_d_reg;

always_ff @( posedge clk ) begin 
    if (b_en) 
        op_b_reg <= coeff;
end

always_ff @( posedge clk ) begin 
    if (d_en)
        op_d_reg <= coeff;
end

sfixed_mult #(
    7, 
    0,
    0, 
    7,
    7,
    0 
) m0 (
    .a  (data_a  ), // int
    .b  (op_b_reg), // tf
    .out(mult_a  )
);

sfixed_mult #(
    7, 
    0,
    0, 
    7,
    7,
    0 
) m1 (
    .a  (data_b  ), // int
    .b  (op_d_reg), // tf
    .out(mult_b  )
);

    
endmodule

rtl/v8/ALU_v2.sv
module ALU_v2 #(
    parameter BUS_WIDTH  = 8
) (
    input  logic                 clk, 
    input  logic [BUS_WIDTH-1:0] imm,
    input  logic [BUS_WIDTH-1:0] data_a,    
    input  logic [BUS_WIDTH-1:0] data_b,    
    input  logic [2:0]           reg_en,
    input  logic                 f_add,
    output logic [BUS_WIDTH-1:0] result 
);       

// setting up of add/subtract inputs
logic [BUS_WIDTH-1:0] op_e, coeff;
logic [BUS_WIDTH-1:0] op_e_reg;

mux_21 #(
    BUS_WIDTH
) op_e_mux (   
    .s  (f_add), 
    .a  (data_a), 
    .b  (imm  ),
    .out(op_e )
);

mux_21 #(
    BUS_WIDTH
) coeff_mux (   
    .s  (f_add            ), 
    .a  ({BUS_WIDTH{1'b0}}), 
    .b  (imm              ),
    .out(coeff            )
);


// input registers
always_ff @( posedge clk ) begin
    if (reg_en[2])
        op_e_reg <= op_e;
end

// the computational part
logic [BUS_WIDTH-1:0] mult_a, mult_b, add_a;

ALU_mult_stage #(
    BUS_WIDTH
) am1 (
    .clk   (clk),
    .b_en  (reg_en[0]), 
    .d_en  (reg_en[1]),
    .data_a(data_a),
    .data_b(data_b),
    .coeff (coeff ),
    .mult_a(mult_a),
    .mult_b(mult_b)
);


sfixed_adder #(
    7, 
    0, 
    7, 
    0,
    7, 
    0
) a0 ( 
    .a  (mult_a), // int
    .b  (mult_b), // int
    .out(add_a )
);

sfixed_adder #(
    7, 
    0, 
    7, 
    0,
    7, 
    0
) a1 (  
    .a  (add_a   ), // int
    .b  (op_e_reg), // int
    .out(result  )
);

endmodule

include/opcodes.sv
//-----------------------------------------------------
// File Name : opcodes.sv
// Function : pMIPS instr opcode definitions
// Author: jf
//-----------------------------------------------------
//
`define NOP  6'b000000
`define ADD  6'b000001
`define SUB  6'b000010
`define ADDI 6'b000011
`define SUBI 6'b000100
`define BEQ  6'b000101
`define BNE  6'b000110
`define BGE  6'b000111
`define BLO  6'b001000

rtl/v8/instruction_decoder.sv
`include "opcodes.sv"

module instruction_decoder #(
    parameter OPCODE_WIDTH = 3
) (
    input  logic [OPCODE_WIDTH-1:0] opcode,                  
    output logic                    f_add,            
    output logic                    f_wait,       
    output logic                    f_load,      
    output logic                    wr_res,         
    output logic [2:0]              ALU_reg_en
);

always_comb 
begin
    case(opcode)    
        `MOV : begin
            f_load     = '0;
            f_add      = '1; 
            f_wait     = '0;
            wr_res     = '1; 
            ALU_reg_en = 5'b111; // C, A
        end
        `MAC : begin 
            f_load     = '0;
            f_add      = '0;
            f_wait     = '0;
            wr_res     = '1; 
            ALU_reg_en = 5'b000; // C, A
        end
        `WAIT: begin
            f_load     = '0;
            f_add      = '0;
            f_wait     = '1;
            wr_res     = '0;
            ALU_reg_en = 5'b000;
        end
        `SETB: begin
            f_load     = '0;
            f_add      = '0;
            f_wait     = '0;
            wr_res     = '0;
            ALU_reg_en = 5'b001; 
        end
        `SETD: begin
            f_load     = '0;
            f_add      = '0;
            f_wait     = '0;
            wr_res     = '0;
            ALU_reg_en = 5'b010;
        end
        `SETE: begin
            f_load     = '0;
            f_add      = '0;
            f_wait     = '0;
            wr_res     = '0;
            ALU_reg_en = 5'b100;
        end
        `LDSW: begin
            f_load     = '1;
            f_add      = '1;
            f_wait     = '0;
            wr_res     = '1;
            ALU_reg_en = 5'b000;
        end
        default : begin
            f_load     = '0;
            f_add      = '0;
            f_wait     = '0;
            wr_res     = '0;
            ALU_reg_en = '0;
        end
    endcase 
end 

endmodule

rtl/v3/register_file.sv
module register_file #(
    parameter BUS_WIDTH  = 8,
    parameter ADDR_WIDTH = 3
) (
	input  logic                  clk, 
	input  logic                  we,
 	input  logic [ADDR_WIDTH-1:0] wr_addr,
	input  logic [BUS_WIDTH-1:0]  wr_data,
 	input  logic [ADDR_WIDTH-1:0] rd_addr_a, rd_addr_b,
 	output logic [BUS_WIDTH-1:0]  rd_data_a, rd_data_b
);

localparam N = (1 << ADDR_WIDTH);

logic [BUS_WIDTH-1:0] gpr [N-1:0];

initial begin
	for (int i = 0; i < N; i = i + 1)
		gpr[i] = '0;
end

// syncrhonous RAM write
always_ff @ (posedge clk)
begin
	if (we) begin 
		gpr[wr_addr] <= wr_data;
	end
	rd_data_b <= gpr[rd_addr_b];
	rd_data_a <= gpr[rd_addr_a];
end	
	

endmodule

rtl/v8/program_memory.sv
module program_memory #(
    parameter ADDR_WIDTH  = 4,
    parameter INSTR_WIDTH = 12
) (
    input  logic [ADDR_WIDTH-1:0]  addr,
    output logic [INSTR_WIDTH-1:0] instr
); 

(* ramstyle = "mlab" *) logic [INSTR_WIDTH-1:0] prog_mem [(1<<ADDR_WIDTH)-1:0];

initial
    $readmemh("/home/jonahfoley/ELEC6234/a_fine_CPU/programs/prog_3.hex", prog_mem);
   
always_comb
    instr = prog_mem[addr]; 
  
endmodule

rtl/v8/program_counter.sv
module program_counter #(
    parameter ADDR_WIDTH = 3
) (
    input  logic                  clk, n_reset,
    input  logic                  en,
    output logic [ADDR_WIDTH-1:0] count
);
 
always_ff @(posedge clk, negedge n_reset) 
begin   
    if (~n_reset) 
        count <= '0;
    else begin
        if (en)
            count <= count + { {ADDR_WIDTH-1{1'b0}}, 1'b1 };
    end
end

endmodule

rtl/v8/CPU.sv
module CPU #(
    parameter INSTR_WIDTH      = 24,
    parameter OPCODE_WIDTH     = 3,
    parameter INSTR_ADDR_WIDTH = 4, 
    parameter REG_ADDR_WIDTH   = 2, 
    parameter BUS_WIDTH        = 8
) (
    input  logic                 clk,  
    input  logic                 n_reset,
    input  logic [BUS_WIDTH-1:0] in_port,
    input  logic                 ready_in,
    output logic [BUS_WIDTH-1:0] out_port
);       

//the macro to dump signals   
`ifdef COCOTB_SIM
initial begin
    $dumpfile ("CPU.vcd");
    $dumpvars (0, CPU);
    #1;
end
`endif

// input switch handshaking
logic ready_in_p, pattern_match;
always_ff @(posedge clk)
    ready_in_p <= ready_in;

logic [1:0][BUS_WIDTH-1:0] sw;
always_ff @(posedge clk)
    sw <= {sw[0], in_port};

assign pattern_match = (~ready_in_p & ready_in);

// -- instr counter
logic [INSTR_ADDR_WIDTH-1:0] PC_count;
logic PC_en, PC_comparator;

mux_21 #(
    1
) PC_en_mux (
    .s  (instr[3]     ), // differentiate between instr[5:3] == 001 (pattern) / 000 (rdy)
    .a  (pattern_match), // 001 -> pattern
    .b  (ready_in     ), // 000 -> ready in 
    .out(PC_comparator)
);

assign PC_en = ~(PC_wait & (PC_comparator ^ instr[0]));

program_counter #(
   INSTR_ADDR_WIDTH
) pc (
   .clk    (clk     ),
   .n_reset(n_reset ),
   .en     (PC_en   ),
   .count  (PC_count)
);

// -- program ROM
logic [INSTR_WIDTH-1:0] instr;

program_memory #(
    INSTR_ADDR_WIDTH,
    INSTR_WIDTH
) pm (
    .addr (PC_count),
    .instr(instr   )
);

// -- reg file
logic wr_res;
logic we;
logic [REG_ADDR_WIDTH-1:0] wr_addr;
logic [BUS_WIDTH-1:0] rd_data_a, rd_data_b;

always_ff @(posedge clk) 
begin
    we      <= wr_res;
    wr_addr <= instr[7:6];
end

register_file #(
    BUS_WIDTH,
    3
) rf (
	.clk      (clk       ),  
    .we       (we        ),
 	.wr_addr  (wr_addr   ),
	.wr_data  (wr_data   ),
 	.rd_addr_a(instr[4:3]), 
    .rd_addr_b(instr[1:0]),
 	.rd_data_a(rd_data_a ), 
    .rd_data_b(rd_data_b )
);

// -- decoder
logic f_add, f_load, PC_wait;
logic [2:0] reg_en; 

instruction_decoder #(
    OPCODE_WIDTH
) id (
    .opcode    (instr[11:9]),                  
    .f_add     (f_add      ), 
    .f_wait    (PC_wait    ),            
    .f_load    (f_load     ),            
    .wr_res    (wr_res     ),         
    .ALU_reg_en(reg_en     )
);

// -- ALU
logic [BUS_WIDTH-1:0] ALU_result;
logic [BUS_WIDTH-1:0] ALU_imm;
logic [2:0]           ALU_reg_en; 
logic                 ALU_add, ALU_load;

always_ff @(posedge clk) begin
    ALU_imm    <= instr[7:0];
    ALU_load   <= f_load;
    ALU_add    <= f_add;
    ALU_reg_en <= reg_en;
end

ALU_v2 #(
    BUS_WIDTH
) alu (
    .clk   (clk       ),
    .imm   (ALU_imm   ),
    .data_a(rd_data_a ),
    .data_b(rd_data_b ),   
    .reg_en(ALU_reg_en),
    .f_add (ALU_add   ),
    .result(ALU_result)
);    

logic [BUS_WIDTH-1:0] wr_data;

mux_21 #(
    BUS_WIDTH
) ALU_res_mux (   
    .s  (ALU_load  ), 
    .a  (sw[1]     ), 
    .b  (ALU_result),
    .out(wr_data   )
);

assign out_port = ALU_result;

endmodule

simulation/v8/CPU/mux_21.vcd
$date
	Sun Apr 23 23:58:07 2023
$end
$version
	Icarus Verilog
$end
$timescale
	1ps
$end
$scope module CPU $end
$scope module PC_en_mux $end
$var wire 1 ! a $end
$var wire 1 " b $end
$var wire 1 # s $end
$var wire 1 $ out $end
$upscope $end
$upscope $end
$scope module CPU $end
$scope module alu $end
$scope module op_e_mux $end
$var wire 8 % b [7:0] $end
$var wire 1 & s $end
$var wire 8 ' out [7:0] $end
$var wire 8 ( a [7:0] $end
$upscope $end
$upscope $end
$upscope $end
$scope module CPU $end
$scope module alu $end
$scope module coeff_mux $end
$var wire 8 ) a [7:0] $end
$var wire 8 * b [7:0] $end
$var wire 1 & s $end
$var wire 8 + out [7:0] $end
$upscope $end
$upscope $end
$upscope $end
$scope module CPU $end
$scope module alu $end
$scope module am1 $end
$scope module m0 $end
$var wire 8 , b [7:0] $end
$var wire 8 - out [7:0] $end
$var wire 8 . a [7:0] $end
$var reg 16 / mult_out [15:0] $end
$upscope $end
$upscope $end
$upscope $end
$upscope $end
$scope module CPU $end
$scope module alu $end
$scope module am1 $end
$scope module m1 $end
$var wire 8 0 b [7:0] $end
$var wire 8 1 out [7:0] $end
$var wire 8 2 a [7:0] $end
$var reg 16 3 mult_out [15:0] $end
$upscope $end
$upscope $end
$upscope $end
$upscope $end
$scope module CPU $end
$scope module alu $end
$scope module am1 $end
$var wire 1 4 a_en $end
$var wire 1 5 b_en $end
$var wire 1 6 c_en $end
$var wire 1 7 clk $end
$var wire 1 8 d_en $end
$var wire 8 9 mult_b [7:0] $end
$var wire 8 : mult_a [7:0] $end
$var wire 8 ; data_b [7:0] $end
$var wire 8 < data_a [7:0] $end
$var wire 8 = coeff [7:0] $end
$var reg 8 > op_b_reg [7:0] $end
$var reg 8 ? op_d_reg [7:0] $end
$scope module m0 $end
$upscope $end
$scope module m1 $end
$upscope $end
$upscope $end
$upscope $end
$upscope $end
$scope module CPU $end
$scope module alu $end
$scope module a0 $end
$var wire 8 @ out [7:0] $end
$var wire 8 A b [7:0] $end
$var wire 8 B a [7:0] $end
$var reg 9 C add_out [8:0] $end
$upscope $end
$upscope $end
$upscope $end
$scope module CPU $end
$scope module alu $end
$scope module a1 $end
$var wire 8 D a [7:0] $end
$var wire 8 E b [7:0] $end
$var wire 8 F out [7:0] $end
$var reg 9 G add_out [8:0] $end
$upscope $end
$upscope $end
$upscope $end
$scope module CPU $end
$scope module ALU_res_mux $end
$var wire 8 H a [7:0] $end
$var wire 1 I s $end
$var wire 8 J out [7:0] $end
$var wire 8 K b [7:0] $end
$upscope $end
$upscope $end
$scope module CPU $end
$var wire 1 L PC_en $end
$var wire 1 7 clk $end
$var wire 8 M in_port [7:0] $end
$var wire 1 N n_reset $end
$var wire 8 O out_port [7:0] $end
$var wire 1 ! pattern_match $end
$var wire 1 " ready_in $end
$var wire 1 P wr_res $end
$var wire 8 Q wr_data [7:0] $end
$var wire 3 R reg_en [2:0] $end
$var wire 8 S rd_data_b [7:0] $end
$var wire 8 T rd_data_a [7:0] $end
$var wire 12 U instr [11:0] $end
$var wire 1 V f_load $end
$var wire 1 W f_add $end
$var wire 1 X PC_wait $end
$var wire 4 Y PC_count [3:0] $end
$var wire 1 $ PC_comparator $end
$var wire 8 Z ALU_result [7:0] $end
$var reg 1 & ALU_add $end
$var reg 8 [ ALU_imm [7:0] $end
$var reg 1 I ALU_load $end
$var reg 3 \ ALU_reg_en [2:0] $end
$var reg 1 ] ready_in_p $end
$var reg 16 ^ sw [15:0] $end
$var reg 1 _ we $end
$var reg 2 ` wr_addr [1:0] $end
$scope module ALU_res_mux $end
$upscope $end
$scope module PC_en_mux $end
$upscope $end
$scope module alu $end
$var wire 1 7 clk $end
$var wire 1 & f_add $end
$var wire 8 a imm [7:0] $end
$var wire 3 b reg_en [2:0] $end
$var wire 8 c result [7:0] $end
$var wire 8 d op_e [7:0] $end
$var wire 8 e mult_b [7:0] $end
$var wire 8 f mult_a [7:0] $end
$var wire 8 g data_b [7:0] $end
$var wire 8 h data_a [7:0] $end
$var wire 8 i coeff [7:0] $end
$var wire 8 j add_a [7:0] $end
$var reg 8 k op_e_reg [7:0] $end
$scope module a0 $end
$upscope $end
$scope module a1 $end
$upscope $end
$scope module am1 $end
$scope module m0 $end
$upscope $end
$scope module m1 $end
$upscope $end
$upscope $end
$scope module coeff_mux $end
$upscope $end
$scope module op_e_mux $end
$upscope $end
$upscope $end
$scope module id $end
$var wire 3 l opcode [2:0] $end
$var reg 3 m ALU_reg_en [2:0] $end
$var reg 1 W f_add $end
$var reg 1 V f_load $end
$var reg 1 X f_wait $end
$var reg 1 P wr_res $end
$upscope $end
$scope module pc $end
$var wire 1 7 clk $end
$var wire 1 L en $end
$var wire 1 N n_reset $end
$var reg 4 n count [3:0] $end
$upscope $end
$scope module pm $end
$var wire 4 o addr [3:0] $end
$var reg 12 p instr [11:0] $end
$upscope $end
$scope module rf $end
$var wire 1 7 clk $end
$var wire 2 q rd_addr_a [1:0] $end
$var wire 2 r rd_addr_b [1:0] $end
$var wire 1 _ we $end
$var wire 2 s wr_addr [1:0] $end
$var wire 8 t wr_data [7:0] $end
$var wire 8 u rd_data_b [7:0] $end
$var wire 8 v rd_data_a [7:0] $end
$scope module sr0 $end
$var wire 1 7 clk $end
$var wire 2 w rd_addr_a [1:0] $end
$var wire 2 x rd_addr_b [1:0] $end
$var wire 1 _ we $end
$var wire 2 y wr_addr [1:0] $end
$var wire 8 z wr_data [7:0] $end
$var reg 8 { rd_data_a [7:0] $end
$var reg 8 | rd_data_b [7:0] $end
$scope begin $ivl_for_loop0 $end
$var integer 32 } i [31:0] $end
$upscope $end
$upscope $end
$upscope $end
$upscope $end
$enddefinitions $end
#0
$dumpvars
b11 }
bx |
bx {
bx z
bx y
b1 x
b1 w
bx v
bx u
bx t
bx s
b1 r
b1 q
b111000001001 p
b0 o
b0 n
b0 m
b111 l
bx k
bx j
bx i
bx h
bx g
bx f
bx e
bx d
bx c
b0 b
bx a
bx `
0_
bx00000000 ^
0]
b0 \
bx [
bx Z
b0 Y
1X
0W
0V
b111000001001 U
bx T
bx S
b0 R
bx Q
0P
bx O
0N
b0 M
0L
bx K
bx J
0I
bx H
bx G
bx F
bx E
bx D
bx C
bx B
bx A
bx @
bx ?
bx >
bx =
bx <
bx ;
bx :
bx 9
08
17
z6
05
z4
bx 3
bx 2
bx 1
bx 0
bx /
bx .
bx -
bx ,
bx +
bx *
b0 )
bx (
bx '
0&
bx %
0$
1#
0"
0!
$end
#5000
07
#10000
b1001 +
b1001 =
b1001 i
b1001 '
b1001 d
b0 H
b1001 %
b1001 *
b1001 [
b1001 a
b0 `
b0 s
b0 y
b0 ^
b0 (
b0 .
b0 <
b0 T
b0 h
b0 v
b0 {
b0 2
b0 ;
b0 S
b0 g
b0 u
b0 |
17
#15000
07
#20000
1N
17
#25000
07
#30000
17
#35000
07
#40000
17
#45000
07
#50000
17
#55000
07
#60000
17
#65000
07
#70000
17
#75000
07
#80000
17
#85000
07
#90000
17
#95000
07
#100000
17
#105000
07
#110000
17
#115000
07
#120000
1L
1$
1!
1"
b10001000 M
17
#125000
07
#130000
0$
0"
1P
0X
1W
1V
0!
b110 l
b0 r
b0 x
b0 q
b0 w
0#
b110000000000 U
b110000000000 p
b10001000 ^
1]
b1 Y
b1 n
b1 o
17
#135000
07
#140000
0L
0P
1X
0W
0V
b111 l
b1 r
b1 x
b1 q
b1 w
1#
b10001000 H
b10001000 J
b10001000 Q
b10001000 t
b10001000 z
b0 +
b0 =
b0 i
b0 '
b0 d
b111000001001 U
b111000001001 p
0]
b1000100010001000 ^
1_
1&
1I
b0 %
b0 *
b0 [
b0 a
b10 Y
b10 n
b10 o
17
#145000
07
#150000
b1001 +
b1001 =
b1001 i
b1001 '
b1001 d
bx J
bx Q
bx t
bx z
0&
0I
b1001 %
b1001 *
b1001 [
b1001 a
0_
17
#155000
07
#160000
17
#165000
07
#170000
17
#175000
07
#180000
17
#185000
07
#190000
1L
1$
1!
1"
b11101 M
17
#195000
07
#200000
0$
0"
1P
0X
1W
1V
0!
b110 l
b0 r
b0 x
b0 q
b0 w
0#
b110001000000 U
b110001000000 p
1]
b1000100000011101 ^
b11 Y
b11 n
b11 o
17
#205000
07
#210000
b1 R
b1 m
0P
0W
0V
b11 l
b11101 J
b11101 Q
b11101 t
b11101 z
b0 +
b0 =
b0 i
b10001000 '
b10001000 d
b11101 H
b11001100000 U
b11001100000 p
1&
1I
b1000000 %
b1000000 *
b1000000 [
b1000000 a
b1 `
b1 s
b1 y
1_
b1110100011101 ^
0]
b10001000 (
b10001000 .
b10001000 <
b10001000 T
b10001000 h
b10001000 v
b10001000 {
b10001000 2
b10001000 ;
b10001000 S
b10001000 g
b10001000 u
b10001000 |
b100 Y
b100 n
b100 o
17
#215000
07
#220000
b10 R
b10 m
b100 l
15
b1100000 +
b1100000 =
b1100000 i
b1100000 '
b1100000 d
bx J
bx Q
bx t
bx z
b100001000000 U
b100001000000 p
0_
b1 \
b1 b
0&
0I
b1100000 %
b1100000 *
b1100000 [
b1100000 a
b101 Y
b101 n
b101 o
17
#225000
07
#230000
b100 R
b100 m
b10100110 -
b10100110 :
b10100110 B
b10100110 f
b101 l
b10 q
b10 w
05
18
b1000000 +
b1000000 =
b1000000 i
b1000000 '
b1000000 d
b1101001100000000 /
b101000010100 U
b101000010100 p
b10 \
b10 b
b1000000 %
b1000000 *
b1000000 [
b1000000 a
b1100000 ,
b1100000 >
b110 Y
b110 n
b110 o
17
#235000
07
#240000
b11000100 @
b11000100 D
b11000100 j
b111000100 C
b0 R
b0 m
1P
b0 -
b0 :
b0 B
b0 f
b11000100 1
b11000100 9
b11000100 A
b11000100 e
b1 l
b1 r
b1 x
b0 q
b0 w
b0 /
b1110001000000000 3
08
b10100 +
b10100 =
b10100 i
b10100 '
b10100 d
b1010000001 U
b1010000001 p
b0 (
b0 .
b0 <
b0 T
b0 h
b0 v
b0 {
b1000000 0
b1000000 ?
b0 `
b0 s
b0 y
b100 \
b100 b
b10100 %
b10100 *
b10100 [
b10100 a
b111 Y
b111 n
b111 o
17
#245000
07
#250000
b10110100 @
b10110100 D
b10110100 j
b11001000 J
b11001000 Q
b11001000 t
b11001000 z
b110110100 C
b1 R
b1 m
0P
b11001000 O
b11001000 F
b11001000 K
b11001000 Z
b11001000 c
b10100110 -
b10100110 :
b10100110 B
b10100110 f
b1110 1
b1110 9
b1110 A
b1110 e
b11 l
b0 r
b0 x
b10000001 +
b10000001 =
b10000001 i
b10000001 '
b10000001 d
b111001000 G
b1101001100000000 /
b11101000000 3
b11011000000 U
b11011000000 p
b0 \
b0 b
b10000001 %
b10000001 *
b10000001 [
b10000001 a
b10 `
b10 s
b10 y
1_
b10100 E
b10100 k
b10001000 (
b10001000 .
b10001000 <
b10001000 T
b10001000 h
b10001000 v
b10001000 {
b11101 2
b11101 ;
b11101 S
b11101 g
b11101 u
b11101 |
b1000 Y
b1000 n
b1000 o
17
#255000
07
#260000
b1111110 J
b1111110 Q
b1111110 t
b1111110 z
b1111110 O
b1111110 F
b1111110 K
b1111110 Z
b1111110 c
b1111110 G
b1101010 @
b1101010 D
b1101010 j
b101101010 C
b10 R
b10 m
b11000100 1
b11000100 9
b11000100 A
b11000100 e
b100 l
b1110001000000000 3
15
b11000000 +
b11000000 =
b11000000 i
b11000000 '
b11000000 d
b100001100000 U
b100001100000 p
b10001000 2
b10001000 ;
b10001000 S
b10001000 g
b10001000 u
b10001000 |
b11 `
b11 s
b11 y
0_
b1 \
b1 b
b11000000 %
b11000000 *
b11000000 [
b11000000 a
b1001 Y
b1001 n
b1001 o
17
#265000
07
#270000
b10100 J
b10100 Q
b10100 t
b10100 z
b10100 O
b10100 F
b10100 K
b10100 Z
b10100 c
b10100 G
b0 @
b0 D
b0 j
b0 C
b100 R
b100 m
b111100 -
b111100 :
b111100 B
b111100 f
b101 l
b1 q
b1 w
1#
05
18
b1100000 +
b1100000 =
b1100000 i
b1100000 '
b1100000 d
b1111000000000 /
b101011101100 U
b101011101100 p
b10 \
b10 b
b1100000 %
b1100000 *
b1100000 [
b1100000 a
b1 `
b1 s
b1 y
b11000000 ,
b11000000 >
b1010 Y
b1010 n
b1010 o
17
#275000
07
#280000
b10101011 J
b10101011 Q
b10101011 t
b10101011 z
b10101011 O
b10101011 F
b10101011 K
b10101011 Z
b10101011 c
b110101011 G
b10010111 @
b10010111 D
b10010111 j
b110010111 C
b0 R
b0 m
1P
b11110001 -
b11110001 :
b11110001 B
b11110001 f
b10100110 1
b10100110 9
b10100110 A
b10100110 e
b1 l
b1 r
b1 x
b0 q
b0 w
0#
b1111100011000000 /
b1101001100000000 3
08
b11101100 +
b11101100 =
b11101100 i
b11101100 '
b11101100 d
b1001000001 U
b1001000001 p
b11101 (
b11101 .
b11101 <
b11101 T
b11101 h
b11101 v
b11101 {
b1100000 0
b1100000 ?
b11 `
b11 s
b11 y
b100 \
b100 b
b11101100 %
b11101100 *
b11101100 [
b11101100 a
b1011 Y
b1011 n
b1011 o
17
#285000
07
#290000
b1010001 @
b1010001 D
b1010001 j
b111101 J
b111101 Q
b111101 t
b111101 z
b1010001 C
b111 R
b111 m
1W
b111101 O
b111101 F
b111101 K
b111101 Z
b111101 c
b111100 -
b111100 :
b111100 B
b111100 f
b10101 1
b10101 9
b10101 A
b10101 e
b0 l
b0 r
b0 x
b10 q
b10 w
b1000001 +
b1000001 =
b1000001 i
b1000001 '
b1000001 d
b111101 G
b1111000000000 /
b101011100000 3
b10000 U
b10000 p
b0 \
b0 b
b1000001 %
b1000001 *
b1000001 [
b1000001 a
b1 `
b1 s
b1 y
1_
b11101100 E
b11101100 k
b10001000 (
b10001000 .
b10001000 <
b10001000 T
b10001000 h
b10001000 v
b10001000 {
b11101 2
b11101 ;
b11101 S
b11101 g
b11101 u
b11101 |
b1100 Y
b1100 n
b1100 o
17
#295000
07
#300000
b10101110 J
b10101110 Q
b10101110 t
b10101110 z
b10101110 O
b10101110 F
b10101110 K
b10101110 Z
b10101110 c
b110101110 G
0L
b11000010 @
b11000010 D
b11000010 j
b111000010 C
b0 R
b0 m
0P
1X
0W
b11100 -
b11100 :
b11100 B
b11100 f
b10100110 1
b10100110 9
b10100110 A
b10100110 e
b111 l
b1 r
b1 x
b0 q
b0 w
b111000000000 /
b1101001100000000 3
15
18
b0 +
b0 =
b0 i
b11001000 '
b11001000 d
b111000000001 U
b111000000001 p
b11001000 (
b11001000 .
b11001000 <
b11001000 T
b11001000 h
b11001000 v
b11001000 {
b10001000 2
b10001000 ;
b10001000 S
b10001000 g
b10001000 u
b10001000 |
b0 `
b0 s
b0 y
b111 \
b111 b
1&
b10000 %
b10000 *
b10000 [
b10000 a
b1101 Y
b1101 n
b1101 o
17
#305000
07
#310000
b0 @
b0 D
b0 j
b11001000 J
b11001000 Q
b11001000 t
b11001000 z
b0 C
b11001000 O
b11001000 F
b11001000 K
b11001000 Z
b11001000 c
b0 -
b0 :
b0 B
b0 f
b0 1
b0 9
b0 A
b0 e
05
08
b1 +
b1 =
b1 i
b111001000 G
b1 '
b1 d
b0 /
b0 3
b0 \
b0 b
0&
b1 %
b1 *
b1 [
b1 a
0_
b11001000 E
b11001000 k
b0 0
b0 ?
b0 ,
b0 >
b10001000 (
b10001000 .
b10001000 <
b10001000 T
b10001000 h
b10001000 v
b10001000 {
b111101 2
b111101 ;
b111101 S
b111101 g
b111101 u
b111101 |
17
#315000
07
#320000
1L
1!
1$
1"
b10101110 (
b10101110 .
b10101110 <
b10101110 T
b10101110 h
b10101110 v
b10101110 {
17
#325000
07
#330000
b111 R
b111 m
1P
0X
1W
0$
0!
b0 l
b0 r
b0 x
b1 q
b1 w
1#
b1000 U
b1000 p
1]
b1110 Y
b1110 n
b1110 o
17
#335000
07
#340000
0L
b0 R
b0 m
0P
1X
0W
1$
b111 l
b0 q
b0 w
0#
15
18
b0 +
b0 =
b0 i
b111101 '
b111101 d
b111000000000 U
b111000000000 p
b111101 (
b111101 .
b111101 <
b111101 T
b111101 h
b111101 v
b111101 {
b10101110 2
b10101110 ;
b10101110 S
b10101110 g
b10101110 u
b10101110 |
1_
b111 \
b111 b
1&
b1000 %
b1000 *
b1000 [
b1000 a
b1111 Y
b1111 n
b1111 o
17
#345000
07
#350000
b111101 J
b111101 Q
b111101 t
b111101 z
b111101 O
b111101 F
b111101 K
b111101 Z
b111101 c
05
08
b111101 G
b0 '
b0 d
b0 \
b0 b
0&
b0 %
b0 *
b0 [
b0 a
0_
b111101 E
b111101 k
b10101110 (
b10101110 .
b10101110 <
b10101110 T
b10101110 h
b10101110 v
b10101110 {
17
#355000
07
#360000
1L
0$
0"
b11001000 (
b11001000 .
b11001000 <
b11001000 T
b11001000 h
b11001000 v
b11001000 {
b11001000 2
b11001000 ;
b11001000 S
b11001000 g
b11001000 u
b11001000 |
17
#365000
07
#370000
0L
b1 r
b1 x
b1 q
b1 w
1#
b111000001001 U
b111000001001 p
0]
b0 Y
b0 n
b0 o
17
#375000
07
#380000
b1001 +
b1001 =
b1001 i
b1001 '
b1001 d
b111101 (
b111101 .
b111101 <
b111101 T
b111101 h
b111101 v
b111101 {
b111101 2
b111101 ;
b111101 S
b111101 g
b111101 u
b111101 |
b1001 %
b1001 *
b1001 [
b1001 a
17
#385000
07
#390000
17
#395000
07
#400000
17
#405000
07
#410000
1L
1$
1!
1"
b100100 M
17
#415000
07
#420000
0$
0"
1P
0X
1W
1V
0!
b110 l
b0 r
b0 x
b0 q
b0 w
0#
b110000000000 U
b110000000000 p
1]
b1110100100100 ^
b1 Y
b1 n
b1 o
17
#425000
07
