rtl/v7/sfixed_adder.sv
import datatypes::max;

module sfixed_adder #(
    parameter A_LEFT    = 3, 
    parameter A_RIGHT   = 4, 
    parameter B_LEFT    = 3, 
    parameter B_RIGHT   = 4,
    parameter OUT_LEFT  = 4, 
    parameter OUT_RIGHT = 4
) (   
    input  logic signed [(A_LEFT+A_RIGHT+1)-1:0]     a,
    input  logic signed [(B_LEFT+B_RIGHT+1)-1:0]     b,
    output logic signed [(OUT_LEFT+OUT_RIGHT+1)-1:0] out
);

`ifdef COCOTB_SIM
initial begin
    $dumpfile ("sfixed_adder.vcd");
    $dumpvars (0, sfixed_adder);
    #1;
end
`endif

localparam OUTPUT_SIZE = (max(A_LEFT,B_LEFT)+1)+max(A_RIGHT,B_RIGHT)+1; 

logic signed [OUTPUT_SIZE-1:0] add_out;

always_comb
    add_out = a + b;

assign out = add_out[max(A_RIGHT,B_RIGHT)+OUT_LEFT:max(A_RIGHT,B_RIGHT)-OUT_RIGHT];

endmodule

rtl/v6/mux_21.sv
module mux_21 #(
    parameter BIT_WIDTH = 8
) (   
    input  logic s, 
    input  logic [BIT_WIDTH-1:0] a, b,
    output logic [BIT_WIDTH-1:0] out
);
    `ifdef COCOTB_SIM
    initial begin
        $dumpfile ("mux_21.vcd");
        $dumpvars (0, mux_21);
        #1;
    end
    `endif 
    assign out = s ? a : b;
endmodule

rtl/v7/sfixed_mult.sv
module sfixed_mult #(
    parameter A_LEFT    = 3, 
    parameter A_RIGHT   = 4,
    parameter B_LEFT    = 3, 
    parameter B_RIGHT   = 4,
    parameter OUT_LEFT  = 7, 
    parameter OUT_RIGHT = 8
) (
    input  logic signed [(A_LEFT+A_RIGHT+1)-1:0]     a,
    input  logic signed [(B_LEFT+B_RIGHT+1)-1:0]     b,
    output logic signed [(OUT_LEFT+OUT_RIGHT+1)-1:0] out
);
`ifdef COCOTB_SIM
initial begin
    $dumpfile ("sfixed_mult.vcd");
    $dumpvars (0, sfixed_mult);
    #1;
end
`endif

localparam OUTPUT_SIZE = (A_LEFT+B_LEFT+1)+(A_RIGHT+B_RIGHT)+1; 
                                                                
logic signed [OUTPUT_SIZE-1:0] mult_out;

always_comb
    mult_out = a * b;

assign out = mult_out[(A_RIGHT+B_RIGHT)+OUT_LEFT:(A_RIGHT+B_RIGHT)-OUT_RIGHT];

endmodule

rtl/v8/ALU_mult_stage.sv
module ALU_mult_stage #(
    parameter BUS_WIDTH = 8
) (
    input  logic clk, f_clr,
    input  logic b_en, d_en,
    input  logic [BUS_WIDTH-1:0] data_a, data_b, imm,
    output logic [BUS_WIDTH-1:0] mult_a, mult_b
);
`ifdef COCOTB_SIM
initial begin
    $dumpfile ("ALU_mult_stage.vcd");
    $dumpvars (0, ALU_mult_stage);
    #1;
end
`endif

// input registers
logic [BUS_WIDTH-1:0] op_b_reg, op_d_reg;

always_ff @( posedge clk ) begin 
    if (b_en) begin
       if (f_clr)
          op_b_reg <= '0;
       else 
          op_b_reg <= imm;
    end   
end

always_ff @( posedge clk ) begin 
    if (d_en) begin
        if (f_clr)
          op_d_reg <= '0;
       else 
          op_d_reg <= imm;
    end
end

sfixed_mult #(
    7, 
    0,
    0, 
    7,
    7,
    0 
) m0 (
    .a  (data_a  ), // int
    .b  (op_b_reg), // tf
    .out(mult_a  )
);

sfixed_mult #(
    7, 
    0,
    0, 
    7,
    7,
    0 
) m1 (
    .a  (data_b  ), // int
    .b  (op_d_reg), // tf
    .out(mult_b  )
);

    
endmodule

rtl/v8/ALU_v2.sv
module ALU_v2 #(
    parameter BUS_WIDTH  = 8
) (
    input  logic                 clk, 
    input  logic [BUS_WIDTH-1:0] sw,
    input  logic [BUS_WIDTH-1:0] imm,
    input  logic [BUS_WIDTH-1:0] data_a,    
    input  logic [BUS_WIDTH-1:0] data_b,    
    input  logic [2:0]           reg_en,
    input  logic                 f_reg_e, f_load, f_clr,
    output logic [BUS_WIDTH-1:0] result 
);       

// setting up of add/subtract inputs
logic [BUS_WIDTH-1:0] op_e, e_add, coeff;
logic [BUS_WIDTH-1:0] op_e_reg;

mux_21 #(
    BUS_WIDTH
) op_e_mux (   
    .s  (f_load), 
    .a  (sw    ), 
    .b  (imm   ),
    .out(op_e  )
);

// input registers
always_ff @( posedge clk ) begin
    if (reg_en[2])
        op_e_reg <= op_e;
end

// the computational part
logic [BUS_WIDTH-1:0] mult_a, mult_b, add_a, add_b;

ALU_mult_stage #(
    BUS_WIDTH
) am1 (
    .clk   (clk       ),
    .f_clr (f_clr    ),
    .b_en  (reg_en[0]), 
    .d_en  (reg_en[1]),
    .data_a(data_a   ),
    .data_b(data_b   ),
    .imm   (imm      ),
    .mult_a(mult_a   ),
    .mult_b(mult_b   )
);

sfixed_adder #(
    7, 
    0, 
    7, 
    0,
    7, 
    0
) a0 ( 
    .a  (mult_a), // int
    .b  (mult_b), // int
    .out(add_a )
);

mux_21 #(
    BUS_WIDTH
) reg_e_mux (   
    .s  (f_reg_e ), 
    .a  (op_e_reg), 
    .b  (data_a  ),
    .out(add_b   )
);

sfixed_adder #(
    7, 
    0, 
    7, 
    0,
    7, 
    0
) a1 (  
    .a  (add_a ), // int
    .b  (add_b ), // int
    .out(result)
);

endmodule

include/opcodes.sv
//-----------------------------------------------------
// File Name : opcodes.sv
// Function : pMIPS instr opcode definitions
// Author: jf
//-----------------------------------------------------
//
`define NOP  6'b000000
`define ADD  6'b000001
`define SUB  6'b000010
`define ADDI 6'b000011
`define SUBI 6'b000100
`define BEQ  6'b000101
`define BNE  6'b000110
`define BGE  6'b000111
`define BLO  6'b001000

rtl/v8/instruction_decoder.sv
`include "opcodes.sv"

module instruction_decoder #(
    parameter OPCODE_WIDTH = 3
) (
    input  logic [OPCODE_WIDTH-1:0] opcode,                  
    output logic                    f_reg_e,            
    output logic                    f_wait,       
    output logic                    f_load,      
    output logic                    f_clr,      
    output logic                    wr_res,         
    output logic [2:0]              ALU_reg_en
);

always_comb 
begin
    case(opcode)    
        `MOV : begin
            f_load     = '0;
            f_reg_e    = '0; 
            f_wait     = '0;
            wr_res     = '1; 
            f_clr      = '1;
            ALU_reg_en = 3'b111; // B, D, E
        end
        `MAC : begin 
            f_load     = '0;
            f_reg_e    = '1;
            f_wait     = '0;
            wr_res     = '1; 
            f_clr      = '0;
            ALU_reg_en = 3'b000; // C, A
        end
        `WAIT: begin
            f_load     = '0;
            f_reg_e    = '0;
            f_wait     = '1;
            wr_res     = '0;
            f_clr      = '0;
            ALU_reg_en = 3'b000;
        end
        `SETB: begin
            f_load     = '0;
            f_reg_e    = '0;
            f_wait     = '0;
            wr_res     = '0;
            f_clr      = '0;
            ALU_reg_en = 3'b001; 
        end
        `SETD: begin
            f_load     = '0;
            f_reg_e    = '0;
            f_wait     = '0;
            wr_res     = '0;
            f_clr      = '0;
            ALU_reg_en = 3'b010;
        end
        `SETE: begin
            f_load     = '0;
            f_reg_e    = '0;
            f_wait     = '0;
            wr_res     = '0;
            f_clr      = '0;
            ALU_reg_en = 3'b100;
        end
        `LDSW: begin
            f_load     = '1;
            f_reg_e    = '1;
            f_wait     = '0;
            f_clr      = '1;
            wr_res     = '1;
            ALU_reg_en = 3'b111;
        end
        default : begin
            f_load     = '0;
            f_reg_e    = '0;
            f_wait     = '0;
            f_clr      = '0;
            wr_res     = '0;
            ALU_reg_en = '0;
        end
    endcase 
end 

endmodule

rtl/v3/register_file.sv
module register_file #(
    parameter BUS_WIDTH  = 8,
    parameter ADDR_WIDTH = 3
) (
	input  logic                  clk, 
	input  logic                  we,
 	input  logic [ADDR_WIDTH-1:0] wr_addr,
	input  logic [BUS_WIDTH-1:0]  wr_data,
 	input  logic [ADDR_WIDTH-1:0] rd_addr_a, rd_addr_b,
 	output logic [BUS_WIDTH-1:0]  rd_data_a, rd_data_b
);

localparam N = (1 << ADDR_WIDTH);

logic [BUS_WIDTH-1:0] gpr [N-1:0];

initial begin
	for (int i = 0; i < N; i = i + 1)
		gpr[i] = '0;
end

// syncrhonous RAM write
always_ff @ (posedge clk)
begin
	if (we) begin 
		gpr[wr_addr] <= wr_data;
	end
	rd_data_b <= gpr[rd_addr_b];
	rd_data_a <= gpr[rd_addr_a];
end	
	

endmodule

rtl/v6/program_memory.sv
module program_memory #(
    parameter ADDR_WIDTH  = 4,
    parameter INSTR_WIDTH = 12
) (
    input  logic [ADDR_WIDTH-1:0]  addr,
    output logic [INSTR_WIDTH-1:0] instr
); 

(* ramstyle = "mlab" *) logic [INSTR_WIDTH-1:0] prog_mem [(1<<ADDR_WIDTH)-1:0];

initial
begin
`ifdef COCOTB_SIM
    $readmemh("/home/jonahfoley/ELEC6234/a_fine_CPU/programs/prog_3.hex", prog_mem);
`else
    $readmemh("../../programs/prog_3.hex", prog_mem);
`endif
end
   
always_comb
    instr = prog_mem[addr]; 
  
endmodule

rtl/v3/program_counter.sv
module program_counter #(
    parameter ADDR_WIDTH = 3
) (
    input  logic                  clk, n_reset,
    input  logic                  en,
    output logic [ADDR_WIDTH-1:0] count
);
 
always_ff @(posedge clk, negedge n_reset) 
begin   
    if (~n_reset) 
        count <= '0;
    else begin
        if (count == (2<<ADDR_WIDTH)-1) 
            count <= '0;
        else begin
            if (en)
                count <= count + { {ADDR_WIDTH-1{1'b0}}, 1'b1 };
        end
    end
end


endmodule

rtl/v8/CPU.sv
module CPU #(
    parameter INSTR_WIDTH      = 24,
    parameter OPCODE_WIDTH     = 3,
    parameter INSTR_ADDR_WIDTH = 4, 
    parameter REG_ADDR_WIDTH   = 2, 
    parameter BUS_WIDTH        = 8
) (
    input  logic                 clk,  
    input  logic                 n_reset,
    input  logic [BUS_WIDTH-1:0] in_port,
    input  logic                 ready_in,
    output logic [BUS_WIDTH-1:0] out_port
);       

//the macro to dump signals   
`ifdef COCOTB_SIM
initial begin
    $dumpfile ("CPU.vcd");
    $dumpvars (0, CPU);
    #1;
end
`endif

// input switch handshaking
logic ready_in_p, pattern_match;
always_ff @(posedge clk)
    ready_in_p <= ready_in;

logic [1:0][BUS_WIDTH-1:0] sw;
always_ff @(posedge clk)
    sw <= {sw[0], in_port};

assign pattern_match = (~ready_in_p & ready_in);

// -- instr counter
logic [INSTR_ADDR_WIDTH-1:0] PC_count;
logic PC_en, PC_comparator;

mux_21 #(
    1
) PC_en_mux (
    .s  (instr[3]     ), // differentiate between instr[5:3] == 001 (pattern) / 000 (rdy)
    .a  (pattern_match), // 001 -> pattern
    .b  (ready_in     ), // 000 -> ready in 
    .out(PC_comparator)
);

assign PC_en = ~(f_wait & (PC_comparator ^ instr[0]));

program_counter #(
   INSTR_ADDR_WIDTH
) pc (
   .clk    (clk     ),
   .n_reset(n_reset ),
   .en     (PC_en   ),
   .count  (PC_count)
);

// -- program ROM
logic [INSTR_WIDTH-1:0] instr;

program_memory #(
    INSTR_ADDR_WIDTH,
    INSTR_WIDTH
) pm (
    .addr (PC_count),
    .instr(instr   )
);

// -- reg file
logic wr_res;
logic we;
logic [REG_ADDR_WIDTH-1:0] wr_addr;
logic [BUS_WIDTH-1:0] rd_data_a, rd_data_b;

always_ff @(posedge clk) 
begin
    we      <= wr_res;
    wr_addr <= instr[7:6];
end

register_file #(
    BUS_WIDTH,
    3
) rf (
	.clk      (clk       ),  
    .we       (we        ),
 	.wr_addr  (wr_addr   ),
	.wr_data  (ALU_result),
 	.rd_addr_a(instr[4:3]), 
    .rd_addr_b(instr[1:0]),
 	.rd_data_a(rd_data_a ), 
    .rd_data_b(rd_data_b )
);

// -- decoder
logic f_reg_e, f_load, f_wait;
logic [2:0] reg_en; 

instruction_decoder #(
    OPCODE_WIDTH
) id (
    .opcode    (instr[11:9]),                  
    .f_reg_e   (f_reg_e    ), 
    .f_wait    (f_wait     ),            
    .f_load    (f_load     ),            
    .f_clr     (f_clr      ),            
    .wr_res    (wr_res     ),         
    .ALU_reg_en(reg_en     )
);

// -- ALU
logic [BUS_WIDTH-1:0] ALU_result;
logic ALU_reg_e;

always_ff @(posedge clk)
    ALU_reg_e <= f_reg_e;

ALU_v2 #(
    BUS_WIDTH
) alu (
    .clk    (clk       ), 
    .sw     (sw        ), 
    .imm    (instr[7:0]),
    .data_a (rd_data_a ),
    .data_b (rd_data_b ),   
    .reg_en (reg_en    ),
    .f_reg_e(ALU_reg_e ),
    .f_load (f_load    ),
    .f_clr  (f_clr     ),
    .result (ALU_result)
);    

assign out_port = ALU_result;

endmodule

simulation/v8/CPU/mux_21.vcd
$date
	Mon Apr 24 03:57:59 2023
$end
$version
	Icarus Verilog
$end
$timescale
	1ps
$end
$scope module CPU $end
$scope module PC_en_mux $end
$var wire 1 ! a $end
$var wire 1 " b $end
$var wire 1 # s $end
$var wire 1 $ out $end
$upscope $end
$upscope $end
$scope module CPU $end
$scope module alu $end
$scope module op_e_mux $end
$var wire 8 % a [7:0] $end
$var wire 8 & b [7:0] $end
$var wire 1 ' s $end
$var wire 8 ( out [7:0] $end
$upscope $end
$upscope $end
$upscope $end
$scope module CPU $end
$scope module alu $end
$scope module am1 $end
$scope module m0 $end
$var wire 8 ) b [7:0] $end
$var wire 8 * out [7:0] $end
$var wire 8 + a [7:0] $end
$var reg 16 , mult_out [15:0] $end
$upscope $end
$upscope $end
$upscope $end
$upscope $end
$scope module CPU $end
$scope module alu $end
$scope module am1 $end
$scope module m1 $end
$var wire 8 - b [7:0] $end
$var wire 8 . out [7:0] $end
$var wire 8 / a [7:0] $end
$var reg 16 0 mult_out [15:0] $end
$upscope $end
$upscope $end
$upscope $end
$upscope $end
$scope module CPU $end
$scope module alu $end
$scope module am1 $end
$var wire 1 1 b_en $end
$var wire 1 2 clk $end
$var wire 1 3 d_en $end
$var wire 8 4 imm [7:0] $end
$var wire 8 5 mult_b [7:0] $end
$var wire 8 6 mult_a [7:0] $end
$var wire 1 7 f_clr $end
$var wire 8 8 data_b [7:0] $end
$var wire 8 9 data_a [7:0] $end
$var reg 8 : op_b_reg [7:0] $end
$var reg 8 ; op_d_reg [7:0] $end
$scope module m0 $end
$upscope $end
$scope module m1 $end
$upscope $end
$upscope $end
$upscope $end
$upscope $end
$scope module CPU $end
$scope module alu $end
$scope module a0 $end
$var wire 8 < out [7:0] $end
$var wire 8 = b [7:0] $end
$var wire 8 > a [7:0] $end
$var reg 9 ? add_out [8:0] $end
$upscope $end
$upscope $end
$upscope $end
$scope module CPU $end
$scope module alu $end
$scope module reg_e_mux $end
$var wire 8 @ a [7:0] $end
$var wire 1 A s $end
$var wire 8 B out [7:0] $end
$var wire 8 C b [7:0] $end
$upscope $end
$upscope $end
$upscope $end
$scope module CPU $end
$scope module alu $end
$scope module a1 $end
$var wire 8 D a [7:0] $end
$var wire 8 E out [7:0] $end
$var wire 8 F b [7:0] $end
$var reg 9 G add_out [8:0] $end
$upscope $end
$upscope $end
$upscope $end
$scope module CPU $end
$var wire 1 H PC_en $end
$var wire 1 2 clk $end
$var wire 8 I in_port [7:0] $end
$var wire 1 J n_reset $end
$var wire 8 K out_port [7:0] $end
$var wire 1 ! pattern_match $end
$var wire 1 " ready_in $end
$var wire 1 L wr_res $end
$var wire 3 M reg_en [2:0] $end
$var wire 8 N rd_data_b [7:0] $end
$var wire 8 O rd_data_a [7:0] $end
$var wire 12 P instr [11:0] $end
$var wire 1 Q f_wait $end
$var wire 1 R f_reg_e $end
$var wire 1 ' f_load $end
$var wire 1 7 f_clr $end
$var wire 4 S PC_count [3:0] $end
$var wire 1 $ PC_comparator $end
$var wire 8 T ALU_result [7:0] $end
$var reg 1 A ALU_reg_e $end
$var reg 1 U ready_in_p $end
$var reg 16 V sw [15:0] $end
$var reg 1 W we $end
$var reg 2 X wr_addr [1:0] $end
$scope module PC_en_mux $end
$upscope $end
$scope module alu $end
$var wire 1 2 clk $end
$var wire 1 A f_reg_e $end
$var wire 8 Y imm [7:0] $end
$var wire 8 Z sw [7:0] $end
$var wire 8 [ result [7:0] $end
$var wire 3 \ reg_en [2:0] $end
$var wire 8 ] op_e [7:0] $end
$var wire 8 ^ mult_b [7:0] $end
$var wire 8 _ mult_a [7:0] $end
$var wire 1 ' f_load $end
$var wire 1 7 f_clr $end
$var wire 8 ` data_b [7:0] $end
$var wire 8 a data_a [7:0] $end
$var wire 8 b add_b [7:0] $end
$var wire 8 c add_a [7:0] $end
$var reg 8 d op_e_reg [7:0] $end
$scope module a0 $end
$upscope $end
$scope module a1 $end
$upscope $end
$scope module am1 $end
$scope module m0 $end
$upscope $end
$scope module m1 $end
$upscope $end
$upscope $end
$scope module op_e_mux $end
$upscope $end
$scope module reg_e_mux $end
$upscope $end
$upscope $end
$scope module id $end
$var wire 3 e opcode [2:0] $end
$var reg 3 f ALU_reg_en [2:0] $end
$var reg 1 7 f_clr $end
$var reg 1 ' f_load $end
$var reg 1 R f_reg_e $end
$var reg 1 Q f_wait $end
$var reg 1 L wr_res $end
$upscope $end
$scope module pc $end
$var wire 1 2 clk $end
$var wire 1 H en $end
$var wire 1 J n_reset $end
$var reg 4 g count [3:0] $end
$upscope $end
$scope module pm $end
$var wire 4 h addr [3:0] $end
$var reg 12 i instr [11:0] $end
$upscope $end
$scope module rf $end
$var wire 1 2 clk $end
$var wire 2 j rd_addr_a [1:0] $end
$var wire 2 k rd_addr_b [1:0] $end
$var wire 1 W we $end
$var wire 2 l wr_addr [1:0] $end
$var wire 8 m wr_data [7:0] $end
$var wire 8 n rd_data_b [7:0] $end
$var wire 8 o rd_data_a [7:0] $end
$scope module sr0 $end
$var wire 1 2 clk $end
$var wire 2 p rd_addr_a [1:0] $end
$var wire 2 q rd_addr_b [1:0] $end
$var wire 1 W we $end
$var wire 2 r wr_addr [1:0] $end
$var wire 8 s wr_data [7:0] $end
$var reg 8 t rd_data_a [7:0] $end
$var reg 8 u rd_data_b [7:0] $end
$scope begin $ivl_for_loop0 $end
$var integer 32 v i [31:0] $end
$upscope $end
$upscope $end
$upscope $end
$upscope $end
$enddefinitions $end
#0
$dumpvars
b11 v
bx u
bx t
bx s
bx r
b1 q
b1 p
bx o
bx n
bx m
bx l
b1 k
b1 j
b111000001001 i
b0 h
b0 g
b0 f
b111 e
bx d
bx c
bx b
bx a
bx `
bx _
bx ^
b1001 ]
b0 \
bx [
b0 Z
b1001 Y
bx X
0W
bx00000000 V
0U
bx T
b0 S
0R
1Q
b111000001001 P
bx O
bx N
b0 M
0L
bx K
0J
b0 I
0H
bx G
bx F
bx E
bx D
bx C
bx B
0A
bx @
bx ?
bx >
bx =
bx <
bx ;
bx :
bx 9
bx 8
07
bx 6
bx 5
b1001 4
03
12
01
bx 0
bx /
bx .
bx -
bx ,
bx +
bx *
bx )
b1001 (
0'
b1001 &
b0 %
0$
1#
0"
0!
$end
#5000
02
#10000
b0 B
b0 F
b0 b
b0 X
b0 l
b0 r
b0 V
b0 +
b0 9
b0 C
b0 O
b0 a
b0 o
b0 t
b0 /
b0 8
b0 N
b0 `
b0 n
b0 u
12
#15000
02
#20000
1J
12
#25000
02
#30000
12
#35000
02
#40000
12
#45000
02
#50000
12
#55000
02
#60000
12
#65000
02
#70000
12
#75000
02
#80000
12
#85000
02
#90000
12
#95000
02
#100000
12
#105000
02
#110000
12
#115000
02
#120000
1H
1$
1!
1"
b10010000 I
12
#125000
02
#130000
0$
0"
13
11
b10010000 (
b10010000 ]
b111 M
b111 \
b111 f
1L
17
0Q
1R
1'
0!
b0 &
b0 4
b0 Y
b110 e
b0 k
b0 q
b0 j
b0 p
0#
b10010000 %
b10010000 Z
b110000000000 P
b110000000000 i
b10010000 V
1U
b1 S
b1 g
b1 h
12
#135000
02
#140000
b10010000 K
b10010000 E
b10010000 T
b10010000 [
b10010000 m
b10010000 s
b110010000 G
0H
b0 <
b0 D
b0 c
03
01
b1001 (
b1001 ]
b0 ?
b0 M
b0 \
b0 f
07
0L
1Q
0R
0'
b0 *
b0 6
b0 >
b0 _
b0 .
b0 5
b0 =
b0 ^
b1001 &
b1001 4
b1001 Y
b111 e
b1 k
b1 q
b1 j
b1 p
1#
b0 ,
b0 0
b10010000 B
b10010000 F
b10010000 b
b111000001001 P
b111000001001 i
b0 )
b0 :
b0 -
b0 ;
b10010000 @
b10010000 d
0U
b1001000010010000 V
1W
1A
b10 S
b10 g
b10 h
12
#145000
02
#150000
b0 K
b0 E
b0 T
b0 [
b0 m
b0 s
b0 G
b0 B
b0 F
b0 b
0A
0W
12
#155000
02
#160000
12
#165000
02
#170000
12
#175000
02
#180000
12
#185000
02
#190000
1H
1$
1!
1"
b1101111 I
12
#195000
02
#200000
0$
0"
13
11
b1101111 (
b1101111 ]
b111 M
b111 \
b111 f
1L
17
0Q
1R
1'
0!
b1000000 &
b1000000 4
b1000000 Y
b110 e
b0 k
b0 q
b0 j
b0 p
0#
b1101111 %
b1101111 Z
b110001000000 P
b110001000000 i
1U
b1001000001101111 V
b11 S
b11 g
b11 h
12
#205000
02
#210000
03
b1100000 (
b1100000 ]
b1101111 K
b1101111 E
b1101111 T
b1101111 [
b1101111 m
b1101111 s
b1 M
b1 \
b1 f
07
0L
0R
0'
b1101111 G
b1100000 &
b1100000 4
b1100000 Y
b11 e
b1101111 B
b1101111 F
b1101111 b
b11001100000 P
b11001100000 i
1A
b1 X
b1 l
b1 r
1W
b110111101101111 V
0U
b1101111 @
b1101111 d
b10010000 +
b10010000 9
b10010000 C
b10010000 O
b10010000 a
b10010000 o
b10010000 t
b10010000 /
b10010000 8
b10010000 N
b10010000 `
b10010000 n
b10010000 u
b100 S
b100 g
b100 h
12
#215000
02
#220000
b10101100 <
b10101100 D
b10101100 c
13
01
b110101100 ?
b111100 K
b111100 E
b111100 T
b111100 [
b111100 m
b111100 s
b1000000 (
b1000000 ]
b10 M
b10 \
b10 f
b10101100 *
b10101100 6
b10101100 >
b10101100 _
b100111100 G
b1000000 &
b1000000 4
b1000000 Y
b100 e
b1101011000000000 ,
b10010000 B
b10010000 F
b10010000 b
b100001000000 P
b100001000000 i
b1100000 )
b1100000 :
0W
0A
b101 S
b101 g
b101 h
12
#225000
02
#230000
b100 K
b100 E
b100 T
b100 [
b100 m
b100 s
b100 G
b1110100 <
b1110100 D
b1110100 c
03
b101110100 ?
b10100 (
b10100 ]
b100 M
b100 \
b100 f
b11001000 .
b11001000 5
b11001000 =
b11001000 ^
b10100 &
b10100 4
b10100 Y
b101 e
b10 j
b10 p
b1110010000000000 0
b101000010100 P
b101000010100 i
b1000000 -
b1000000 ;
b110 S
b110 g
b110 h
12
#235000
02
#240000
b11001000 <
b11001000 D
b11001000 c
b11001000 K
b11001000 E
b11001000 T
b11001000 [
b11001000 m
b11001000 s
b10000001 (
b10000001 ]
b0 M
b0 \
b0 f
1L
1R
b111001000 ?
b111001000 G
b0 *
b0 6
b0 >
b0 _
b10000001 &
b10000001 4
b10000001 Y
b1 e
b1 k
b1 q
b0 j
b0 p
b0 B
b0 F
b0 b
b0 ,
b1010000001 P
b1010000001 i
b0 +
b0 9
b0 C
b0 O
b0 a
b0 o
b0 t
b10100 @
b10100 d
b0 X
b0 l
b0 r
b111 S
b111 g
b111 h
12
#245000
02
#250000
11
b11100011 <
b11100011 D
b11100011 c
b11110111 K
b11110111 E
b11110111 T
b11110111 [
b11110111 m
b11110111 s
b11000000 (
b11000000 ]
b1 M
b1 \
b1 f
0L
0R
b111100011 ?
b111110111 G
b10101100 *
b10101100 6
b10101100 >
b10101100 _
b110111 .
b110111 5
b110111 =
b110111 ^
b11000000 &
b11000000 4
b11000000 Y
b11 e
b0 k
b0 q
b10100 B
b10100 F
b10100 b
b1101011000000000 ,
b1101111000000 0
b11011000000 P
b11011000000 i
1A
b10 X
b10 l
b10 r
1W
b10010000 +
b10010000 9
b10010000 C
b10010000 O
b10010000 a
b10010000 o
b10010000 t
b1101111 /
b1101111 8
b1101111 N
b1101111 `
b1101111 n
b1101111 u
b1000 S
b1000 g
b1000 h
12
#255000
02
#260000
b0 <
b0 D
b0 c
13
01
b0 ?
b10010000 K
b10010000 E
b10010000 T
b10010000 [
b10010000 m
b10010000 s
b1100000 (
b1100000 ]
b10 M
b10 \
b10 f
b11001000 .
b11001000 5
b11001000 =
b11001000 ^
b111000 *
b111000 6
b111000 >
b111000 _
b110010000 G
b1100000 &
b1100000 4
b1100000 Y
b100 e
b1110010000000000 0
b1110000000000 ,
b10010000 B
b10010000 F
b10010000 b
b100001100000 P
b100001100000 i
b10010000 /
b10010000 8
b10010000 N
b10010000 `
b10010000 n
b10010000 u
b11000000 )
b11000000 :
b11 X
b11 l
b11 r
0W
0A
b1001 S
b1001 g
b1001 h
12
#265000
02
#270000
b1110100 K
b1110100 E
b1110100 T
b1110100 [
b1110100 m
b1110100 s
b101110100 G
b11100100 <
b11100100 D
b11100100 c
03
b111100100 ?
b11101100 (
b11101100 ]
b100 M
b100 \
b100 f
b10101100 .
b10101100 5
b10101100 =
b10101100 ^
b11101100 &
b11101100 4
b11101100 Y
b101 e
b1 j
b1 p
1#
b1101011000000000 0
b101011101100 P
b101011101100 i
b1 X
b1 l
b1 r
b1100000 -
b1100000 ;
b1010 S
b1010 g
b1010 h
12
#275000
02
#280000
b1110100 <
b1110100 D
b1110100 c
b11100011 K
b11100011 E
b11100011 T
b11100011 [
b11100011 m
b11100011 s
b1000001 (
b1000001 ]
b0 M
b0 \
b0 f
1L
1R
b101110100 ?
b11100011 G
b11001000 *
b11001000 6
b11001000 >
b11001000 _
b1000001 &
b1000001 4
b1000001 Y
b1 e
b1 k
b1 q
b0 j
b0 p
0#
b1101111 B
b1101111 F
b1101111 b
b1110010001000000 ,
b1001000001 P
b1001000001 i
b1101111 +
b1101111 9
b1101111 C
b1101111 O
b1101111 a
b1101111 o
b1101111 t
b11101100 @
b11101100 d
b11 X
b11 l
b11 r
b1011 S
b1011 g
b1011 h
12
#285000
02
#290000
13
11
b10001011 <
b10001011 D
b10001011 c
b1110111 K
b1110111 E
b1110111 T
b1110111 [
b1110111 m
b1110111 s
b10000 (
b10000 ]
b111 M
b111 \
b111 f
17
0R
b10001011 ?
b101110111 G
b111000 *
b111000 6
b111000 >
b111000 _
b1010011 .
b1010011 5
b1010011 =
b1010011 ^
b10000 &
b10000 4
b10000 Y
b0 e
b0 k
b0 q
b10 j
b10 p
b11101100 B
b11101100 F
b11101100 b
b1110000000000 ,
b10100110100000 0
b10000 P
b10000 i
1A
b1 X
b1 l
b1 r
1W
b10010000 +
b10010000 9
b10010000 C
b10010000 O
b10010000 a
b10010000 o
b10010000 t
b1101111 /
b1101111 8
b1101111 N
b1101111 `
b1101111 n
b1101111 u
b1100 S
b1100 g
b1100 h
12
#295000
02
#300000
0H
b0 <
b0 D
b0 c
03
01
b0 ?
b11110111 K
b11110111 E
b11110111 T
b11110111 [
b11110111 m
b11110111 s
b1 (
b1 ]
b0 M
b0 \
b0 f
07
0L
1Q
b0 *
b0 6
b0 >
b0 _
b0 .
b0 5
b0 =
b0 ^
b111110111 G
b1 &
b1 4
b1 Y
b111 e
b1 k
b1 q
b0 j
b0 p
b0 ,
b0 0
b11110111 B
b11110111 F
b11110111 b
b111000000001 P
b111000000001 i
b11110111 +
b11110111 9
b11110111 C
b11110111 O
b11110111 a
b11110111 o
b11110111 t
b10010000 /
b10010000 8
b10010000 N
b10010000 `
b10010000 n
b10010000 u
b0 )
b0 :
b0 -
b0 ;
b10000 @
b10000 d
b0 X
b0 l
b0 r
0A
b1101 S
b1101 g
b1101 h
12
#305000
02
#310000
1H
1!
1$
1"
b10010000 K
b10010000 E
b10010000 T
b10010000 [
b10010000 m
b10010000 s
b110010000 G
b10010000 B
b10010000 F
b10010000 b
0W
b10010000 +
b10010000 9
b10010000 C
b10010000 O
b10010000 a
b10010000 o
b10010000 t
b1110111 /
b1110111 8
b1110111 N
b1110111 `
b1110111 n
b1110111 u
12
#315000
02
#320000
13
11
b11110111 K
b11110111 E
b11110111 T
b11110111 [
b11110111 m
b11110111 s
b1000 (
b1000 ]
0$
b111 M
b111 \
b111 f
17
1L
0Q
b111110111 G
0!
b1000 &
b1000 4
b1000 Y
b0 e
b0 k
b0 q
b1 j
b1 p
1#
b11110111 B
b11110111 F
b11110111 b
b1000 P
b1000 i
b11110111 +
b11110111 9
b11110111 C
b11110111 O
b11110111 a
b11110111 o
b11110111 t
1U
b1110 S
b1110 g
b1110 h
12
#325000
02
#330000
0H
03
01
b1110111 K
b1110111 E
b1110111 T
b1110111 [
b1110111 m
b1110111 s
b0 (
b0 ]
1$
b0 M
b0 \
b0 f
07
0L
1Q
b1110111 G
b0 &
b0 4
b0 Y
b111 e
b0 j
b0 p
0#
b1110111 B
b1110111 F
b1110111 b
b111000000000 P
b111000000000 i
1W
b1000 @
b1000 d
b1110111 +
b1110111 9
b1110111 C
b1110111 O
b1110111 a
b1110111 o
b1110111 t
b11110111 /
b11110111 8
b11110111 N
b11110111 `
b11110111 n
b11110111 u
b1111 S
b1111 g
b1111 h
12
#335000
02
#340000
1H
0$
0"
b11110111 K
b11110111 E
b11110111 T
b11110111 [
b11110111 m
b11110111 s
b111110111 G
b11110111 B
b11110111 F
b11110111 b
b11110111 +
b11110111 9
b11110111 C
b11110111 O
b11110111 a
b11110111 o
b11110111 t
0W
12
#345000
02
#350000
0H
b1110111 K
b1110111 E
b1110111 T
b1110111 [
b1110111 m
b1110111 s
b1001 (
b1001 ]
b1110111 G
b1001 &
b1001 4
b1001 Y
b1 k
b1 q
b1 j
b1 p
1#
b1110111 B
b1110111 F
b1110111 b
b111000001001 P
b111000001001 i
0U
b1110111 +
b1110111 9
b1110111 C
b1110111 O
b1110111 a
b1110111 o
b1110111 t
b1110111 /
b1110111 8
b1110111 N
b1110111 `
b1110111 n
b1110111 u
b0 S
b0 g
b0 h
12
#355000
02
#360000
12
#365000
02
#370000
12
#375000
02
#380000
12
#385000
02
#390000
1H
1$
1!
1"
b10000 I
12
