rtl/v6/mux_21.sv
module mux_21 #(
    parameter BIT_WIDTH = 8
) (   
    input  logic s, 
    input  logic [BIT_WIDTH-1:0] a, b,
    output logic [BIT_WIDTH-1:0] out
);
    `ifdef COCOTB_SIM
    initial begin
        $dumpfile ("mux_21.vcd");
        $dumpvars (0, mux_21);
        #1;
    end
    `endif 
    assign out = s ? a : b;
endmodule

rtl/v7/sfixed_adder.sv
import datatypes::max;

module sfixed_adder #(
    parameter A_LEFT    = 3, 
    parameter A_RIGHT   = 4, 
    parameter B_LEFT    = 3, 
    parameter B_RIGHT   = 4,
    parameter OUT_LEFT  = 4, 
    parameter OUT_RIGHT = 4
) (   
    input  logic signed [(A_LEFT+A_RIGHT+1)-1:0]     a,
    input  logic signed [(B_LEFT+B_RIGHT+1)-1:0]     b,
    output logic signed [(OUT_LEFT+OUT_RIGHT+1)-1:0] out
);

`ifdef COCOTB_SIM
initial begin
    $dumpfile ("sfixed_adder.vcd");
    $dumpvars (0, sfixed_adder);
    #1;
end
`endif

localparam OUTPUT_SIZE = (max(A_LEFT,B_LEFT)+1)+max(A_RIGHT,B_RIGHT)+1; 

logic signed [OUTPUT_SIZE-1:0] add_out;

always_comb
    add_out = a + b;

assign out = add_out[max(A_RIGHT,B_RIGHT)+OUT_LEFT:max(A_RIGHT,B_RIGHT)-OUT_RIGHT];

endmodule

rtl/v7/sfixed_mult.sv
module sfixed_mult #(
    parameter A_LEFT    = 3, 
    parameter A_RIGHT   = 4,
    parameter B_LEFT    = 3, 
    parameter B_RIGHT   = 4,
    parameter OUT_LEFT  = 7, 
    parameter OUT_RIGHT = 8
) (
    input  logic signed [(A_LEFT+A_RIGHT+1)-1:0]     a,
    input  logic signed [(B_LEFT+B_RIGHT+1)-1:0]     b,
    output logic signed [(OUT_LEFT+OUT_RIGHT+1)-1:0] out
);
`ifdef COCOTB_SIM
initial begin
    $dumpfile ("sfixed_mult.vcd");
    $dumpvars (0, sfixed_mult);
    #1;
end
`endif

localparam OUTPUT_SIZE = (A_LEFT+B_LEFT+1)+(A_RIGHT+B_RIGHT)+1; 
                                                                
logic signed [OUTPUT_SIZE-1:0] mult_out;

always_comb
    mult_out = a * b;

assign out = mult_out[(A_RIGHT+B_RIGHT)+OUT_LEFT:(A_RIGHT+B_RIGHT)-OUT_RIGHT];

endmodule

rtl/v8/ALU_mult_stage.sv
module ALU_mult_stage #(
    parameter BUS_WIDTH = 8
) (
    input  logic clk, f_clr,
    input  logic b_en, d_en,
    input  logic [BUS_WIDTH-1:0] data_a, data_b, imm,
    output logic [BUS_WIDTH-1:0] mult_a, mult_b
);
`ifdef COCOTB_SIM
initial begin
    $dumpfile ("ALU_mult_stage.vcd");
    $dumpvars (0, ALU_mult_stage);
    #1;
end
`endif

// input registers
logic [BUS_WIDTH-1:0] op_b_reg, op_d_reg;

always_ff @( posedge clk ) begin 
    if (b_en) begin
       if (f_clr)
          op_b_reg <= '0;
       else 
          op_b_reg <= imm;
    end   
end

always_ff @( posedge clk ) begin 
    if (d_en) begin
        if (f_clr)
          op_d_reg <= '0;
       else 
          op_d_reg <= imm;
    end
end

sfixed_mult #(
    7, 
    0,
    0, 
    7,
    7,
    0 
) m0 (
    .a  (data_a  ), // int
    .b  (op_b_reg), // tf
    .out(mult_a  )
);

sfixed_mult #(
    7, 
    0,
    0, 
    7,
    7,
    0 
) m1 (
    .a  (data_b  ), // int
    .b  (op_d_reg), // tf
    .out(mult_b  )
);

    
endmodule

rtl/v8/ALU_v2.sv
module ALU_v2 #(
    parameter BUS_WIDTH  = 8
) (
    input  logic                 clk, 
    input  logic [BUS_WIDTH-1:0] imm,
    input  logic [BUS_WIDTH-1:0] data_a,    
    input  logic [BUS_WIDTH-1:0] data_b,    
    input  logic [2:0]           reg_en,
    input  logic                 f_clr,
    output logic [BUS_WIDTH-1:0] result 
);       


// the multiplier part

logic [BUS_WIDTH-1:0] mult_a, mult_b, add_a, add_b;

ALU_mult_stage #(
    BUS_WIDTH
) am1 (
    .clk   (clk      ),
    .f_clr (f_clr    ),
    .b_en  (reg_en[0]), 
    .d_en  (reg_en[1]),
    .data_a(data_a   ),
    .data_b(data_b   ),
    .imm   (imm      ),
    .mult_a(mult_a   ),
    .mult_b(mult_b   )
);

// the adder part 

logic [BUS_WIDTH-1:0] op_e, e_add, coeff;
logic [BUS_WIDTH-1:0] op_e_reg;

always_ff @( posedge clk ) begin
    if (reg_en[2])
        op_e_reg <= imm;
end

sfixed_adder #(
    7, 
    0, 
    7, 
    0,
    7, 
    0
) a0 ( 
    .a  (mult_a), // int
    .b  (mult_b), // int
    .out(add_a )
);

sfixed_adder #(
    7, 
    0, 
    7, 
    0,
    7, 
    0
) a1 (  
    .a  (add_a   ), // int
    .b  (op_e_reg), // int
    .out(result  )
);

endmodule

include/opcodes.sv
//-----------------------------------------------------
// File Name : opcodes.sv
// Function : pMIPS instr opcode definitions
// Author: jf
//-----------------------------------------------------
//
`define NOP  6'b000000
`define ADD  6'b000001
`define SUB  6'b000010
`define ADDI 6'b000011
`define SUBI 6'b000100
`define BEQ  6'b000101
`define BNE  6'b000110
`define BGE  6'b000111
`define BLO  6'b001000

rtl/v8/instruction_decoder.sv
`include "opcodes.sv"

module instruction_decoder #(
    parameter OPCODE_WIDTH = 3
) (
    input  logic [OPCODE_WIDTH-1:0] opcode,                  
    output logic                    f_move,            
    output logic                    f_wait,       
    output logic                    f_load,      
    output logic                    f_clr,      
    output logic                    wr_res,         
    output logic [2:0]              ALU_reg_en
);

always_comb 
begin
    case(opcode)    
        `MOV : begin
            f_load     = '0;
            f_move     = '1; 
            f_wait     = '0;
            wr_res     = '1; 
            f_clr      = '1;
            ALU_reg_en = 3'b111; // B, D, E
        end
        `MAC : begin 
            f_load     = '0;
            f_move     = '0; 
            f_wait     = '0;
            wr_res     = '1; 
            f_clr      = '0;
            ALU_reg_en = 3'b000; // C, A
        end
        `WAIT: begin
            f_load     = '0;
            f_move     = '0; 
            f_wait     = '1;
            wr_res     = '0;
            f_clr      = '0;
            ALU_reg_en = 3'b000;
        end
        `SETB: begin
            f_load     = '0;
            f_move     = '0; 
            f_wait     = '0;
            wr_res     = '0;
            f_clr      = '0;
            ALU_reg_en = 3'b001; 
        end
        `SETD: begin
            f_load     = '0;
            f_move     = '0; 
            f_wait     = '0;
            wr_res     = '0;
            f_clr      = '0;
            ALU_reg_en = 3'b010;
        end
        `SETE: begin
            f_load     = '0;
            f_move     = '0; 
            f_wait     = '0;
            wr_res     = '0;
            f_clr      = '0;
            ALU_reg_en = 3'b100;
        end
        `LDSW: begin
            f_load     = '1;
            f_move     = '0; 
            f_wait     = '0;
            f_clr      = '1;
            wr_res     = '1;
            ALU_reg_en = 3'b111;
        end
        default : begin
            f_load     = '0;
            f_move     = '0; 
            f_wait     = '0;
            f_clr      = '0;
            wr_res     = '0;
            ALU_reg_en = '0;
        end
    endcase 
end 

endmodule

rtl/v3/register_file.sv
module register_file #(
    parameter BUS_WIDTH  = 8,
    parameter ADDR_WIDTH = 3
) (
	input  logic                  clk, 
	input  logic                  we,
 	input  logic [ADDR_WIDTH-1:0] wr_addr,
	input  logic [BUS_WIDTH-1:0]  wr_data,
 	input  logic [ADDR_WIDTH-1:0] rd_addr_a, rd_addr_b,
 	output logic [BUS_WIDTH-1:0]  rd_data_a, rd_data_b
);

localparam N = (1 << ADDR_WIDTH);

logic [BUS_WIDTH-1:0] gpr [N-1:0];

initial begin
	for (int i = 0; i < N; i = i + 1)
		gpr[i] = '0;
end

// syncrhonous RAM write
always_ff @ (posedge clk)
begin
	if (we) begin 
		gpr[wr_addr] <= wr_data;
	end
	rd_data_b <= gpr[rd_addr_b];
	rd_data_a <= gpr[rd_addr_a];
end	
	

endmodule

rtl/v6/program_memory.sv
module program_memory #(
    parameter ADDR_WIDTH  = 4,
    parameter INSTR_WIDTH = 12
) (
    input  logic [ADDR_WIDTH-1:0]  addr,
    output logic [INSTR_WIDTH-1:0] instr
); 

(* ramstyle = "mlab" *) logic [INSTR_WIDTH-1:0] prog_mem [(1<<ADDR_WIDTH)-1:0];

initial
begin
`ifdef COCOTB_SIM
    $readmemh("/home/jonahfoley/ELEC6234/a_fine_CPU/programs/prog_3.hex", prog_mem);
`else
    $readmemh("../../programs/prog_3.hex", prog_mem);
`endif
end
   
always_comb
    instr = prog_mem[addr]; 
  
endmodule

rtl/v3/program_counter.sv
module program_counter #(
    parameter ADDR_WIDTH = 3
) (
    input  logic                  clk, n_reset,
    input  logic                  en,
    output logic [ADDR_WIDTH-1:0] count
);
 
always_ff @(posedge clk, negedge n_reset) 
begin   
    if (~n_reset) 
        count <= '0;
    else begin
        if (count == (2<<ADDR_WIDTH)-1) 
            count <= '0;
        else begin
            if (en)
                count <= count + { {ADDR_WIDTH-1{1'b0}}, 1'b1 };
        end
    end
end


endmodule

rtl/v8/CPU.sv
module CPU #(
    parameter INSTR_WIDTH      = 12,
    parameter OPCODE_WIDTH     = 3,
    parameter INSTR_ADDR_WIDTH = 4, 
    parameter REG_ADDR_WIDTH   = 2, 
    parameter BUS_WIDTH        = 8
) (
    input  logic                 clk,  
    input  logic                 n_reset,
    input  logic [BUS_WIDTH-1:0] in_port,
    input  logic                 ready_in,
    output logic [BUS_WIDTH-1:0] out_port
);       

//the macro to dump signals   
`ifdef COCOTB_SIM
initial begin
    $dumpfile ("CPU.vcd");
    $dumpvars (0, CPU);
    #1;
end
`endif

// input switch handshaking
logic ready_in_p, pattern_match;
always_ff @(posedge clk)
    ready_in_p <= ready_in;

logic [1:0][BUS_WIDTH-1:0] sw;
always_ff @(posedge clk)
    sw <= {sw[0], in_port};

assign pattern_match = (~ready_in_p & ready_in);

// -- instr counter
logic [INSTR_ADDR_WIDTH-1:0] PC_count;
logic PC_en, PC_comparator;

mux_21 #(
    1
) PC_en_mux (
    .s  (instr[3]     ), 
    .a  (pattern_match), 
    .b  (ready_in     ), 
    .out(PC_comparator)
);

assign PC_en = ~(f_wait & (PC_comparator ^ instr[0]));

program_counter #(
   INSTR_ADDR_WIDTH
) pc (
   .clk    (clk     ),
   .n_reset(n_reset ),
   .en     (PC_en   ),
   .count  (PC_count)
);

// -- program ROM
logic [INSTR_WIDTH-1:0] instr;

program_memory #(
    INSTR_ADDR_WIDTH,
    INSTR_WIDTH
) pm (
    .addr (PC_count),
    .instr(instr   )
);

// -- reg file
logic wr_res;
logic we;
logic [REG_ADDR_WIDTH-1:0] wr_addr;
logic [BUS_WIDTH-1:0] rd_data_a, rd_data_b;

always_ff @(posedge clk) 
begin
    we      <= wr_res;
    wr_addr <= instr[7:6];
end

register_file #(
    BUS_WIDTH,
    3
) rf (
	.clk      (clk       ),  
    .we       (we        ),
 	.wr_addr  (wr_addr   ),
	.wr_data  (wr_data   ),
 	.rd_addr_a(instr[4:3]), 
    .rd_addr_b(instr[1:0]),
 	.rd_data_a(rd_data_a ), 
    .rd_data_b(rd_data_b )
);

// -- decoder
logic f_reg_e, f_load, f_wait;
logic [2:0] reg_en; 

instruction_decoder #(
    OPCODE_WIDTH
) id (
    .opcode    (instr[11:9]),                  
    .f_move    (f_move     ), 
    .f_wait    (f_wait     ),            
    .f_load    (f_load     ),            
    .f_clr     (f_clr      ),            
    .wr_res    (wr_res     ),         
    .ALU_reg_en(reg_en     )
);

// -- ALU
logic [BUS_WIDTH-1:0] ALU_result;

ALU_v2 #(
    BUS_WIDTH
) alu (
    .clk    (clk       ), 
    .imm    (instr[7:0]),
    .data_a (rd_data_a ),
    .data_b (rd_data_b ),   
    .reg_en (reg_en    ),
    .f_clr  (f_clr     ),
    .result (ALU_result)
);    

logic [BUS_WIDTH-1:0] m1, wr_data;
logic f_move_p, f_load_p;

always_ff @(posedge clk)
begin
    f_move_p <= f_move;
    f_load_p <= f_load;
end 

mux_21 #(
    BUS_WIDTH
) mov_mux (
    .s  (f_move_p  ), 
    .a  (rd_data_a ), 
    .b  (ALU_result), 
    .out(m1        )
);

mux_21 #(
    BUS_WIDTH
) sw_mux (
    .s  (f_load_p), 
    .a  (sw[1]   ), 
    .b  (m1      ), 
    .out(wr_data )
);

assign out_port = wr_data;

endmodule

simulation/v8/CPU/mux_21.vcd
$date
	Mon Apr 24 05:19:01 2023
$end
$version
	Icarus Verilog
$end
$timescale
	1ps
$end
$scope module CPU $end
$scope module PC_en_mux $end
$var wire 1 ! a $end
$var wire 1 " b $end
$var wire 1 # s $end
$var wire 1 $ out $end
$upscope $end
$upscope $end
$scope module CPU $end
$scope module alu $end
$scope module am1 $end
$scope module m0 $end
$var wire 8 % b [7:0] $end
$var wire 8 & out [7:0] $end
$var wire 8 ' a [7:0] $end
$var reg 16 ( mult_out [15:0] $end
$upscope $end
$upscope $end
$upscope $end
$upscope $end
$scope module CPU $end
$scope module alu $end
$scope module am1 $end
$scope module m1 $end
$var wire 8 ) b [7:0] $end
$var wire 8 * out [7:0] $end
$var wire 8 + a [7:0] $end
$var reg 16 , mult_out [15:0] $end
$upscope $end
$upscope $end
$upscope $end
$upscope $end
$scope module CPU $end
$scope module alu $end
$scope module am1 $end
$var wire 1 - b_en $end
$var wire 1 . clk $end
$var wire 1 / d_en $end
$var wire 8 0 imm [7:0] $end
$var wire 8 1 mult_b [7:0] $end
$var wire 8 2 mult_a [7:0] $end
$var wire 1 3 f_clr $end
$var wire 8 4 data_b [7:0] $end
$var wire 8 5 data_a [7:0] $end
$var reg 8 6 op_b_reg [7:0] $end
$var reg 8 7 op_d_reg [7:0] $end
$scope module m0 $end
$upscope $end
$scope module m1 $end
$upscope $end
$upscope $end
$upscope $end
$upscope $end
$scope module CPU $end
$scope module alu $end
$scope module a0 $end
$var wire 8 8 out [7:0] $end
$var wire 8 9 b [7:0] $end
$var wire 8 : a [7:0] $end
$var reg 9 ; add_out [8:0] $end
$upscope $end
$upscope $end
$upscope $end
$scope module CPU $end
$scope module alu $end
$scope module a1 $end
$var wire 8 < a [7:0] $end
$var wire 8 = b [7:0] $end
$var wire 8 > out [7:0] $end
$var reg 9 ? add_out [8:0] $end
$upscope $end
$upscope $end
$upscope $end
$scope module CPU $end
$scope module mov_mux $end
$var wire 8 @ b [7:0] $end
$var wire 1 A s $end
$var wire 8 B out [7:0] $end
$var wire 8 C a [7:0] $end
$upscope $end
$upscope $end
$scope module CPU $end
$scope module sw_mux $end
$var wire 8 D a [7:0] $end
$var wire 8 E b [7:0] $end
$var wire 1 F s $end
$var wire 8 G out [7:0] $end
$upscope $end
$upscope $end
$scope module CPU $end
$var wire 1 H PC_en $end
$var wire 1 . clk $end
$var wire 8 I in_port [7:0] $end
$var wire 1 J n_reset $end
$var wire 8 K out_port [7:0] $end
$var wire 1 ! pattern_match $end
$var wire 1 " ready_in $end
$var wire 1 L wr_res $end
$var wire 8 M wr_data [7:0] $end
$var wire 3 N reg_en [2:0] $end
$var wire 8 O rd_data_b [7:0] $end
$var wire 8 P rd_data_a [7:0] $end
$var wire 8 Q m1 [7:0] $end
$var wire 12 R instr [11:0] $end
$var wire 1 S f_wait $end
$var wire 1 T f_move $end
$var wire 1 U f_load $end
$var wire 1 3 f_clr $end
$var wire 4 V PC_count [3:0] $end
$var wire 1 $ PC_comparator $end
$var wire 8 W ALU_result [7:0] $end
$var reg 1 F f_load_p $end
$var reg 1 A f_move_p $end
$var reg 1 X ready_in_p $end
$var reg 16 Y sw [15:0] $end
$var reg 1 Z we $end
$var reg 2 [ wr_addr [1:0] $end
$scope module PC_en_mux $end
$upscope $end
$scope module alu $end
$var wire 1 . clk $end
$var wire 8 \ imm [7:0] $end
$var wire 8 ] result [7:0] $end
$var wire 3 ^ reg_en [2:0] $end
$var wire 8 _ mult_b [7:0] $end
$var wire 8 ` mult_a [7:0] $end
$var wire 1 3 f_clr $end
$var wire 8 a data_b [7:0] $end
$var wire 8 b data_a [7:0] $end
$var wire 8 c add_a [7:0] $end
$var reg 8 d op_e_reg [7:0] $end
$scope module a0 $end
$upscope $end
$scope module a1 $end
$upscope $end
$scope module am1 $end
$scope module m0 $end
$upscope $end
$scope module m1 $end
$upscope $end
$upscope $end
$upscope $end
$scope module id $end
$var wire 3 e opcode [2:0] $end
$var reg 3 f ALU_reg_en [2:0] $end
$var reg 1 3 f_clr $end
$var reg 1 U f_load $end
$var reg 1 T f_move $end
$var reg 1 S f_wait $end
$var reg 1 L wr_res $end
$upscope $end
$scope module mov_mux $end
$upscope $end
$scope module pc $end
$var wire 1 . clk $end
$var wire 1 H en $end
$var wire 1 J n_reset $end
$var reg 4 g count [3:0] $end
$upscope $end
$scope module pm $end
$var wire 4 h addr [3:0] $end
$var reg 12 i instr [11:0] $end
$upscope $end
$scope module rf $end
$var wire 1 . clk $end
$var wire 2 j rd_addr_a [1:0] $end
$var wire 2 k rd_addr_b [1:0] $end
$var wire 1 Z we $end
$var wire 2 l wr_addr [1:0] $end
$var wire 8 m wr_data [7:0] $end
$var wire 8 n rd_data_b [7:0] $end
$var wire 8 o rd_data_a [7:0] $end
$scope module sr0 $end
$var wire 1 . clk $end
$var wire 2 p rd_addr_a [1:0] $end
$var wire 2 q rd_addr_b [1:0] $end
$var wire 1 Z we $end
$var wire 2 r wr_addr [1:0] $end
$var wire 8 s wr_data [7:0] $end
$var reg 8 t rd_data_a [7:0] $end
$var reg 8 u rd_data_b [7:0] $end
$scope begin $ivl_for_loop0 $end
$var integer 32 v i [31:0] $end
$upscope $end
$upscope $end
$upscope $end
$scope module sw_mux $end
$upscope $end
$upscope $end
$enddefinitions $end
#0
$dumpvars
b11 v
bx u
bx t
bx s
bx r
b1 q
b1 p
bx o
bx n
bx m
bx l
b1 k
b1 j
b111000001001 i
b0 h
b0 g
b0 f
b111 e
bx d
bx c
bx b
bx a
bx `
bx _
b0 ^
bx ]
b1001 \
bx [
0Z
bx00000000 Y
0X
bx W
b0 V
0U
0T
1S
b111000001001 R
bx Q
bx P
bx O
b0 N
bx M
0L
bx K
0J
b0 I
0H
bx G
0F
bx E
bx D
bx C
bx B
0A
bx @
bx ?
bx >
bx =
bx <
bx ;
bx :
bx 9
bx 8
bx 7
bx 6
bx 5
bx 4
03
bx 2
bx 1
b1001 0
0/
1.
0-
bx ,
bx +
bx *
bx )
bx (
bx '
bx &
bx %
0$
1#
0"
0!
$end
#5000
0.
#10000
b0 D
b0 [
b0 l
b0 r
b0 Y
b0 '
b0 5
b0 C
b0 P
b0 b
b0 o
b0 t
b0 +
b0 4
b0 O
b0 a
b0 n
b0 u
1.
#15000
0.
#20000
1J
1.
#25000
0.
#30000
1.
#35000
0.
#40000
1.
#45000
0.
#50000
1.
#55000
0.
#60000
1.
#65000
0.
#70000
1.
#75000
0.
#80000
1.
#85000
0.
#90000
1.
#95000
0.
#100000
1.
#105000
0.
#110000
1.
#115000
0.
#120000
1H
1$
1!
1"
b10111011 I
1.
#125000
0.
#130000
0$
0"
1/
1-
b111 N
b111 ^
b111 f
1L
13
0S
1U
0!
b0 0
b0 \
b110 e
b0 k
b0 q
b0 j
b0 p
0#
b110000000000 R
b110000000000 i
b10111011 Y
1X
b1 V
b1 g
b1 h
1.
#135000
0.
#140000
b0 B
b0 E
b0 Q
b0 >
b0 @
b0 W
b0 ]
b0 ?
0H
b0 8
b0 <
b0 c
0/
0-
b0 ;
b0 N
b0 ^
b0 f
03
0L
1S
0U
b0 &
b0 2
b0 :
b0 `
b0 *
b0 1
b0 9
b0 _
b1001 0
b1001 \
b111 e
b1 k
b1 q
b1 j
b1 p
1#
b0 (
b0 ,
b10111011 D
b10111011 K
b10111011 G
b10111011 M
b10111011 m
b10111011 s
b111000001001 R
b111000001001 i
b0 %
b0 6
b0 )
b0 7
b0 =
b0 d
0X
b1011101110111011 Y
1Z
1F
b10 V
b10 g
b10 h
1.
#145000
0.
#150000
b0 K
b0 G
b0 M
b0 m
b0 s
0F
0Z
1.
#155000
0.
#160000
1.
#165000
0.
#170000
1.
#175000
0.
#180000
1.
#185000
0.
#190000
1H
1$
1!
1"
b11001111 I
1.
#195000
0.
#200000
0$
0"
1/
1-
b111 N
b111 ^
b111 f
1L
13
0S
1U
0!
b1000000 0
b1000000 \
b110 e
b0 k
b0 q
b0 j
b0 p
0#
b110001000000 R
b110001000000 i
1X
b1011101111001111 Y
b11 V
b11 g
b11 h
1.
#205000
0.
#210000
0/
b1000000 B
b1000000 E
b1000000 Q
b1 N
b1 ^
b1 f
03
0L
0U
b1000000 >
b1000000 @
b1000000 W
b1000000 ]
b1100000 0
b1100000 \
b11 e
b11001111 K
b11001111 G
b11001111 M
b11001111 m
b11001111 s
b11001111 D
b1000000 ?
b11001100000 R
b11001100000 i
1F
b1 [
b1 l
b1 r
1Z
b1100111111001111 Y
0X
b1000000 =
b1000000 d
b10111011 '
b10111011 5
b10111011 C
b10111011 P
b10111011 b
b10111011 o
b10111011 t
b10111011 +
b10111011 4
b10111011 O
b10111011 a
b10111011 n
b10111011 u
b100 V
b100 g
b100 h
1.
#215000
0.
#220000
b1100 B
b1100 E
b1100 Q
b1100 >
b1100 @
b1100 W
b1100 ]
b1100 ?
b11001100 8
b11001100 <
b11001100 c
1/
0-
b111001100 ;
b10 N
b10 ^
b10 f
b11001100 &
b11001100 2
b11001100 :
b11001100 `
b1000000 0
b1000000 \
b100 e
b1110011000100000 (
b1100 K
b1100 G
b1100 M
b1100 m
b1100 s
b100001000000 R
b100001000000 i
b1100000 %
b1100000 6
0Z
0F
b101 V
b101 g
b101 h
1.
#225000
0.
#230000
b11101001 K
b11101001 G
b11101001 M
b11101001 m
b11101001 s
b11101001 B
b11101001 E
b11101001 Q
b11101001 >
b11101001 @
b11101001 W
b11101001 ]
b111101001 ?
b10101001 8
b10101001 <
b10101001 c
0/
b110101001 ;
b100 N
b100 ^
b100 f
b11011101 *
b11011101 1
b11011101 9
b11011101 _
b10100 0
b10100 \
b101 e
b10 j
b10 p
b1110111011000000 ,
b101000010100 R
b101000010100 i
b1000000 )
b1000000 7
b110 V
b110 g
b110 h
1.
#235000
0.
#240000
b11011101 8
b11011101 <
b11011101 c
b11110001 K
b11110001 G
b11110001 M
b11110001 m
b11110001 s
b111011101 ;
b11110001 B
b11110001 E
b11110001 Q
b0 N
b0 ^
b0 f
1L
b0 &
b0 2
b0 :
b0 `
b11110001 >
b11110001 @
b11110001 W
b11110001 ]
b10000001 0
b10000001 \
b1 e
b1 k
b1 q
b0 j
b0 p
b0 (
b111110001 ?
b1010000001 R
b1010000001 i
b0 '
b0 5
b0 C
b0 P
b0 b
b0 o
b0 t
b10100 =
b10100 d
b0 [
b0 l
b0 r
b111 V
b111 g
b111 h
1.
#245000
0.
#250000
b11000111 K
b11000111 G
b11000111 M
b11000111 m
b11000111 s
b11000111 B
b11000111 E
b11000111 Q
b11000111 >
b11000111 @
b11000111 W
b11000111 ]
b111000111 ?
b10110011 8
b10110011 <
b10110011 c
1-
b110110011 ;
b1 N
b1 ^
b1 f
0L
b11001100 &
b11001100 2
b11001100 :
b11001100 `
b11100111 *
b11100111 1
b11100111 9
b11100111 _
b11000000 0
b11000000 \
b11 e
b0 k
b0 q
b1110011000100000 (
b1111001111000000 ,
b11011000000 R
b11011000000 i
b10 [
b10 l
b10 r
1Z
b10111011 '
b10111011 5
b10111011 C
b10111011 P
b10111011 b
b10111011 o
b10111011 t
b11001111 +
b11001111 4
b11001111 O
b11001111 a
b11001111 n
b11001111 u
b1000 V
b1000 g
b1000 h
1.
#255000
0.
#260000
b10011 K
b10011 G
b10011 M
b10011 m
b10011 s
b10011 B
b10011 E
b10011 Q
b10011 >
b10011 @
b10011 W
b10011 ]
b10011 ?
b11111111 8
b11111111 <
b11111111 c
1/
0-
b111111111 ;
b10 N
b10 ^
b10 f
b11011101 *
b11011101 1
b11011101 9
b11011101 _
b100010 &
b100010 2
b100010 :
b100010 `
b1100000 0
b1100000 \
b100 e
b1110111011000000 ,
b1000101000000 (
b100001100000 R
b100001100000 i
b10111011 +
b10111011 4
b10111011 O
b10111011 a
b10111011 n
b10111011 u
b11000000 %
b11000000 6
b11 [
b11 l
b11 r
0Z
b1001 V
b1001 g
b1001 h
1.
#265000
0.
#270000
b10 K
b10 G
b10 M
b10 m
b10 s
b10 B
b10 E
b10 Q
b10 >
b10 @
b10 W
b10 ]
b10 ?
b11101110 8
b11101110 <
b11101110 c
0/
b111101110 ;
b100 N
b100 ^
b100 f
b11001100 *
b11001100 1
b11001100 9
b11001100 _
b11101100 0
b11101100 \
b101 e
b1 j
b1 p
1#
b1110011000100000 ,
b101011101100 R
b101011101100 i
b1 [
b1 l
b1 r
b1100000 )
b1100000 7
b1010 V
b1010 g
b1010 h
1.
#275000
0.
#280000
b11100100 8
b11100100 <
b11100100 c
b11010000 K
b11010000 G
b11010000 M
b11010000 m
b11010000 s
b111100100 ;
b11010000 B
b11010000 E
b11010000 Q
b0 N
b0 ^
b0 f
1L
b11000 &
b11000 2
b11000 :
b11000 `
b11010000 >
b11010000 @
b11010000 W
b11010000 ]
b1000001 0
b1000001 \
b1 e
b1 k
b1 q
b0 j
b0 p
0#
b110001000000 (
b111010000 ?
b1001000001 R
b1001000001 i
b11001111 '
b11001111 5
b11001111 C
b11001111 P
b11001111 b
b11001111 o
b11001111 t
b11101100 =
b11101100 d
b11 [
b11 l
b11 r
b1011 V
b1011 g
b1011 h
1.
#285000
0.
#290000
b11101001 K
b11101001 G
b11101001 M
b11101001 m
b11101001 s
b11101001 B
b11101001 E
b11101001 Q
b11101001 >
b11101001 @
b11101001 W
b11101001 ]
b111101001 ?
b11111101 8
b11111101 <
b11111101 c
1/
1-
b111111101 ;
b111 N
b111 ^
b111 f
13
1T
b100010 &
b100010 2
b100010 :
b100010 `
b11011011 *
b11011011 1
b11011011 9
b11011011 _
b10000 0
b10000 \
b0 e
b0 k
b0 q
b10 j
b10 p
b1000101000000 (
b1110110110100000 ,
b10000 R
b10000 i
b1 [
b1 l
b1 r
1Z
b10111011 '
b10111011 5
b10111011 C
b10111011 P
b10111011 b
b10111011 o
b10111011 t
b11001111 +
b11001111 4
b11001111 O
b11001111 a
b11001111 n
b11001111 u
b1100 V
b1100 g
b1100 h
1.
#295000
0.
#300000
0H
b0 8
b0 <
b0 c
0/
0-
b0 ;
b0 N
b0 ^
b0 f
03
0L
1S
0T
b0 &
b0 2
b0 :
b0 `
b0 *
b0 1
b0 9
b0 _
b10000 >
b10000 @
b10000 W
b10000 ]
b11000111 K
b11000111 G
b11000111 M
b11000111 m
b11000111 s
b1 0
b1 \
b111 e
b1 k
b1 q
b0 j
b0 p
b0 (
b0 ,
b10000 ?
b11000111 B
b11000111 E
b11000111 Q
b111000000001 R
b111000000001 i
b11000111 '
b11000111 5
b11000111 C
b11000111 P
b11000111 b
b11000111 o
b11000111 t
b10111011 +
b10111011 4
b10111011 O
b10111011 a
b10111011 n
b10111011 u
b0 %
b0 6
b0 )
b0 7
b10000 =
b10000 d
b0 [
b0 l
b0 r
1A
b1101 V
b1101 g
b1101 h
1.
#305000
0.
#310000
1H
1!
1$
1"
b10000 K
b10000 G
b10000 M
b10000 m
b10000 s
b10000 B
b10000 E
b10000 Q
0A
0Z
b10111011 '
b10111011 5
b10111011 C
b10111011 P
b10111011 b
b10111011 o
b10111011 t
b11101001 +
b11101001 4
b11101001 O
b11101001 a
b11101001 n
b11101001 u
1.
#315000
0.
#320000
1/
1-
b111 N
b111 ^
b111 f
13
1L
0S
1T
0$
0!
b1000 0
b1000 \
b0 e
b0 k
b0 q
b1 j
b1 p
1#
b1000 R
b1000 i
b11000111 '
b11000111 5
b11000111 C
b11000111 P
b11000111 b
b11000111 o
b11000111 t
1X
b1110 V
b1110 g
b1110 h
1.
#325000
0.
#330000
0H
0/
0-
b0 N
b0 ^
b0 f
03
0L
1S
0T
1$
b11101001 K
b11101001 G
b11101001 M
b11101001 m
b11101001 s
b1000 >
b1000 @
b1000 W
b1000 ]
b0 0
b0 \
b111 e
b0 j
b0 p
0#
b11101001 B
b11101001 E
b11101001 Q
b1000 ?
b111000000000 R
b111000000000 i
1A
1Z
b1000 =
b1000 d
b11101001 '
b11101001 5
b11101001 C
b11101001 P
b11101001 b
b11101001 o
b11101001 t
b11000111 +
b11000111 4
b11000111 O
b11000111 a
b11000111 n
b11000111 u
b1111 V
b1111 g
b1111 h
1.
#335000
0.
#340000
1H
0$
0"
b1000 K
b1000 G
b1000 M
b1000 m
b1000 s
b1000 B
b1000 E
b1000 Q
b11000111 '
b11000111 5
b11000111 C
b11000111 P
b11000111 b
b11000111 o
b11000111 t
0Z
0A
1.
#345000
0.
#350000
0H
b1001 0
b1001 \
b1 k
b1 q
b1 j
b1 p
1#
b111000001001 R
b111000001001 i
0X
b11101001 '
b11101001 5
b11101001 C
b11101001 P
b11101001 b
b11101001 o
b11101001 t
b11101001 +
b11101001 4
b11101001 O
b11101001 a
b11101001 n
b11101001 u
b0 V
b0 g
b0 h
1.
#355000
0.
#360000
1.
#365000
0.
#370000
1.
#375000
0.
#380000
1.
#385000
0.
#390000
1H
1$
1!
1"
b1111010 I
1.
#395000
0.
#400000
0$
0"
1/
1-
b111 N
b111 ^
b111 f
1L
13
0S
1U
0!
b0 0
b0 \
b110 e
b0 k
b0 q
b0 j
b0 p
0#
b110000000000 R
b110000000000 i
1X
b1100111101111010 Y
b1 V
b1 g
b1 h
1.
#405000
0.
#410000
0H
0/
0-
b0 B
b0 E
b0 Q
b0 N
b0 ^
b0 f
03
0L
1S
0U
b0 >
b0 @
b0 W
b0 ]
b1001 0
b1001 \
b111 e
b1 k
b1 q
b1 j
b1 p
1#
b1111010 K
b1111010 G
b1111010 M
b1111010 m
b1111010 s
b1111010 D
b0 ?
b111000001001 R
b111000001001 i
1F
1Z
b111101001111010 Y
0X
b0 =
b0 d
b10 V
b10 g
b10 h
1.
#415000
0.
