rtl/v7/sfixed_adder.sv
import datatypes::max;

module sfixed_adder #(
    parameter A_LEFT    = 3, 
    parameter A_RIGHT   = 4, 
    parameter B_LEFT    = 3, 
    parameter B_RIGHT   = 4,
    parameter OUT_LEFT  = 4, 
    parameter OUT_RIGHT = 4
) (   
    input  logic signed [(A_LEFT+A_RIGHT+1)-1:0]     a,
    input  logic signed [(B_LEFT+B_RIGHT+1)-1:0]     b,
    output logic signed [(OUT_LEFT+OUT_RIGHT+1)-1:0] out
);

`ifdef COCOTB_SIM
initial begin
    $dumpfile ("sfixed_adder.vcd");
    $dumpvars (0, sfixed_adder);
    #1;
end
`endif

localparam OUTPUT_SIZE = (max(A_LEFT,B_LEFT)+1)+max(A_RIGHT,B_RIGHT)+1; 

logic signed [OUTPUT_SIZE-1:0] add_out;

always_comb
    add_out = a + b;

assign out = add_out[max(A_RIGHT,B_RIGHT)+OUT_LEFT:max(A_RIGHT,B_RIGHT)-OUT_RIGHT];

endmodule

rtl/v6/sfixed_mult_9x9_x3.sv
module sfixed_mult_9x9_x3 #(
    parameter A_LEFT    = 3, 
    parameter A_RIGHT   = 4,
    parameter B_LEFT    = 3, 
    parameter B_RIGHT   = 4,
    parameter OUT_LEFT  = 7, 
    parameter OUT_RIGHT = 8
) (
    input  logic signed [(A_LEFT+A_RIGHT+1)-1:0]     a_x,   a_y, //   a_z,
    input  logic signed [(B_LEFT+B_RIGHT+1)-1:0]     b_x,   b_y, //   b_z,
    output logic signed [(OUT_LEFT+OUT_RIGHT+1)-1:0] out_x, out_y//, out_z
);
`ifdef COCOTB_SIM
initial begin
    $dumpfile ("sfixed_mult_9x9_x3.vcd");
    $dumpvars (0, sfixed_mult_9x9_x3);
    #1;
end
`endif

localparam A_SIZE      = (A_LEFT+A_RIGHT+1);
localparam B_SIZE      = (B_LEFT+B_RIGHT+1);
localparam OUTPUT_SIZE = (A_LEFT+B_LEFT+1)+(A_RIGHT+B_RIGHT)+1; 

logic signed [OUTPUT_SIZE-1:0] result_a, result_b;
		
always_comb 
begin   
    result_a = a_x * b_x;
    result_b = a_y * b_y;
end

assign out_x = result_a[(A_RIGHT+B_RIGHT)+OUT_LEFT:(A_RIGHT+B_RIGHT)-OUT_RIGHT];
assign out_y = result_b[(A_RIGHT+B_RIGHT)+OUT_LEFT:(A_RIGHT+B_RIGHT)-OUT_RIGHT]; 
    
endmodule

rtl/v6/ALU_mult_stage.sv
module ALU_mult_stage #(
    parameter BUS_WIDTH = 8
) (
    input  logic clk,
    input  logic a_en, b_en, c_en, d_en,
    input  logic [BUS_WIDTH-1:0] data_a, data_b, coeff,
    output logic [BUS_WIDTH-1:0] mult_a, mult_b
);
`ifdef COCOTB_SIM
initial begin
    $dumpfile ("ALU_mult_stage.vcd");
    $dumpvars (0, ALU_mult_stage);
    #1;
end
`endif

// input registers
logic [BUS_WIDTH-1:0] op_a_reg, op_b_reg, op_c_reg, op_d_reg;

always_ff @( posedge clk ) begin 
    if (a_en) 
        op_a_reg <= data_a;
end

always_ff @( posedge clk ) begin 
    if (b_en) 
        op_b_reg <= coeff;
end

always_ff @( posedge clk ) begin 
    if (c_en) begin
        op_c_reg <= data_b;
    end
end

always_ff @( posedge clk ) begin 
    if (d_en)
        op_d_reg <= coeff;
end

(* keep *) sfixed_mult_9x9_x3 #(
    7, 
    0,
    0, 
    7,
    7, 
    0
) m0 (
    .a_x  (op_a_reg),
    .a_y  (op_c_reg), 
    .b_x  (op_b_reg),
    .b_y  (op_d_reg), 
    .out_x(mult_a  ),
    .out_y(mult_b  )
);
    
endmodule

rtl/v6/mux_21.sv
module mux_21 #(
    parameter BIT_WIDTH = 8
) (   
    input  logic s, 
    input  logic [BIT_WIDTH-1:0] a, b,
    output logic [BIT_WIDTH-1:0] out
);
    `ifdef COCOTB_SIM
    initial begin
        $dumpfile ("mux_21.vcd");
        $dumpvars (0, mux_21);
        #1;
    end
    `endif 
    assign out = s ? a : b;
endmodule

rtl/v6/ALU_v2.sv
module ALU_v2 #(
    parameter BUS_WIDTH  = 8
) (
    input  logic                 clk, 
    input  logic [BUS_WIDTH-1:0] sw,
    input  logic [BUS_WIDTH-1:0] imm,
    input  logic [BUS_WIDTH-1:0] data_a,    
    input  logic [BUS_WIDTH-1:0] data_b,    
    input  logic [4:0]           reg_en,
    input  logic                 add,
    input  logic                 load,
    output logic [BUS_WIDTH-1:0] result 
);       

// setting up of add/subtract inputs
logic [BUS_WIDTH-1:0] op_e, e_add, coeff;
logic [BUS_WIDTH-1:0] op_e_reg;


mux_21 #(
    BUS_WIDTH
) e_add_mux (   
    .s  (load), 
    .a  (sw    ), 
    .b  (data_a),
    .out(e_add )
);

mux_21 #(
    BUS_WIDTH
) op_e_mux (   
    .s  (add), 
    .a  (e_add), 
    .b  (imm  ),
    .out(op_e )
);

mux_21 #(
    BUS_WIDTH
) coeff_mux (   
    .s  (add              ), 
    .a  ({BUS_WIDTH{1'b0}}), 
    .b  (imm                ),
    .out(coeff               )
);


// input registers
always_ff @( posedge clk ) begin
    if (reg_en[4])
        op_e_reg <= op_e;
end

// the computational part
logic [BUS_WIDTH-1:0] mult_a, mult_b, add_a;

ALU_mult_stage #(
    BUS_WIDTH
) am1 (
    .clk   (clk),
    .a_en  (reg_en[0]), 
    .b_en  (reg_en[1]), 
    .c_en  (reg_en[2]), 
    .d_en  (reg_en[3]),
    .data_a(data_a),
    .data_b(data_b),
    .coeff (coeff  ),
    .mult_a(mult_a),
    .mult_b(mult_b)
);


sfixed_adder #(
    7, 
    0, 
    7, 
    0,
    7, 
    0
) a0 ( 
    .a  (mult_a), // int
    .b  (mult_b), // int
    .out(add_a )
);

sfixed_adder #(
    7, 
    0, 
    7, 
    0,
    7, 
    0
) a1 (  
    .a  (add_a   ), // int
    .b  (op_e_reg), // int
    .out(result  )
);

endmodule

include/opcodes.sv
//-----------------------------------------------------
// File Name : opcodes.sv
// Function : pMIPS instr opcode definitions
// Author: jf
//-----------------------------------------------------
//
`define NOP  6'b000000
`define ADD  6'b000001
`define SUB  6'b000010
`define ADDI 6'b000011
`define SUBI 6'b000100
`define BEQ  6'b000101
`define BNE  6'b000110
`define BGE  6'b000111
`define BLO  6'b001000

rtl/v6/instruction_decoder.sv
`include "opcodes.sv"

module instruction_decoder #(
    parameter OPCODE_WIDTH = 3
) (
    input  logic [OPCODE_WIDTH-1:0] opcode,                  
    output logic                    ALU_add,        
    output logic                    PC_wait,   
    output logic                    ALU_load,  
    output logic                    wr_res,       
    output logic [4:0]              ALU_reg_en
);

always_comb 
begin
    case(opcode)    
        `MOV : begin
            ALU_load   = '0;
            ALU_add    = '1; 
            PC_wait    = '0;
            wr_res     = '1; 
            ALU_reg_en = 5'b11111; // C, A
        end
        `MAC : begin 
            ALU_load   = '0;
            ALU_add    = '0;
            PC_wait    = '0;
            wr_res     = '1; 
            ALU_reg_en = 5'b00101; // C, A
        end
        `WAIT: begin
            ALU_load   = '0;
            ALU_add    = '0;
            PC_wait    = '1;
            wr_res     = '0;
            ALU_reg_en = 5'b00000;
        end
        `SETB: begin
            ALU_load   = '0;
            ALU_add    = '0;
            PC_wait    = '0;
            wr_res     = '0;
            ALU_reg_en = 5'b00010; 
        end
        `SETD: begin
            ALU_load   = '0;
            ALU_add    = '0;
            PC_wait    = '0;
            wr_res     = '0;
            ALU_reg_en = 5'b01000;
        end
        `SETE: begin
            ALU_load   = '0;
            ALU_add    = '0;
            PC_wait    = '0;
            wr_res     = '0;
            ALU_reg_en = 5'b10000;
        end
        `LDSW: begin
            ALU_load   = '1;
            ALU_add    = '1;
            PC_wait    = '0;
            wr_res     = '1;
            ALU_reg_en = 5'b11111;
        end
        default : begin
            ALU_load   = '0;
            ALU_add    = '0;
            PC_wait    = '0;
            wr_res     = '0;
            ALU_reg_en = '0;
        end
    endcase 
end 

endmodule

rtl/v3/register_file.sv
module register_file #(
    parameter BUS_WIDTH  = 8,
    parameter ADDR_WIDTH = 3
) (
	input  logic                  clk, 
	input  logic                  we,
 	input  logic [ADDR_WIDTH-1:0] wr_addr,
	input  logic [BUS_WIDTH-1:0]  wr_data,
 	input  logic [ADDR_WIDTH-1:0] rd_addr_a, rd_addr_b,
 	output logic [BUS_WIDTH-1:0]  rd_data_a, rd_data_b
);

localparam N = (1 << ADDR_WIDTH);

logic [BUS_WIDTH-1:0] gpr [N-1:0];

initial begin
	for (int i = 0; i < N; i = i + 1)
		gpr[i] = '0;
end

// syncrhonous RAM write
always_ff @ (posedge clk)
begin
	if (we) begin 
		gpr[wr_addr] <= wr_data;
	end
	rd_data_b <= gpr[rd_addr_b];
	rd_data_a <= gpr[rd_addr_a];
end	
	

endmodule

rtl/v6/program_memory.sv
module program_memory #(
    parameter ADDR_WIDTH  = 4,
    parameter INSTR_WIDTH = 12
) (
    input  logic [ADDR_WIDTH-1:0]  addr,
    output logic [INSTR_WIDTH-1:0] instr
); 

(* ramstyle = "mlab" *) logic [INSTR_WIDTH-1:0] prog_mem [(1<<ADDR_WIDTH)-1:0];

initial
begin
`ifdef COCOTB_SIM
    $readmemh("/home/jonahfoley/ELEC6234/a_fine_CPU/programs/prog_3.hex", prog_mem);
`else
    $readmemh("../../programs/prog_3.hex", prog_mem);
`endif
end
   
always_comb
    instr = prog_mem[addr]; 
  
endmodule

rtl/v3/program_counter.sv
module program_counter #(
    parameter ADDR_WIDTH = 3
) (
    input  logic                  clk, n_reset,
    input  logic                  en,
    output logic [ADDR_WIDTH-1:0] count
);
 
always_ff @(posedge clk, negedge n_reset) 
begin   
    if (~n_reset) 
        count <= '0;
    else begin
        if (count == (2<<ADDR_WIDTH)-1) 
            count <= '0;
        else begin
            if (en)
                count <= count + { {ADDR_WIDTH-1{1'b0}}, 1'b1 };
        end
    end
end


endmodule

rtl/v6/CPU.sv
module CPU #(
    parameter INSTR_WIDTH      = 12,
    parameter OPCODE_WIDTH     = 3,
    parameter INSTR_ADDR_WIDTH = 4, 
    parameter REG_ADDR_WIDTH   = 2, 
    parameter BUS_WIDTH        = 8
) (
    input  logic                 clk,  
    input  logic                 n_reset,
    input  logic [BUS_WIDTH-1:0] in_port,
    input  logic                 ready_in,
    output logic [BUS_WIDTH-1:0] out_port
);       

//the macro to dump signals   
`ifdef COCOTB_SIM
initial begin
    $dumpfile ("CPU.vcd");
    $dumpvars (0, CPU);
    #1;
end
`endif

// input switch handshaking
logic ready_in_p, pattern_match;
always_ff @(posedge clk)
    ready_in_p <= ready_in;

logic [1:0][BUS_WIDTH-1:0] sw;
always_ff @(posedge clk)
    sw <= {sw[0], in_port};

assign pattern_match = (~ready_in_p & ready_in);

// -- instr counter
logic [INSTR_ADDR_WIDTH-1:0] PC_count;
logic PC_en, PC_comparator;

mux_21 #(
    1
) PC_en_mux (
    .s  (instr[3]     ), // differentiate between instr[5:3] == 001 (pattern) / 000 (rdy)
    .a  (pattern_match), // 001 -> pattern
    .b  (ready_in     ), // 000 -> ready in 
    .out(PC_comparator)
);

assign PC_en = ~(PC_wait & (PC_comparator ^ instr[0]));

program_counter #(
   INSTR_ADDR_WIDTH
) pc (
   .clk    (clk     ),
   .n_reset(n_reset ),
   .en     (PC_en   ),
   .count  (PC_count)
);

// -- program ROM
logic [INSTR_WIDTH-1:0] instr;

program_memory #(
    INSTR_ADDR_WIDTH,
    INSTR_WIDTH
) pm (
    .addr (PC_count),
    .instr(instr   )
);

// -- reg file
logic wr_res;
logic [1:0] we;
logic [1:0][REG_ADDR_WIDTH-1:0] wr_addr;
logic [BUS_WIDTH-1:0] rd_data_a, rd_data_b;

always_ff @(posedge clk) 
begin
    we      <= {we[0], wr_res};
    wr_addr <= {wr_addr[0], instr[7:6]};
end

register_file #(
    BUS_WIDTH,
    3
) rf (
	.clk      (clk       ),  
    .we       (we[1]     ),
 	.wr_addr  (wr_addr[1]),
	.wr_data  (ALU_result),
 	.rd_addr_a(instr[4:3]), 
    .rd_addr_b(instr[1:0]),
 	.rd_data_a(rd_data_a ), 
    .rd_data_b(rd_data_b )
);

// -- decoder
logic ALU_add, ALU_load, PC_wait;
logic [4:0] reg_en; 

instruction_decoder #(
    OPCODE_WIDTH
) id (
    .opcode    (instr[11:9]),                  
    .ALU_add   (ALU_add    ), 
    .PC_wait   (PC_wait    ),            
    .ALU_load  (ALU_load   ),            
    .wr_res    (wr_res     ),         
    .ALU_reg_en(reg_en     )
);

// -- ALU
logic [BUS_WIDTH-1:0] ALU_result;
logic [BUS_WIDTH-1:0] ALU_imm;
logic [4:0]           ALU_reg_en_p; 
logic                 ALU_add_p, ALU_load_p;

always_ff @(posedge clk) begin
    ALU_imm      <= instr[7:0];
    ALU_load_p   <= ALU_load;
    ALU_add_p    <= ALU_add;
    ALU_reg_en_p <= reg_en;
end

ALU_v2 #(
    BUS_WIDTH
) alu (
    .clk   (clk         ),
    .sw    (sw[1]       ),
    .imm   (ALU_imm     ),
    .data_a(rd_data_a   ),
    .data_b(rd_data_b   ),   
    .reg_en(ALU_reg_en_p),
    .add   (ALU_add_p   ),
    .load  (ALU_load_p  ),
    .result(ALU_result  )
);    

assign out_port = ALU_result;

endmodule

simulation/v6/CPU/mux_21.vcd
$date
	Mon Apr 24 05:01:23 2023
$end
$version
	Icarus Verilog
$end
$timescale
	1ps
$end
$scope module CPU $end
$scope module PC_en_mux $end
$var wire 1 ! a $end
$var wire 1 " b $end
$var wire 1 # s $end
$var wire 1 $ out $end
$upscope $end
$upscope $end
$scope module CPU $end
$scope module alu $end
$scope module e_add_mux $end
$var wire 8 % a [7:0] $end
$var wire 1 & s $end
$var wire 8 ' out [7:0] $end
$var wire 8 ( b [7:0] $end
$upscope $end
$upscope $end
$upscope $end
$scope module CPU $end
$scope module alu $end
$scope module op_e_mux $end
$var wire 8 ) a [7:0] $end
$var wire 8 * b [7:0] $end
$var wire 1 + s $end
$var wire 8 , out [7:0] $end
$upscope $end
$upscope $end
$upscope $end
$scope module CPU $end
$scope module alu $end
$scope module coeff_mux $end
$var wire 8 - a [7:0] $end
$var wire 8 . b [7:0] $end
$var wire 1 + s $end
$var wire 8 / out [7:0] $end
$upscope $end
$upscope $end
$upscope $end
$scope module CPU $end
$scope module alu $end
$scope module am1 $end
$scope module m0 $end
$var wire 8 0 a_x [7:0] $end
$var wire 8 1 a_y [7:0] $end
$var wire 8 2 b_x [7:0] $end
$var wire 8 3 b_y [7:0] $end
$var wire 8 4 out_y [7:0] $end
$var wire 8 5 out_x [7:0] $end
$var reg 16 6 result_a [15:0] $end
$var reg 16 7 result_b [15:0] $end
$upscope $end
$upscope $end
$upscope $end
$upscope $end
$scope module CPU $end
$scope module alu $end
$scope module am1 $end
$var wire 1 8 a_en $end
$var wire 1 9 b_en $end
$var wire 1 : c_en $end
$var wire 1 ; clk $end
$var wire 1 < d_en $end
$var wire 8 = mult_b [7:0] $end
$var wire 8 > mult_a [7:0] $end
$var wire 8 ? data_b [7:0] $end
$var wire 8 @ data_a [7:0] $end
$var wire 8 A coeff [7:0] $end
$var reg 8 B op_a_reg [7:0] $end
$var reg 8 C op_b_reg [7:0] $end
$var reg 8 D op_c_reg [7:0] $end
$var reg 8 E op_d_reg [7:0] $end
$scope module m0 $end
$upscope $end
$upscope $end
$upscope $end
$upscope $end
$scope module CPU $end
$scope module alu $end
$scope module a0 $end
$var wire 8 F out [7:0] $end
$var wire 8 G b [7:0] $end
$var wire 8 H a [7:0] $end
$var reg 9 I add_out [8:0] $end
$upscope $end
$upscope $end
$upscope $end
$scope module CPU $end
$scope module alu $end
$scope module a1 $end
$var wire 8 J a [7:0] $end
$var wire 8 K b [7:0] $end
$var wire 8 L out [7:0] $end
$var reg 9 M add_out [8:0] $end
$upscope $end
$upscope $end
$upscope $end
$scope module CPU $end
$var wire 1 N PC_en $end
$var wire 1 ; clk $end
$var wire 8 O in_port [7:0] $end
$var wire 1 P n_reset $end
$var wire 8 Q out_port [7:0] $end
$var wire 1 ! pattern_match $end
$var wire 1 " ready_in $end
$var wire 1 R wr_res $end
$var wire 5 S reg_en [4:0] $end
$var wire 8 T rd_data_b [7:0] $end
$var wire 8 U rd_data_a [7:0] $end
$var wire 12 V instr [11:0] $end
$var wire 1 W PC_wait $end
$var wire 4 X PC_count [3:0] $end
$var wire 1 $ PC_comparator $end
$var wire 8 Y ALU_result [7:0] $end
$var wire 1 Z ALU_load $end
$var wire 1 [ ALU_add $end
$var reg 1 + ALU_add_p $end
$var reg 8 \ ALU_imm [7:0] $end
$var reg 1 & ALU_load_p $end
$var reg 5 ] ALU_reg_en_p [4:0] $end
$var reg 1 ^ ready_in_p $end
$var reg 16 _ sw [15:0] $end
$var reg 2 ` we [1:0] $end
$var reg 4 a wr_addr [3:0] $end
$scope module PC_en_mux $end
$upscope $end
$scope module alu $end
$var wire 1 + add $end
$var wire 1 ; clk $end
$var wire 8 b imm [7:0] $end
$var wire 1 & load $end
$var wire 5 c reg_en [4:0] $end
$var wire 8 d sw [7:0] $end
$var wire 8 e result [7:0] $end
$var wire 8 f op_e [7:0] $end
$var wire 8 g mult_b [7:0] $end
$var wire 8 h mult_a [7:0] $end
$var wire 8 i e_add [7:0] $end
$var wire 8 j data_b [7:0] $end
$var wire 8 k data_a [7:0] $end
$var wire 8 l coeff [7:0] $end
$var wire 8 m add_a [7:0] $end
$var reg 8 n op_e_reg [7:0] $end
$scope module a0 $end
$upscope $end
$scope module a1 $end
$upscope $end
$scope module am1 $end
$scope module m0 $end
$upscope $end
$upscope $end
$scope module coeff_mux $end
$upscope $end
$scope module e_add_mux $end
$upscope $end
$scope module op_e_mux $end
$upscope $end
$upscope $end
$scope module id $end
$var wire 3 o opcode [2:0] $end
$var reg 1 [ ALU_add $end
$var reg 1 Z ALU_load $end
$var reg 5 p ALU_reg_en [4:0] $end
$var reg 1 W PC_wait $end
$var reg 1 R wr_res $end
$upscope $end
$scope module pc $end
$var wire 1 ; clk $end
$var wire 1 N en $end
$var wire 1 P n_reset $end
$var reg 4 q count [3:0] $end
$upscope $end
$scope module pm $end
$var wire 4 r addr [3:0] $end
$var reg 12 s instr [11:0] $end
$upscope $end
$scope module rf $end
$var wire 1 ; clk $end
$var wire 2 t rd_addr_a [1:0] $end
$var wire 2 u rd_addr_b [1:0] $end
$var wire 1 v we $end
$var wire 2 w wr_addr [1:0] $end
$var wire 8 x wr_data [7:0] $end
$var wire 8 y rd_data_b [7:0] $end
$var wire 8 z rd_data_a [7:0] $end
$scope module sr0 $end
$var wire 1 ; clk $end
$var wire 2 { rd_addr_a [1:0] $end
$var wire 2 | rd_addr_b [1:0] $end
$var wire 1 v we $end
$var wire 2 } wr_addr [1:0] $end
$var wire 8 ~ wr_data [7:0] $end
$var reg 8 !" rd_data_a [7:0] $end
$var reg 8 "" rd_data_b [7:0] $end
$scope begin $ivl_for_loop0 $end
$var integer 32 #" i [31:0] $end
$upscope $end
$upscope $end
$upscope $end
$upscope $end
$enddefinitions $end
#0
$dumpvars
b11 #"
bx ""
bx !"
bx ~
bx }
b1 |
b1 {
bx z
bx y
bx x
bx w
xv
b1 u
b1 t
b111000001001 s
b0 r
b0 q
b0 p
b111 o
bx n
bx m
bx l
bx k
bx j
bx i
bx h
bx g
bx f
bx e
bx d
b0 c
bx b
bx a
bx0 `
bx00000000 _
0^
b0 ]
bx \
0[
0Z
bx Y
b0 X
1W
b111000001001 V
bx U
bx T
b0 S
0R
bx Q
0P
b0 O
0N
bx M
bx L
bx K
bx J
bx I
bx H
bx G
bx F
bx E
bx D
bx C
bx B
bx A
bx @
bx ?
bx >
bx =
0<
1;
0:
09
08
bx 7
bx 6
bx 5
bx 4
bx 3
bx 2
bx 1
bx 0
bx /
bx .
b0 -
bx ,
0+
bx *
bx )
bx (
bx '
0&
bx %
0$
1#
0"
0!
$end
#5000
0;
#10000
b1001 /
b1001 A
b1001 l
b1001 ,
b1001 f
0v
b0 %
b0 d
b0 '
b0 )
b0 i
b1001 *
b1001 .
b1001 \
b1001 b
bx00 a
b0 `
b0 _
b0 (
b0 @
b0 U
b0 k
b0 z
b0 !"
b0 ?
b0 T
b0 j
b0 y
b0 ""
1;
#15000
0;
#20000
1P
b0 w
b0 }
b0 a
1;
#25000
0;
#30000
1;
#35000
0;
#40000
1;
#45000
0;
#50000
1;
#55000
0;
#60000
1;
#65000
0;
#70000
1;
#75000
0;
#80000
1;
#85000
0;
#90000
1;
#95000
0;
#100000
1;
#105000
0;
#110000
1;
#115000
0;
#120000
1N
1$
1!
1"
b1011011 O
1;
#125000
0;
#130000
0$
0"
b11111 S
b11111 p
1R
0W
1[
1Z
0!
b110 o
b0 u
b0 |
b0 t
b0 {
0#
b110000000000 V
b110000000000 s
b1011011 _
1^
b1 X
b1 q
b1 r
1;
#135000
0;
#140000
0N
b0 S
b0 p
0R
1W
0[
0Z
b1011011 '
b1011011 )
b1011011 i
b111 o
b1 u
b1 |
b1 t
b1 {
1#
b1011011 %
b1011011 d
18
19
1:
1<
b0 /
b0 A
b0 l
b1011011 ,
b1011011 f
b111000001001 V
b111000001001 s
0^
b101101101011011 _
b1 `
b11111 ]
b11111 c
1+
1&
b0 *
b0 .
b0 \
b0 b
b10 X
b10 q
b10 r
1;
#145000
0;
#150000
b1011011 Q
b1011011 L
b1011011 Y
b1011011 e
b1011011 x
b1011011 ~
b1011011 M
b0 F
b0 J
b0 m
b0 I
b0 4
b0 =
b0 G
b0 g
b0 5
b0 >
b0 H
b0 h
08
09
0:
0<
b1001 /
b1001 A
b1001 l
b1001 ,
b1001 f
b0 '
b0 )
b0 i
1v
b0 7
b0 6
b0 ]
b0 c
0+
0&
b1001 *
b1001 .
b1001 \
b1001 b
b10 `
b1011011 K
b1011011 n
b0 3
b0 E
b0 1
b0 D
b0 2
b0 C
b0 0
b0 B
1;
#155000
0;
#160000
0v
b0 `
1;
#165000
0;
#170000
1;
#175000
0;
#180000
1;
#185000
0;
#190000
1N
1$
1!
1"
b1111100 O
1;
#195000
0;
#200000
0$
0"
b11111 S
b11111 p
1R
0W
1[
1Z
0!
b110 o
b0 u
b0 |
b0 t
b0 {
0#
b110001000000 V
b110001000000 s
1^
b101101101111100 _
b11 X
b11 q
b11 r
1;
#205000
0;
#210000
b10 S
b10 p
0R
0[
0Z
b11 o
18
19
1:
1<
b0 /
b0 A
b0 l
b1111100 ,
b1111100 f
b1111100 %
b1111100 d
b1111100 '
b1111100 )
b1111100 i
b11001100000 V
b11001100000 s
b11111 ]
b11111 c
1+
1&
b1000000 *
b1000000 .
b1000000 \
b1000000 b
b1 a
b1 `
b111110001111100 _
0^
b1011011 (
b1011011 @
b1011011 U
b1011011 k
b1011011 z
b1011011 !"
b1011011 ?
b1011011 T
b1011011 j
b1011011 y
b1011011 ""
b100 X
b100 q
b100 r
1;
#215000
0;
#220000
b1000 S
b1000 p
b1111100 Q
b1111100 L
b1111100 Y
b1111100 e
b1111100 x
b1111100 ~
b100 o
b1111100 M
b1 w
b1 }
1v
08
0:
0<
b1100000 /
b1100000 A
b1100000 l
b1100000 ,
b1100000 f
b1011011 '
b1011011 )
b1011011 i
b100001000000 V
b100001000000 s
b1011011 0
b1011011 B
b1011011 1
b1011011 D
b1111100 K
b1111100 n
b101 a
b10 `
b10 ]
b10 c
0+
0&
b1100000 *
b1100000 .
b1100000 \
b1100000 b
b101 X
b101 q
b101 r
1;
#225000
0;
#230000
b11000000 Q
b11000000 L
b11000000 Y
b11000000 e
b11000000 x
b11000000 ~
b11000000 M
b1000100 F
b1000100 J
b1000100 m
b1000100 I
b10000 S
b10000 p
b1000100 5
b1000100 >
b1000100 H
b1000100 h
b101 o
b10 t
b10 {
09
1<
b1000000 /
b1000000 A
b1000000 l
b1000000 ,
b1000000 f
0v
b10001000100000 6
b101000010100 V
b101000010100 s
b1000 ]
b1000 c
b1000000 *
b1000000 .
b1000000 \
b1000000 b
b0 `
b1100000 2
b1100000 C
b110 X
b110 q
b110 r
1;
#235000
0;
#240000
b11101101 Q
b11101101 L
b11101101 Y
b11101101 e
b11101101 x
b11101101 ~
b11101101 M
b1110001 F
b1110001 J
b1110001 m
b1110001 I
b101 S
b101 p
1R
b101101 4
b101101 =
b101101 G
b101101 g
b1 o
b1 u
b1 |
b0 t
b0 {
b0 '
b0 )
b0 i
b1011011000000 7
0<
b10100 /
b10100 A
b10100 l
b10100 ,
b10100 f
b1010000001 V
b1010000001 s
b0 (
b0 @
b0 U
b0 k
b0 z
b0 !"
b1000000 3
b1000000 E
b100 a
b10000 ]
b10000 c
b10100 *
b10100 .
b10100 \
b10100 b
b111 X
b111 q
b111 r
1;
#245000
0;
#250000
b10 S
b10 p
0R
b10000101 Q
b10000101 L
b10000101 Y
b10000101 e
b10000101 x
b10000101 ~
b11 o
b0 u
b0 |
18
1:
b10000001 /
b10000001 A
b10000001 l
b10000001 ,
b10000001 f
b0 w
b0 }
b10000101 M
b1011011 '
b1011011 )
b1011011 i
b11011000000 V
b11011000000 s
b101 ]
b101 c
b10000001 *
b10000001 .
b10000001 \
b10000001 b
b10 a
b1 `
b10100 K
b10100 n
b1011011 (
b1011011 @
b1011011 U
b1011011 k
b1011011 z
b1011011 !"
b1111100 ?
b1111100 T
b1111100 j
b1111100 y
b1111100 ""
b1000 X
b1000 q
b1000 r
1;
#255000
0;
#260000
b10010110 Q
b10010110 L
b10010110 Y
b10010110 e
b10010110 x
b10010110 ~
b110010110 M
b10000010 F
b10000010 J
b10000010 m
b10000010 I
b1000 S
b1000 p
b111110 4
b111110 =
b111110 G
b111110 g
b100 o
b1111100000000 7
b10 w
b10 }
1v
08
19
0:
b11000000 /
b11000000 A
b11000000 l
b11000000 ,
b11000000 f
b100001100000 V
b100001100000 s
b1011011 ?
b1011011 T
b1011011 j
b1011011 y
b1011011 ""
b1111100 1
b1111100 D
b1011 a
b10 `
b10 ]
b10 c
b11000000 *
b11000000 .
b11000000 \
b11000000 b
b1001 X
b1001 q
b1001 r
1;
#265000
0;
#270000
b100100 Q
b100100 L
b100100 Y
b100100 e
b100100 x
b100100 ~
b100100 M
b10000 F
b10000 J
b10000 m
b10000 I
b10000 S
b10000 p
b11010010 5
b11010010 >
b11010010 H
b11010010 h
b101 o
b1 t
b1 {
1#
09
1<
b1100000 /
b1100000 A
b1100000 l
b1100000 ,
b1100000 f
b11 w
b11 }
0v
b1110100101000000 6
b101011101100 V
b101011101100 s
b1000 ]
b1000 c
b1100000 *
b1100000 .
b1100000 \
b1100000 b
b1101 a
b0 `
b11000000 2
b11000000 C
b1010 X
b1010 q
b1010 r
1;
#275000
0;
#280000
b1000011 Q
b1000011 L
b1000011 Y
b1000011 e
b1000011 x
b1000011 ~
b1000011 M
b101111 F
b101111 J
b101111 m
b101111 I
b101 S
b101 p
1R
b1011101 4
b1011101 =
b1011101 G
b1011101 g
b1 o
b1 u
b1 |
b0 t
b0 {
0#
b1111100 '
b1111100 )
b1111100 i
b10111010000000 7
b1 w
b1 }
0<
b11101100 /
b11101100 A
b11101100 l
b11101100 ,
b11101100 f
b1001000001 V
b1001000001 s
b1111100 (
b1111100 @
b1111100 U
b1111100 k
b1111100 z
b1111100 !"
b1100000 3
b1100000 E
b111 a
b10000 ]
b10000 c
b11101100 *
b11101100 .
b11101100 \
b11101100 b
b1011 X
b1011 q
b1011 r
1;
#285000
0;
#290000
b11111 S
b11111 p
1[
b11011 Q
b11011 L
b11011 Y
b11011 e
b11011 x
b11011 ~
b0 o
b0 u
b0 |
b10 t
b10 {
18
1:
b1000001 /
b1000001 A
b1000001 l
b1000001 ,
b1000001 f
b11 w
b11 }
b11011 M
b1011011 '
b1011011 )
b1011011 i
b10000 V
b10000 s
b101 ]
b101 c
b1000001 *
b1000001 .
b1000001 \
b1000001 b
b1101 a
b1 `
b11101100 K
b11101100 n
b1011011 (
b1011011 @
b1011011 U
b1011011 k
b1011011 z
b1011011 !"
b1111100 ?
b1111100 T
b1111100 j
b1111100 y
b1111100 ""
b1100 X
b1100 q
b1100 r
1;
#295000
0;
#300000
0N
b0 S
b0 p
0R
1W
0[
b111 o
b1 u
b1 |
b0 t
b0 {
b10010110 '
b10010110 )
b10010110 i
b1 w
b1 }
1v
19
1<
b0 /
b0 A
b0 l
b10010110 ,
b10010110 f
b111000000001 V
b111000000001 s
b10010110 (
b10010110 @
b10010110 U
b10010110 k
b10010110 z
b10010110 !"
b1011011 ?
b1011011 T
b1011011 j
b1011011 y
b1011011 ""
b100 a
b11 `
b11111 ]
b11111 c
1+
b10000 *
b10000 .
b10000 \
b10000 b
b1101 X
b1101 q
b1101 r
1;
#305000
0;
#310000
b0 F
b0 J
b0 m
b0 I
b10010110 Q
b10010110 L
b10010110 Y
b10010110 e
b10010110 x
b10010110 ~
b0 4
b0 =
b0 G
b0 g
b0 5
b0 >
b0 H
b0 h
08
09
0:
0<
b1 /
b1 A
b1 l
b1 ,
b1 f
b0 w
b0 }
b110010110 M
b0 7
b0 6
b1011011 '
b1011011 )
b1011011 i
b0 ]
b0 c
0+
b1 *
b1 .
b1 \
b1 b
b0 a
b10 `
b10010110 K
b10010110 n
b0 3
b0 E
b1011011 1
b1011011 D
b0 2
b0 C
b10010110 0
b10010110 B
b1011011 (
b1011011 @
b1011011 U
b1011011 k
b1011011 z
b1011011 !"
b1111100 ?
b1111100 T
b1111100 j
b1111100 y
b1111100 ""
1;
#315000
0;
#320000
1N
1!
1$
1"
0v
b11011 ?
b11011 T
b11011 j
b11011 y
b11011 ""
b0 `
1;
#325000
0;
#330000
b11111 S
b11111 p
1R
0W
1[
0$
0!
b0 o
b0 u
b0 |
b1 t
b1 {
1#
b10010110 '
b10010110 )
b10010110 i
b1000 V
b1000 s
1^
b10010110 (
b10010110 @
b10010110 U
b10010110 k
b10010110 z
b10010110 !"
b1110 X
b1110 q
b1110 r
1;
#335000
0;
